Workbook

Sheet Sheet1
I1: 2025
A2: Employee | B2: Grant | C2: Req'd Grant Hours/Month | D2: Actual Rate | E2: 2025 Annual/2080 | F2: Grant Rate | G2: Rate Burdened? | H2: Fringe | I2: January | J2: February | K2: March | L2: April | M2: May | N2: June | O2: July | P2: August | Q2: September | R2: October | S2: November | T2: December | U2: Allocation w/Actual Burdened | V2: Budget Amount | W2: Budget - Actual
A3: Daniel Longo | B3: Rising Tides | C3: 81.87 | D3: =90000/2080 -> 43.269231 | E3: =91374.4/2080 -> 43.93 | F3: 43.26 | G3: No | H3: 0.3 | I3: 65 | J3: 74 | K3: 82 | L3: 80 | M3: 86 | N3: 80 | O3: 110 | P3: 98 | Q3: 88 | R3: 153 | S3: 108 | T3: 91 | U3: =(E3*1.29)*(SUM(I3:T3)) -> 63186.715 | V3: =F3*(C3*12) -> 42500.354 | W3: =V3-U3 -> -20686.361
A4: Daniel Longo | B4: Hybrid | C4: =(4250/24)/2 -> 88.541667 | D4: =90000/2080 -> 43.269231 | E4: =91374.4/2080 -> 43.93 | F4: 50 | I4: 63 | J4: 28 | K4: 43 | L4: 34 | M4: 45 | N4: 47 | O4: 68 | P4: 62 | Q4: 88 | R4: 31 | S4: 52 | T4: 93 | U4: =(E4*1.29)*(SUM(I4:T4)) -> 37061.984 | V4: =F4*(C4*12) -> 53125 | W4: =V4-U4 -> 16063.016
A5: Daniel Longo | B5: Digital Engineering | D5: =90000/2080 -> 43.269231 | E5: =91374.4/2080 -> 43.93 | I5: 56 | J5: 58 | K5: 43 | L5: 61 | M5: 49 | N5: 41 | O5: 8 | P5: 0 | R5: 0 | S5: 0 | T5: 0 | U5: =(E5*1.29)*(SUM(I5:T5)) -> 17907.625 | V5: =F5*(C5*12) -> 0 | W5: =V5-U5 -> -17907.625
A6: Brittany Engel | B6: Drive AM | C6: 177 | D6: =77000/2080 -> 37.019231 | E6: =78307.73/2080 -> 37.647947 | F6: 63.83 | G6: No | I6: 100 | J6: 80 | K6: 100 | L6: 100 | M6: 100 | N6: 100 | O6: 100 | P6: 100 | Q6: 100 | R6: 100 | S6: 100 | T6: 100 | U6: =(E6*1.29)*(SUM(I6:T6)) -> 57307.705 | V6: =F6*(C6*12) -> 135574.92 | W6: =V6-U6 -> 78267.215
A7: Brittany Engel | B7: LTM | C7: 83.4 | D7: =77000/2080 -> 37.019231 | E7: =78307.73/2080 -> 37.647947 | F7: 52.55 | G7: Yes | I7: 80 | J7: 80 | K7: 80 | L7: 80 | M7: 56 | N7: 92 | O7: 80 | P7: 80 | Q7: 80 | R7: 80 | S7: 80 | T7: 80 | U7: =(E7*1.29)*(SUM(I7:T7)) -> 46040.427 | V7: =F7*(C7*12) -> 52592.04 | W7: =V7-U7 -> 6551.6125
A8: Dylan Negro | B8: Xjet | D8: =75000/2080 -> 36.057692 | E8: =76312.09/2080 -> 36.688505 | I8: 68 | J8: 38 | K8: 46 | L8: 49 | M8: 28 | N8: 68 | O8: 56 | P8: 42 | Q8: 21 | R8: 24 | S8: 0 | T8: 29 | U8: =(E8*1.29)*(SUM(I8:T8)) -> 22196.912 | V8: =F8*(C8*12) -> 0 | W8: =V8-U8 -> -22196.912
A9: Dylan Negro | B9: Rising Tides | C9: 34.67 | D9: =75000/2080 -> 36.057692 | E9: =76312.09/2080 -> 36.688505 | F9: 36.05 | G9: No | H9: 0.3 | I9: 20 | J9: 42 | K9: 42 | L9: 41 | M9: 68 | N9: 36 | O9: 64 | P9: 46 | Q9: 74 | R9: 76 | S9: 80 | T9: 75 | U9: =(E9*1.29)*(SUM(I9:T9)) -> 31425.906 | V9: =F9*(C9*12) -> 14998.242 | W9: =V9-U9 -> -16427.664
A10: Dylan Negro | B10: Drive AM | C10: 88 | D10: =75000/2080 -> 36.057692 | E10: =76312.09/2080 -> 36.688505 | F10: 63.83 | G10: Yes | I10: 88 | J10: 80 | K10: 80 | L10: 80 | M10: 80 | N10: 80 | O10: 80 | P10: 80 | Q10: 81 | R10: 84 | S10: 80 | T10: 80 | U10: =(E10*1.29)*(SUM(I10:T10)) -> 46050.311 | V10: =F10*(C10*12) -> 67404.48 | W10: =V10-U10 -> 21354.169
A11: Dean Jaric | B11: Drive AM | C11: 88 | D11: =77500/2080 -> 37.259615 | E11: =78492.76/2080 -> 37.736904 | F11: 63.83 | G11: Yes | I11: 59 | O11: 48 | U11: =(E11*1.29)*(SUM(I11:T11)) -> 5208.8248 | V11: =F11*(C11*12) -> 67404.48
A12: Dean Jaric | B12: Hybrid | C12: =C4 -> 88.541667 | D12: =77500/2080 -> 37.259615 | E12: =78492.76/2080 -> 37.736904 | F12: 50 | I12: 16 | O12: 15 | U12: =(E12*1.29)*(SUM(I12:T12)) -> 1509.0988 | V12: =F12*(C12*12) -> 53125
A13: Dean Jaric | B13: YBI | D13: =77500/2080 -> 37.259615 | E13: =78492.76/2080 -> 37.736904 | I13: 108 | O13: 121 | U13: =(E13*1.29)*(SUM(I13:T13)) -> 11147.859 | V13: =F13*(C13*12) -> 0
A14: Stephanie Gaffney | B14: Rising Tides | C14: 36.35 | D14: =155000/2080 -> 74.519231 | F14: 74.51 | G14: No | H14: 0.3 | U14: =(E14*1.29)*(SUM(I14:T14)) -> 0 | V14: =F14*(C14*12) -> 32501.262
A15: Stephanie Gaffney | B15: LTM | C15: 38.4 | D15: =155000/2080 -> 74.519231 | F15: 86.56 | G15: Yes | U15: =(E15*1.29)*(SUM(I15:T15)) -> 0 | V15: =F15*(C15*12) -> 39886.848
A16: Stephanie Gaffney | B16: Drive AM | C16: 14 | D16: =155000/2080 -> 74.519231 | F16: 92.08 | G16: Yes | U16: =(E16*1.29)*(SUM(I16:T16)) -> 0 | V16: =F16*(C16*12) -> 15469.44
A17: Stephanie Gaffney | B17: Rising Tides | C17: 36.35 | D17: =185000/2080 -> 88.942308 | F17: 74.51 | G17: No | H17: 0.3 | U17: =(E17*1.29)*(SUM(I17:T17)) -> 0 | V17: =F17*(C17*12) -> 32501.262
A18: Stephanie Gaffney | B18: LTM | C18: 38.4 | D18: =185000/2080 -> 88.942308 | F18: 86.56 | G18: Yes | U18: =(E18*1.29)*(SUM(I18:T18)) -> 0 | V18: =F18*(C18*12) -> 39886.848
A19: Stephanie Gaffney | B19: Drive AM | C19: 14 | D19: =185000/2080 -> 88.942308 | F19: 92.08 | G19: Yes | U19: =(E19*1.29)*(SUM(I19:T19)) -> 0 | V19: =F19*(C19*12) -> 15469.44
A20: Jessica Sprowl | B20: Rising Tides | C20: 33.43 | D20: =70000/2080 -> 33.653846 | E20: =71317.16/2080 -> 34.287096 | F20: 33.65 | G20: No | H20: 0.3 | I20: 7 | J20: 19 | K20: 19 | L20: 27 | M20: 28 | N20: =175/7 -> 25 | O20: =175/7 -> 25 | P20: =175/7 -> 25 | Q20: =175/7 -> 25 | R20: =175/7 -> 25 | S20: =175/7 -> 25 | T20: =175/7 -> 25 | U20: =(E20*1.29)*(SUM(I20:T20)) -> 12163.347 | V20: =F20*(C20*12) -> 13499.034 | W20: =V20-U20 -> 1335.6866
A21: Rory Kale | B21: Drive AM | C21: 44 | E21: =59850/2080 -> 28.774038 | F21: 34.53 | G21: Yes | I21: 42 | J21: 37 | K21: 44 | L21: 50 | M21: 50 | N21: 0 | O21: 0 | P21: 0 | Q21: 0 | R21: 0 | S21: 0 | T21: 0 | U21: =(E21*1.29)*(SUM(I21:T21)) -> 8277.4276 | V21: =F21*(C21*12) -> 18231.84 | W21: =V21-U21 -> 9954.4124
A22: Rory Kale | B22: Rising Tides | C22: 62.14 | D22: =52000/2080 -> 25 | E22: =59850/2080 -> 28.774038 | F22: 25.48 | G22: No | H22: 0.3 | I22: 8 | J22: 4 | K22: 4 | L22: 7 | M22: 0 | N22: 13 | O22: 4 | Q22: 0 | R22: 0 | S22: 0 | T22: 0 | U22: =(E22*1.29)*(SUM(I22:T22)) -> 1484.7404 | V22: =F22*(C22*12) -> 18999.926 | W22: =V22-U22 -> 17515.186

Sheet Time Breakdown
A1: 2025 | B1: Adj-AAMEN | C1: Adj-AM Other | D1: Adj-Apex | E1: Adj-CDBG | F1: Adj-Dig Eng M7 | G1: Adj-DLA | H1: Adj-Drive AM | I1: Adj-ESP | J1: Adj-Fundraising | K1: Adj-Hub | L1: Adj-Hybrid | M1: Adj-IIOT | N1: Adj-LTM | O1: Adj-MBAC | P1: Adj-NavAir | Q1: Adj-Rising Tides | R1: Adj-VGV | S1: Adj-Xjet | T1: Adj-Youth | U1: Adj-YBI | V1: Total
A2: Anderson | B2: =SUMIFS('Hours Log'!AD$2:AD$323,'Hours Log'!$A$2:$A$323,"="&'Time Breakdown'!$A2,'Hours Log'!$C$2:$C$323,"="&'Time Breakdown'!$A$1) -> 0 | C2: =SUMIFS('Hours Log'!AE$2:AE$323,'Hours Log'!$A$2:$A$323,"="&'Time Breakdown'!$A2,'Hours Log'!$C$2:$C$323,"="&'Time Breakdown'!$A$1) -> 0 | D2: =SUMIFS('Hours Log'!AF$2:AF$323,'Hours Log'!$A$2:$A$323,"="&'Time Breakdown'!$A2,'Hours Log'!$C$2:$C$323,"="&'Time Breakdown'!$A$1) -> 0 | E2: =SUMIFS('Hours Log'!AG$2:AG$323,'Hours Log'!$A$2:$A$323,"="&'Time Breakdown'!$A2,'Hours Log'!$C$2:$C$323,"="&'Time Breakdown'!$A$1) -> 0 | F2: =SUMIFS('Hours Log'!AH$2:AH$323,'Hours Log'!$A$2:$A$323,"="&'Time Breakdown'!$A2,'Hours Log'!$C$2:$C$323,"="&'Time Breakdown'!$A$1) -> 0 | G2: =SUMIFS('Hours Log'!AI$2:AI$323,'Hours Log'!$A$2:$A$323,"="&'Time Breakdown'!$A2,'Hours Log'!$C$2:$C$323,"="&'Time Breakdown'!$A$1) -> 0 | H2: =SUMIFS('Hours Log'!AJ$2:AJ$323,'Hours Log'!$A$2:$A$323,"="&'Time Breakdown'!$A2,'Hours Log'!$C$2:$C$323,"="&'Time Breakdown'!$A$1) -> 0 | I2: =SUMIFS('Hours Log'!AK$2:AK$323,'Hours Log'!$A$2:$A$323,"="&'Time Breakdown'!$A2,'Hours Log'!$C$2:$C$323,"="&'Time Breakdown'!$A$1) -> 0 | ... U2: =SUMIFS('Hours Log'!AW$2:AW$323,'Hours Log'!$A$2:$A$323,"="&'Time Breakdown'!$A2,'Hours Log'!$C$2:$C$323,"="&'Time Breakdown'!$A$1) -> 0 | V2: =SUM(B2:U2) -> 100
A3: Baxter | B3: =SUMIFS('Hours Log'!AD$2:AD$323,'Hours Log'!$A$2:$A$323,"="&'Time Breakdown'!$A3,'Hours Log'!$C$2:$C$323,"="&'Time Breakdown'!$A$1) -> 0 | C3: =SUMIFS('Hours Log'!AE$2:AE$323,'Hours Log'!$A$2:$A$323,"="&'Time Breakdown'!$A3,'Hours Log'!$C$2:$C$323,"="&'Time Breakdown'!$A$1) -> 0 | D3: =SUMIFS('Hours Log'!AF$2:AF$323,'Hours Log'!$A$2:$A$323,"="&'Time Breakdown'!$A3,'Hours Log'!$C$2:$C$323,"="&'Time Breakdown'!$A$1) -> 0 | E3: =SUMIFS('Hours Log'!AG$2:AG$323,'Hours Log'!$A$2:$A$323,"="&'Time Breakdown'!$A3,'Hours Log'!$C$2:$C$323,"="&'Time Breakdown'!$A$1) -> 0 | F3: =SUMIFS('Hours Log'!AH$2:AH$323,'Hours Log'!$A$2:$A$323,"="&'Time Breakdown'!$A3,'Hours Log'!$C$2:$C$323,"="&'Time Breakdown'!$A$1) -> 0 | G3: =SUMIFS('Hours Log'!AI$2:AI$323,'Hours Log'!$A$2:$A$323,"="&'Time Breakdown'!$A3,'Hours Log'!$C$2:$C$323,"="&'Time Breakdown'!$A$1) -> 0 | H3: =SUMIFS('Hours Log'!AJ$2:AJ$323,'Hours Log'!$A$2:$A$323,"="&'Time Breakdown'!$A3,'Hours Log'!$C$2:$C$323,"="&'Time Breakdown'!$A$1) -> 0 | I3: =SUMIFS('Hours Log'!AK$2:AK$323,'Hours Log'!$A$2:$A$323,"="&'Time Breakdown'!$A3,'Hours Log'!$C$2:$C$323,"="&'Time Breakdown'!$A$1) -> 100 | ... U3: =SUMIFS('Hours Log'!AW$2:AW$323,'Hours Log'!$A$2:$A$323,"="&'Time Breakdown'!$A3,'Hours Log'!$C$2:$C$323,"="&'Time Breakdown'!$A$1) -> 0 | V3: =SUM(B3:U3) -> 100
A4: Bixel | B4: =SUMIFS('Hours Log'!AD$2:AD$323,'Hours Log'!$A$2:$A$323,"="&'Time Breakdown'!$A4,'Hours Log'!$C$2:$C$323,"="&'Time Breakdown'!$A$1) -> 0 | C4: =SUMIFS('Hours Log'!AE$2:AE$323,'Hours Log'!$A$2:$A$323,"="&'Time Breakdown'!$A4,'Hours Log'!$C$2:$C$323,"="&'Time Breakdown'!$A$1) -> 0 | D4: =SUMIFS('Hours Log'!AF$2:AF$323,'Hours Log'!$A$2:$A$323,"="&'Time Breakdown'!$A4,'Hours Log'!$C$2:$C$323,"="&'Time Breakdown'!$A$1) -> 0 | E4: =SUMIFS('Hours Log'!AG$2:AG$323,'Hours Log'!$A$2:$A$323,"="&'Time Breakdown'!$A4,'Hours Log'!$C$2:$C$323,"="&'Time Breakdown'!$A$1) -> 0 | F4: =SUMIFS('Hours Log'!AH$2:AH$323,'Hours Log'!$A$2:$A$323,"="&'Time Breakdown'!$A4,'Hours Log'!$C$2:$C$323,"="&'Time Breakdown'!$A$1) -> 0 | G4: =SUMIFS('Hours Log'!AI$2:AI$323,'Hours Log'!$A$2:$A$323,"="&'Time Breakdown'!$A4,'Hours Log'!$C$2:$C$323,"="&'Time Breakdown'!$A$1) -> 0 | H4: =SUMIFS('Hours Log'!AJ$2:AJ$323,'Hours Log'!$A$2:$A$323,"="&'Time Breakdown'!$A4,'Hours Log'!$C$2:$C$323,"="&'Time Breakdown'!$A$1) -> 0 | I4: =SUMIFS('Hours Log'!AK$2:AK$323,'Hours Log'!$A$2:$A$323,"="&'Time Breakdown'!$A4,'Hours Log'!$C$2:$C$323,"="&'Time Breakdown'!$A$1) -> 100 | ... U4: =SUMIFS('Hours Log'!AW$2:AW$323,'Hours Log'!$A$2:$A$323,"="&'Time Breakdown'!$A4,'Hours Log'!$C$2:$C$323,"="&'Time Breakdown'!$A$1) -> 0 | V4: =SUM(B4:U4) -> 100
A5: Byers | B5: =SUMIFS('Hours Log'!AD$2:AD$323,'Hours Log'!$A$2:$A$323,"="&'Time Breakdown'!$A5,'Hours Log'!$C$2:$C$323,"="&'Time Breakdown'!$A$1) -> 0 | C5: =SUMIFS('Hours Log'!AE$2:AE$323,'Hours Log'!$A$2:$A$323,"="&'Time Breakdown'!$A5,'Hours Log'!$C$2:$C$323,"="&'Time Breakdown'!$A$1) -> 0 | D5: =SUMIFS('Hours Log'!AF$2:AF$323,'Hours Log'!$A$2:$A$323,"="&'Time Breakdown'!$A5,'Hours Log'!$C$2:$C$323,"="&'Time Breakdown'!$A$1) -> 0 | E5: =SUMIFS('Hours Log'!AG$2:AG$323,'Hours Log'!$A$2:$A$323,"="&'Time Breakdown'!$A5,'Hours Log'!$C$2:$C$323,"="&'Time Breakdown'!$A$1) -> 0 | F5: =SUMIFS('Hours Log'!AH$2:AH$323,'Hours Log'!$A$2:$A$323,"="&'Time Breakdown'!$A5,'Hours Log'!$C$2:$C$323,"="&'Time Breakdown'!$A$1) -> 0 | G5: =SUMIFS('Hours Log'!AI$2:AI$323,'Hours Log'!$A$2:$A$323,"="&'Time Breakdown'!$A5,'Hours Log'!$C$2:$C$323,"="&'Time Breakdown'!$A$1) -> 0 | H5: =SUMIFS('Hours Log'!AJ$2:AJ$323,'Hours Log'!$A$2:$A$323,"="&'Time Breakdown'!$A5,'Hours Log'!$C$2:$C$323,"="&'Time Breakdown'!$A$1) -> 0 | I5: =SUMIFS('Hours Log'!AK$2:AK$323,'Hours Log'!$A$2:$A$323,"="&'Time Breakdown'!$A5,'Hours Log'!$C$2:$C$323,"="&'Time Breakdown'!$A$1) -> 0 | ... U5: =SUMIFS('Hours Log'!AW$2:AW$323,'Hours Log'!$A$2:$A$323,"="&'Time Breakdown'!$A5,'Hours Log'!$C$2:$C$323,"="&'Time Breakdown'!$A$1) -> 0 | V5: =SUM(B5:U5) -> 100
A6: Canton | B6: =SUMIFS('Hours Log'!AD$2:AD$323,'Hours Log'!$A$2:$A$323,"="&'Time Breakdown'!$A6,'Hours Log'!$C$2:$C$323,"="&'Time Breakdown'!$A$1) -> 0 | C6: =SUMIFS('Hours Log'!AE$2:AE$323,'Hours Log'!$A$2:$A$323,"="&'Time Breakdown'!$A6,'Hours Log'!$C$2:$C$323,"="&'Time Breakdown'!$A$1) -> 0 | D6: =SUMIFS('Hours Log'!AF$2:AF$323,'Hours Log'!$A$2:$A$323,"="&'Time Breakdown'!$A6,'Hours Log'!$C$2:$C$323,"="&'Time Breakdown'!$A$1) -> 0 | E6: =SUMIFS('Hours Log'!AG$2:AG$323,'Hours Log'!$A$2:$A$323,"="&'Time Breakdown'!$A6,'Hours Log'!$C$2:$C$323,"="&'Time Breakdown'!$A$1) -> 0 | F6: =SUMIFS('Hours Log'!AH$2:AH$323,'Hours Log'!$A$2:$A$323,"="&'Time Breakdown'!$A6,'Hours Log'!$C$2:$C$323,"="&'Time Breakdown'!$A$1) -> 0 | G6: =SUMIFS('Hours Log'!AI$2:AI$323,'Hours Log'!$A$2:$A$323,"="&'Time Breakdown'!$A6,'Hours Log'!$C$2:$C$323,"="&'Time Breakdown'!$A$1) -> 0 | H6: =SUMIFS('Hours Log'!AJ$2:AJ$323,'Hours Log'!$A$2:$A$323,"="&'Time Breakdown'!$A6,'Hours Log'!$C$2:$C$323,"="&'Time Breakdown'!$A$1) -> 0 | I6: =SUMIFS('Hours Log'!AK$2:AK$323,'Hours Log'!$A$2:$A$323,"="&'Time Breakdown'!$A6,'Hours Log'!$C$2:$C$323,"="&'Time Breakdown'!$A$1) -> 100 | ... U6: =SUMIFS('Hours Log'!AW$2:AW$323,'Hours Log'!$A$2:$A$323,"="&'Time Breakdown'!$A6,'Hours Log'!$C$2:$C$323,"="&'Time Breakdown'!$A$1) -> 0 | V6: =SUM(B6:U6) -> 100
A7: Chunn | B7: =SUMIFS('Hours Log'!AD$2:AD$323,'Hours Log'!$A$2:$A$323,"="&'Time Breakdown'!$A7,'Hours Log'!$C$2:$C$323,"="&'Time Breakdown'!$A$1) -> 0 | C7: =SUMIFS('Hours Log'!AE$2:AE$323,'Hours Log'!$A$2:$A$323,"="&'Time Breakdown'!$A7,'Hours Log'!$C$2:$C$323,"="&'Time Breakdown'!$A$1) -> 0 | D7: =SUMIFS('Hours Log'!AF$2:AF$323,'Hours Log'!$A$2:$A$323,"="&'Time Breakdown'!$A7,'Hours Log'!$C$2:$C$323,"="&'Time Breakdown'!$A$1) -> 0 | E7: =SUMIFS('Hours Log'!AG$2:AG$323,'Hours Log'!$A$2:$A$323,"="&'Time Breakdown'!$A7,'Hours Log'!$C$2:$C$323,"="&'Time Breakdown'!$A$1) -> 0 | F7: =SUMIFS('Hours Log'!AH$2:AH$323,'Hours Log'!$A$2:$A$323,"="&'Time Breakdown'!$A7,'Hours Log'!$C$2:$C$323,"="&'Time Breakdown'!$A$1) -> 0 | G7: =SUMIFS('Hours Log'!AI$2:AI$323,'Hours Log'!$A$2:$A$323,"="&'Time Breakdown'!$A7,'Hours Log'!$C$2:$C$323,"="&'Time Breakdown'!$A$1) -> 0 | H7: =SUMIFS('Hours Log'!AJ$2:AJ$323,'Hours Log'!$A$2:$A$323,"="&'Time Breakdown'!$A7,'Hours Log'!$C$2:$C$323,"="&'Time Breakdown'!$A$1) -> 0 | I7: =SUMIFS('Hours Log'!AK$2:AK$323,'Hours Log'!$A$2:$A$323,"="&'Time Breakdown'!$A7,'Hours Log'!$C$2:$C$323,"="&'Time Breakdown'!$A$1) -> 100 | ... U7: =SUMIFS('Hours Log'!AW$2:AW$323,'Hours Log'!$A$2:$A$323,"="&'Time Breakdown'!$A7,'Hours Log'!$C$2:$C$323,"="&'Time Breakdown'!$A$1) -> 0 | V7: =SUM(B7:U7) -> 100
A8: Davis | B8: =SUMIFS('Hours Log'!AD$2:AD$323,'Hours Log'!$A$2:$A$323,"="&'Time Breakdown'!$A8,'Hours Log'!$C$2:$C$323,"="&'Time Breakdown'!$A$1) -> 0 | C8: =SUMIFS('Hours Log'!AE$2:AE$323,'Hours Log'!$A$2:$A$323,"="&'Time Breakdown'!$A8,'Hours Log'!$C$2:$C$323,"="&'Time Breakdown'!$A$1) -> 0 | D8: =SUMIFS('Hours Log'!AF$2:AF$323,'Hours Log'!$A$2:$A$323,"="&'Time Breakdown'!$A8,'Hours Log'!$C$2:$C$323,"="&'Time Breakdown'!$A$1) -> 0 | E8: =SUMIFS('Hours Log'!AG$2:AG$323,'Hours Log'!$A$2:$A$323,"="&'Time Breakdown'!$A8,'Hours Log'!$C$2:$C$323,"="&'Time Breakdown'!$A$1) -> 0 | F8: =SUMIFS('Hours Log'!AH$2:AH$323,'Hours Log'!$A$2:$A$323,"="&'Time Breakdown'!$A8,'Hours Log'!$C$2:$C$323,"="&'Time Breakdown'!$A$1) -> 0 | G8: =SUMIFS('Hours Log'!AI$2:AI$323,'Hours Log'!$A$2:$A$323,"="&'Time Breakdown'!$A8,'Hours Log'!$C$2:$C$323,"="&'Time Breakdown'!$A$1) -> 0 | H8: =SUMIFS('Hours Log'!AJ$2:AJ$323,'Hours Log'!$A$2:$A$323,"="&'Time Breakdown'!$A8,'Hours Log'!$C$2:$C$323,"="&'Time Breakdown'!$A$1) -> 0 | I8: =SUMIFS('Hours Log'!AK$2:AK$323,'Hours Log'!$A$2:$A$323,"="&'Time Breakdown'!$A8,'Hours Log'!$C$2:$C$323,"="&'Time Breakdown'!$A$1) -> 0 | ... U8: =SUMIFS('Hours Log'!AW$2:AW$323,'Hours Log'!$A$2:$A$323,"="&'Time Breakdown'!$A8,'Hours Log'!$C$2:$C$323,"="&'Time Breakdown'!$A$1) -> 0 | V8: =SUM(B8:U8) -> 100
A9: Dively | B9: =SUMIFS('Hours Log'!AD$2:AD$323,'Hours Log'!$A$2:$A$323,"="&'Time Breakdown'!$A9,'Hours Log'!$C$2:$C$323,"="&'Time Breakdown'!$A$1) -> 0 | C9: =SUMIFS('Hours Log'!AE$2:AE$323,'Hours Log'!$A$2:$A$323,"="&'Time Breakdown'!$A9,'Hours Log'!$C$2:$C$323,"="&'Time Breakdown'!$A$1) -> 0 | D9: =SUMIFS('Hours Log'!AF$2:AF$323,'Hours Log'!$A$2:$A$323,"="&'Time Breakdown'!$A9,'Hours Log'!$C$2:$C$323,"="&'Time Breakdown'!$A$1) -> 0 | E9: =SUMIFS('Hours Log'!AG$2:AG$323,'Hours Log'!$A$2:$A$323,"="&'Time Breakdown'!$A9,'Hours Log'!$C$2:$C$323,"="&'Time Breakdown'!$A$1) -> 0 | F9: =SUMIFS('Hours Log'!AH$2:AH$323,'Hours Log'!$A$2:$A$323,"="&'Time Breakdown'!$A9,'Hours Log'!$C$2:$C$323,"="&'Time Breakdown'!$A$1) -> 0 | G9: =SUMIFS('Hours Log'!AI$2:AI$323,'Hours Log'!$A$2:$A$323,"="&'Time Breakdown'!$A9,'Hours Log'!$C$2:$C$323,"="&'Time Breakdown'!$A$1) -> 0 | H9: =SUMIFS('Hours Log'!AJ$2:AJ$323,'Hours Log'!$A$2:$A$323,"="&'Time Breakdown'!$A9,'Hours Log'!$C$2:$C$323,"="&'Time Breakdown'!$A$1) -> 0 | I9: =SUMIFS('Hours Log'!AK$2:AK$323,'Hours Log'!$A$2:$A$323,"="&'Time Breakdown'!$A9,'Hours Log'!$C$2:$C$323,"="&'Time Breakdown'!$A$1) -> 100 | ... U9: =SUMIFS('Hours Log'!AW$2:AW$323,'Hours Log'!$A$2:$A$323,"="&'Time Breakdown'!$A9,'Hours Log'!$C$2:$C$323,"="&'Time Breakdown'!$A$1) -> 0 | V9: =SUM(B9:U9) -> 100
A10: Dwyer | B10: =SUMIFS('Hours Log'!AD$2:AD$323,'Hours Log'!$A$2:$A$323,"="&'Time Breakdown'!$A10,'Hours Log'!$C$2:$C$323,"="&'Time Breakdown'!$A$1) -> 0 | C10: =SUMIFS('Hours Log'!AE$2:AE$323,'Hours Log'!$A$2:$A$323,"="&'Time Breakdown'!$A10,'Hours Log'!$C$2:$C$323,"="&'Time Breakdown'!$A$1) -> 0 | D10: =SUMIFS('Hours Log'!AF$2:AF$323,'Hours Log'!$A$2:$A$323,"="&'Time Breakdown'!$A10,'Hours Log'!$C$2:$C$323,"="&'Time Breakdown'!$A$1) -> 0 | E10: =SUMIFS('Hours Log'!AG$2:AG$323,'Hours Log'!$A$2:$A$323,"="&'Time Breakdown'!$A10,'Hours Log'!$C$2:$C$323,"="&'Time Breakdown'!$A$1) -> 0 | F10: =SUMIFS('Hours Log'!AH$2:AH$323,'Hours Log'!$A$2:$A$323,"="&'Time Breakdown'!$A10,'Hours Log'!$C$2:$C$323,"="&'Time Breakdown'!$A$1) -> 0 | G10: =SUMIFS('Hours Log'!AI$2:AI$323,'Hours Log'!$A$2:$A$323,"="&'Time Breakdown'!$A10,'Hours Log'!$C$2:$C$323,"="&'Time Breakdown'!$A$1) -> 0 | H10: =SUMIFS('Hours Log'!AJ$2:AJ$323,'Hours Log'!$A$2:$A$323,"="&'Time Breakdown'!$A10,'Hours Log'!$C$2:$C$323,"="&'Time Breakdown'!$A$1) -> 0 | I10: =SUMIFS('Hours Log'!AK$2:AK$323,'Hours Log'!$A$2:$A$323,"="&'Time Breakdown'!$A10,'Hours Log'!$C$2:$C$323,"="&'Time Breakdown'!$A$1) -> 100 | ... U10: =SUMIFS('Hours Log'!AW$2:AW$323,'Hours Log'!$A$2:$A$323,"="&'Time Breakdown'!$A10,'Hours Log'!$C$2:$C$323,"="&'Time Breakdown'!$A$1) -> 0 | V10: =SUM(B10:U10) -> 100
A11: Engel | B11: =SUMIFS('Hours Log'!AD$2:AD$323,'Hours Log'!$A$2:$A$323,"="&'Time Breakdown'!$A11,'Hours Log'!$C$2:$C$323,"="&'Time Breakdown'!$A$1) -> 0 | C11: =SUMIFS('Hours Log'!AE$2:AE$323,'Hours Log'!$A$2:$A$323,"="&'Time Breakdown'!$A11,'Hours Log'!$C$2:$C$323,"="&'Time Breakdown'!$A$1) -> 0 | D11: =SUMIFS('Hours Log'!AF$2:AF$323,'Hours Log'!$A$2:$A$323,"="&'Time Breakdown'!$A11,'Hours Log'!$C$2:$C$323,"="&'Time Breakdown'!$A$1) -> 0 | E11: =SUMIFS('Hours Log'!AG$2:AG$323,'Hours Log'!$A$2:$A$323,"="&'Time Breakdown'!$A11,'Hours Log'!$C$2:$C$323,"="&'Time Breakdown'!$A$1) -> 0 | F11: =SUMIFS('Hours Log'!AH$2:AH$323,'Hours Log'!$A$2:$A$323,"="&'Time Breakdown'!$A11,'Hours Log'!$C$2:$C$323,"="&'Time Breakdown'!$A$1) -> 0 | G11: =SUMIFS('Hours Log'!AI$2:AI$323,'Hours Log'!$A$2:$A$323,"="&'Time Breakdown'!$A11,'Hours Log'!$C$2:$C$323,"="&'Time Breakdown'!$A$1) -> 0 | H11: =SUMIFS('Hours Log'!AJ$2:AJ$323,'Hours Log'!$A$2:$A$323,"="&'Time Breakdown'!$A11,'Hours Log'!$C$2:$C$323,"="&'Time Breakdown'!$A$1) -> 1160.3205 | I11: =SUMIFS('Hours Log'!AK$2:AK$323,'Hours Log'!$A$2:$A$323,"="&'Time Breakdown'!$A11,'Hours Log'!$C$2:$C$323,"="&'Time Breakdown'!$A$1) -> 0 | ... U11: =SUMIFS('Hours Log'!AW$2:AW$323,'Hours Log'!$A$2:$A$323,"="&'Time Breakdown'!$A11,'Hours Log'!$C$2:$C$323,"="&'Time Breakdown'!$A$1) -> 0 | V11: =SUM(B11:U11) -> 2088
A12: Ewing | B12: =SUMIFS('Hours Log'!AD$2:AD$323,'Hours Log'!$A$2:$A$323,"="&'Time Breakdown'!$A12,'Hours Log'!$C$2:$C$323,"="&'Time Breakdown'!$A$1) -> 0 | C12: =SUMIFS('Hours Log'!AE$2:AE$323,'Hours Log'!$A$2:$A$323,"="&'Time Breakdown'!$A12,'Hours Log'!$C$2:$C$323,"="&'Time Breakdown'!$A$1) -> 0 | D12: =SUMIFS('Hours Log'!AF$2:AF$323,'Hours Log'!$A$2:$A$323,"="&'Time Breakdown'!$A12,'Hours Log'!$C$2:$C$323,"="&'Time Breakdown'!$A$1) -> 0 | E12: =SUMIFS('Hours Log'!AG$2:AG$323,'Hours Log'!$A$2:$A$323,"="&'Time Breakdown'!$A12,'Hours Log'!$C$2:$C$323,"="&'Time Breakdown'!$A$1) -> 0 | F12: =SUMIFS('Hours Log'!AH$2:AH$323,'Hours Log'!$A$2:$A$323,"="&'Time Breakdown'!$A12,'Hours Log'!$C$2:$C$323,"="&'Time Breakdown'!$A$1) -> 0 | G12: =SUMIFS('Hours Log'!AI$2:AI$323,'Hours Log'!$A$2:$A$323,"="&'Time Breakdown'!$A12,'Hours Log'!$C$2:$C$323,"="&'Time Breakdown'!$A$1) -> 0 | H12: =SUMIFS('Hours Log'!AJ$2:AJ$323,'Hours Log'!$A$2:$A$323,"="&'Time Breakdown'!$A12,'Hours Log'!$C$2:$C$323,"="&'Time Breakdown'!$A$1) -> 0 | I12: =SUMIFS('Hours Log'!AK$2:AK$323,'Hours Log'!$A$2:$A$323,"="&'Time Breakdown'!$A12,'Hours Log'!$C$2:$C$323,"="&'Time Breakdown'!$A$1) -> 951.59721 | ... U12: =SUMIFS('Hours Log'!AW$2:AW$323,'Hours Log'!$A$2:$A$323,"="&'Time Breakdown'!$A12,'Hours Log'!$C$2:$C$323,"="&'Time Breakdown'!$A$1) -> 282.91665 | V12: =SUM(B12:U12) -> 2088
A13: Fiffick | B13: =SUMIFS('Hours Log'!AD$2:AD$323,'Hours Log'!$A$2:$A$323,"="&'Time Breakdown'!$A13,'Hours Log'!$C$2:$C$323,"="&'Time Breakdown'!$A$1) -> 0 | C13: =SUMIFS('Hours Log'!AE$2:AE$323,'Hours Log'!$A$2:$A$323,"="&'Time Breakdown'!$A13,'Hours Log'!$C$2:$C$323,"="&'Time Breakdown'!$A$1) -> 0 | D13: =SUMIFS('Hours Log'!AF$2:AF$323,'Hours Log'!$A$2:$A$323,"="&'Time Breakdown'!$A13,'Hours Log'!$C$2:$C$323,"="&'Time Breakdown'!$A$1) -> 0 | E13: =SUMIFS('Hours Log'!AG$2:AG$323,'Hours Log'!$A$2:$A$323,"="&'Time Breakdown'!$A13,'Hours Log'!$C$2:$C$323,"="&'Time Breakdown'!$A$1) -> 0 | F13: =SUMIFS('Hours Log'!AH$2:AH$323,'Hours Log'!$A$2:$A$323,"="&'Time Breakdown'!$A13,'Hours Log'!$C$2:$C$323,"="&'Time Breakdown'!$A$1) -> 0 | G13: =SUMIFS('Hours Log'!AI$2:AI$323,'Hours Log'!$A$2:$A$323,"="&'Time Breakdown'!$A13,'Hours Log'!$C$2:$C$323,"="&'Time Breakdown'!$A$1) -> 0 | H13: =SUMIFS('Hours Log'!AJ$2:AJ$323,'Hours Log'!$A$2:$A$323,"="&'Time Breakdown'!$A13,'Hours Log'!$C$2:$C$323,"="&'Time Breakdown'!$A$1) -> 0 | I13: =SUMIFS('Hours Log'!AK$2:AK$323,'Hours Log'!$A$2:$A$323,"="&'Time Breakdown'!$A13,'Hours Log'!$C$2:$C$323,"="&'Time Breakdown'!$A$1) -> 1739.25 | ... U13: =SUMIFS('Hours Log'!AW$2:AW$323,'Hours Log'!$A$2:$A$323,"="&'Time Breakdown'!$A13,'Hours Log'!$C$2:$C$323,"="&'Time Breakdown'!$A$1) -> 340.75 | V13: =SUM(B13:U13) -> 2080
... A46: Wheeler | B46: =SUMIFS('Hours Log'!AD$2:AD$323,'Hours Log'!$A$2:$A$323,"="&'Time Breakdown'!$A46,'Hours Log'!$C$2:$C$323,"="&'Time Breakdown'!$A$1) -> 0 | C46: =SUMIFS('Hours Log'!AE$2:AE$323,'Hours Log'!$A$2:$A$323,"="&'Time Breakdown'!$A46,'Hours Log'!$C$2:$C$323,"="&'Time Breakdown'!$A$1) -> 0 | D46: =SUMIFS('Hours Log'!AF$2:AF$323,'Hours Log'!$A$2:$A$323,"="&'Time Breakdown'!$A46,'Hours Log'!$C$2:$C$323,"="&'Time Breakdown'!$A$1) -> 0 | E46: =SUMIFS('Hours Log'!AG$2:AG$323,'Hours Log'!$A$2:$A$323,"="&'Time Breakdown'!$A46,'Hours Log'!$C$2:$C$323,"="&'Time Breakdown'!$A$1) -> 0 | F46: =SUMIFS('Hours Log'!AH$2:AH$323,'Hours Log'!$A$2:$A$323,"="&'Time Breakdown'!$A46,'Hours Log'!$C$2:$C$323,"="&'Time Breakdown'!$A$1) -> 0 | G46: =SUMIFS('Hours Log'!AI$2:AI$323,'Hours Log'!$A$2:$A$323,"="&'Time Breakdown'!$A46,'Hours Log'!$C$2:$C$323,"="&'Time Breakdown'!$A$1) -> 0 | H46: =SUMIFS('Hours Log'!AJ$2:AJ$323,'Hours Log'!$A$2:$A$323,"="&'Time Breakdown'!$A46,'Hours Log'!$C$2:$C$323,"="&'Time Breakdown'!$A$1) -> 0 | I46: =SUMIFS('Hours Log'!AK$2:AK$323,'Hours Log'!$A$2:$A$323,"="&'Time Breakdown'!$A46,'Hours Log'!$C$2:$C$323,"="&'Time Breakdown'!$A$1) -> 0 | ... U46: =SUMIFS('Hours Log'!AW$2:AW$323,'Hours Log'!$A$2:$A$323,"="&'Time Breakdown'!$A46,'Hours Log'!$C$2:$C$323,"="&'Time Breakdown'!$A$1) -> 0 | V46: =SUM(B46:U46) -> 100
A48: 2025 | B48: Adj-AAMEN | C48: Adj-AM Other | D48: Adj-Apex | E48: Adj-CDBG | F48: Adj-Dig Eng M7 | G48: Adj-DLA | H48: Adj-Drive AM | I48: Adj-ESP | J48: Adj-Fundraising | K48: Adj-Hub | L48: Adj-Hybrid | M48: Adj-IIOT | N48: Adj-LTM | O48: Adj-MBAC | P48: Adj-NavAir | Q48: Adj-Rising Tides | R48: Adj-VGV | S48: Adj-Xjet | T48: Adj-Youth | U48: Adj-YBI | V48: Total
A49: Anderson | B49: =B2/$V2 -> 0 | C49: =C2/$V2 -> 0 | D49: =D2/$V2 -> 0 | E49: =E2/$V2 -> 0 | F49: =F2/$V2 -> 0 | G49: =G2/$V2 -> 0 | H49: =H2/$V2 -> 0 | I49: =I2/$V2 -> 0 | ... U49: =U2/$V2 -> 0 | V49: =SUM(B49:U49) -> 1
A50: Baxter | B50: =B3/$V3 -> 0 | C50: =C3/$V3 -> 0 | D50: =D3/$V3 -> 0 | E50: =E3/$V3 -> 0 | F50: =F3/$V3 -> 0 | G50: =G3/$V3 -> 0 | H50: =H3/$V3 -> 0 | I50: =I3/$V3 -> 1 | ... U50: =U3/$V3 -> 0 | V50: =SUM(B50:U50) -> 1
A51: Bixel | B51: =B4/$V4 -> 0 | C51: =C4/$V4 -> 0 | D51: =D4/$V4 -> 0 | E51: =E4/$V4 -> 0 | F51: =F4/$V4 -> 0 | G51: =G4/$V4 -> 0 | H51: =H4/$V4 -> 0 | I51: =I4/$V4 -> 1 | ... U51: =U4/$V4 -> 0 | V51: =SUM(B51:U51) -> 1
A52: Byers | B52: =B5/$V5 -> 0 | C52: =C5/$V5 -> 0 | D52: =D5/$V5 -> 0 | E52: =E5/$V5 -> 0 | F52: =F5/$V5 -> 0 | G52: =G5/$V5 -> 0 | H52: =H5/$V5 -> 0 | I52: =I5/$V5 -> 0 | ... U52: =U5/$V5 -> 0 | V52: =SUM(B52:U52) -> 1
A53: Canton | B53: =B6/$V6 -> 0 | C53: =C6/$V6 -> 0 | D53: =D6/$V6 -> 0 | E53: =E6/$V6 -> 0 | F53: =F6/$V6 -> 0 | G53: =G6/$V6 -> 0 | H53: =H6/$V6 -> 0 | I53: =I6/$V6 -> 1 | ... U53: =U6/$V6 -> 0 | V53: =SUM(B53:U53) -> 1
A54: Chunn | B54: =B7/$V7 -> 0 | C54: =C7/$V7 -> 0 | D54: =D7/$V7 -> 0 | E54: =E7/$V7 -> 0 | F54: =F7/$V7 -> 0 | G54: =G7/$V7 -> 0 | H54: =H7/$V7 -> 0 | I54: =I7/$V7 -> 1 | ... U54: =U7/$V7 -> 0 | V54: =SUM(B54:U54) -> 1
A55: Davis | B55: =B8/$V8 -> 0 | C55: =C8/$V8 -> 0 | D55: =D8/$V8 -> 0 | E55: =E8/$V8 -> 0 | F55: =F8/$V8 -> 0 | G55: =G8/$V8 -> 0 | H55: =H8/$V8 -> 0 | I55: =I8/$V8 -> 0 | ... U55: =U8/$V8 -> 0 | V55: =SUM(B55:U55) -> 1
A56: Dively | B56: =B9/$V9 -> 0 | C56: =C9/$V9 -> 0 | D56: =D9/$V9 -> 0 | E56: =E9/$V9 -> 0 | F56: =F9/$V9 -> 0 | G56: =G9/$V9 -> 0 | H56: =H9/$V9 -> 0 | I56: =I9/$V9 -> 1 | ... U56: =U9/$V9 -> 0 | V56: =SUM(B56:U56) -> 1
A57: Dwyer | B57: =B10/$V10 -> 0 | C57: =C10/$V10 -> 0 | D57: =D10/$V10 -> 0 | E57: =E10/$V10 -> 0 | F57: =F10/$V10 -> 0 | G57: =G10/$V10 -> 0 | H57: =H10/$V10 -> 0 | I57: =I10/$V10 -> 1 | ... U57: =U10/$V10 -> 0 | V57: =SUM(B57:U57) -> 1
A58: Engel | B58: =B11/$V11 -> 0 | C58: =C11/$V11 -> 0 | D58: =D11/$V11 -> 0 | E58: =E11/$V11 -> 0 | F58: =F11/$V11 -> 0 | G58: =G11/$V11 -> 0 | H58: =H11/$V11 -> 0.55570906 | I58: =I11/$V11 -> 0 | ... U58: =U11/$V11 -> 0 | V58: =SUM(B58:U58) -> 1
A59: Ewing | B59: =B12/$V12 -> 0 | C59: =C12/$V12 -> 0 | D59: =D12/$V12 -> 0 | E59: =E12/$V12 -> 0 | F59: =F12/$V12 -> 0 | G59: =G12/$V12 -> 0 | H59: =H12/$V12 -> 0 | I59: =I12/$V12 -> 0.45574579 | ... U59: =U12/$V12 -> 0.13549648 | V59: =SUM(B59:U59) -> 1
A60: Fiffick | B60: =B13/$V13 -> 0 | C60: =C13/$V13 -> 0 | D60: =D13/$V13 -> 0 | E60: =E13/$V13 -> 0 | F60: =F13/$V13 -> 0 | G60: =G13/$V13 -> 0 | H60: =H13/$V13 -> 0 | I60: =I13/$V13 -> 0.83617788 | ... U60: =U13/$V13 -> 0.16382212 | V60: =SUM(B60:U60) -> 1
... A93: Wheeler | B93: =B46/$V46 -> 0 | C93: =C46/$V46 -> 0 | D93: =D46/$V46 -> 0 | E93: =E46/$V46 -> 0 | F93: =F46/$V46 -> 0 | G93: =G46/$V46 -> 0 | H93: =H46/$V46 -> 0 | I93: =I46/$V46 -> 0 | ... U93: =U46/$V46 -> 0 | V93: =SUM(B93:U93) -> 1
A95: 5139 Wages
C96: FFP Federal | D96: Program | E96: Federal | F96: Federal | G96: Federal | H96: Federal | I96: Federal | J96: Program | K96: Fundraising | L96: Non-Federal | M96: Federal | N96: Federal | O96: Federal | P96: Program | Q96: Program | R96: Federal | S96: Program | T96: Manufacturing Svcs | U96: Program | V96: M&A
A97: 2025 | B97: 2025 Wages | C97: Adj-AAMEN | D97: Adj-AM Other | E97: Adj-Apex | F97: Adj-CDBG | G97: Adj-Dig Eng M7 | H97: Adj-DLA | I97: Adj-Drive AM | J97: Adj-ESP | K97: Adj-Fundraising | L97: Adj-Hub | M97: Adj-Hybrid | N97: Adj-IIOT | O97: Adj-LTM | P97: Adj-MBAC | Q97: Adj-NavAir | R97: Adj-Rising Tides | S97: Adj-VGV | T97: Adj-Xjet | U97: Adj-Youth | V97: Adj-YBI | W97: Total
A98: Alkraein | B98: -53.2 | J98: -53.2 | W98: =SUM(C98:V98) -> -53.2
A99: Anderson | B99: =INDEX('Reference Sheet'!$G$9:$J$100,MATCH('Time Breakdown'!$A99,'Reference Sheet'!$F$9:$F$100),MATCH($A$97,'Reference Sheet'!$G$8:$J$8)) -> 61232 | C99: =$B99*B49 -> 0 | D99: =$B99*C49 -> 0 | E99: =$B99*D49 -> 0 | F99: =$B99*E49 -> 0 | G99: =$B99*F49 -> 0 | H99: =$B99*G49 -> 0 | I99: =$B99*H49 -> 0 | J99: =$B99*I49 -> 0 | ... V99: =$B99*U49 -> 0 | W99: =SUM(C99:V99) -> 61232
A100: Baxter | B100: =INDEX('Reference Sheet'!$G$9:$J$100,MATCH('Time Breakdown'!$A100,'Reference Sheet'!$F$9:$F$100),MATCH($A$97,'Reference Sheet'!$G$8:$J$8)) -> 10805.36 | C100: =$B100*B50 -> 0 | D100: =$B100*C50 -> 0 | E100: =$B100*D50 -> 0 | F100: =$B100*E50 -> 0 | G100: =$B100*F50 -> 0 | H100: =$B100*G50 -> 0 | I100: =$B100*H50 -> 0 | J100: =$B100*I50 -> 10805.36 | ... V100: =$B100*U50 -> 0 | W100: =SUM(C100:V100) -> 10805.36
A101: Bixel | B101: =INDEX('Reference Sheet'!$G$9:$J$100,MATCH('Time Breakdown'!$A101,'Reference Sheet'!$F$9:$F$100),MATCH($A$97,'Reference Sheet'!$G$8:$J$8)) -> 2412.3 | C101: =$B101*B51 -> 0 | D101: =$B101*C51 -> 0 | E101: =$B101*D51 -> 0 | F101: =$B101*E51 -> 0 | G101: =$B101*F51 -> 0 | H101: =$B101*G51 -> 0 | I101: =$B101*H51 -> 0 | J101: =$B101*I51 -> 2412.3 | ... V101: =$B101*U51 -> 0 | W101: =SUM(C101:V101) -> 2412.3
A102: Byers | B102: =INDEX('Reference Sheet'!$G$9:$J$100,MATCH('Time Breakdown'!$A102,'Reference Sheet'!$F$9:$F$100),MATCH($A$97,'Reference Sheet'!$G$8:$J$8)) -> 20280.45 | C102: =$B102*B52 -> 0 | D102: =$B102*C52 -> 0 | E102: =$B102*D52 -> 0 | F102: =$B102*E52 -> 0 | G102: =$B102*F52 -> 0 | H102: =$B102*G52 -> 0 | I102: =$B102*H52 -> 0 | J102: =$B102*I52 -> 0 | ... V102: =$B102*U52 -> 0 | W102: =SUM(C102:V102) -> 20280.45
A103: Canton | B103: =INDEX('Reference Sheet'!$G$9:$J$100,MATCH('Time Breakdown'!$A103,'Reference Sheet'!$F$9:$F$100),MATCH($A$97,'Reference Sheet'!$G$8:$J$8)) -> 9608.44 | C103: =$B103*B53 -> 0 | D103: =$B103*C53 -> 0 | E103: =$B103*D53 -> 0 | F103: =$B103*E53 -> 0 | G103: =$B103*F53 -> 0 | H103: =$B103*G53 -> 0 | I103: =$B103*H53 -> 0 | J103: =$B103*I53 -> 9608.44 | ... V103: =$B103*U53 -> 0 | W103: =SUM(C103:V103) -> 9608.44
A104: Chunn | B104: =INDEX('Reference Sheet'!$G$9:$J$100,MATCH('Time Breakdown'!$A104,'Reference Sheet'!$F$9:$F$100),MATCH($A$97,'Reference Sheet'!$G$8:$J$8)) -> 1430.65 | C104: =$B104*B54 -> 0 | D104: =$B104*C54 -> 0 | E104: =$B104*D54 -> 0 | F104: =$B104*E54 -> 0 | G104: =$B104*F54 -> 0 | H104: =$B104*G54 -> 0 | I104: =$B104*H54 -> 0 | J104: =$B104*I54 -> 1430.65 | ... V104: =$B104*U54 -> 0 | W104: =SUM(C104:V104) -> 1430.65
A105: Davis | B105: =INDEX('Reference Sheet'!$G$9:$J$100,MATCH('Time Breakdown'!$A105,'Reference Sheet'!$F$9:$F$100),MATCH($A$97,'Reference Sheet'!$G$8:$J$8)) -> 56212.62 | C105: =$B105*B55 -> 0 | D105: =$B105*C55 -> 0 | E105: =$B105*D55 -> 0 | F105: =$B105*E55 -> 0 | G105: =$B105*F55 -> 0 | H105: =$B105*G55 -> 0 | I105: =$B105*H55 -> 0 | J105: =$B105*I55 -> 0 | ... V105: =$B105*U55 -> 0 | W105: =SUM(C105:V105) -> 56212.62
A106: Dively | B106: =INDEX('Reference Sheet'!$G$9:$J$100,MATCH('Time Breakdown'!$A106,'Reference Sheet'!$F$9:$F$100),MATCH($A$97,'Reference Sheet'!$G$8:$J$8)) -> 12715.75 | C106: =$B106*B56 -> 0 | D106: =$B106*C56 -> 0 | E106: =$B106*D56 -> 0 | F106: =$B106*E56 -> 0 | G106: =$B106*F56 -> 0 | H106: =$B106*G56 -> 0 | I106: =$B106*H56 -> 0 | J106: =$B106*I56 -> 12715.75 | ... V106: =$B106*U56 -> 0 | W106: =SUM(C106:V106) -> 12715.75
A107: Dwyer | B107: =INDEX('Reference Sheet'!$G$9:$J$100,MATCH('Time Breakdown'!$A107,'Reference Sheet'!$F$9:$F$100),MATCH($A$97,'Reference Sheet'!$G$8:$J$8)) -> 2782.9 | C107: =$B107*B57 -> 0 | D107: =$B107*C57 -> 0 | E107: =$B107*D57 -> 0 | F107: =$B107*E57 -> 0 | G107: =$B107*F57 -> 0 | H107: =$B107*G57 -> 0 | I107: =$B107*H57 -> 0 | J107: =$B107*I57 -> 2782.9 | ... V107: =$B107*U57 -> 0 | W107: =SUM(C107:V107) -> 2782.9
A108: Engel | B108: =INDEX('Reference Sheet'!$G$9:$J$100,MATCH('Time Breakdown'!$A108,'Reference Sheet'!$F$9:$F$100),MATCH($A$97,'Reference Sheet'!$G$8:$J$8)) -> 78307.73 | C108: =$B108*B58 -> 0 | D108: =$B108*C58 -> 0 | E108: =$B108*D58 -> 0 | F108: =$B108*E58 -> 0 | G108: =$B108*F58 -> 0 | H108: =$B108*G58 -> 0 | I108: =$B108*H58 -> 43516.315 | J108: =$B108*I58 -> 0 | ... V108: =$B108*U58 -> 0 | W108: =SUM(C108:V108) -> 78307.73
A109: Ewing | B109: =INDEX('Reference Sheet'!$G$9:$J$100,MATCH('Time Breakdown'!$A109,'Reference Sheet'!$F$9:$F$100),MATCH($A$97,'Reference Sheet'!$G$8:$J$8)) -> 192087.13 | C109: =$B109*B59 -> 0 | D109: =$B109*C59 -> 0 | E109: =$B109*D59 -> 0 | F109: =$B109*E59 -> 0 | G109: =$B109*F59 -> 0 | H109: =$B109*G59 -> 0 | I109: =$B109*H59 -> 0 | J109: =$B109*I59 -> 87542.901 | ... V109: =$B109*U59 -> 26027.13 | W109: =SUM(C109:V109) -> 192087.13
A110: Fiffick | B110: =INDEX('Reference Sheet'!$G$9:$J$100,MATCH('Time Breakdown'!$A110,'Reference Sheet'!$F$9:$F$100),MATCH($A$97,'Reference Sheet'!$G$8:$J$8)) -> 83316.89 | C110: =$B110*B60 -> 0 | D110: =$B110*C60 -> 0 | E110: =$B110*D60 -> 0 | F110: =$B110*E60 -> 0 | G110: =$B110*F60 -> 0 | H110: =$B110*G60 -> 0 | I110: =$B110*H60 -> 0 | J110: =$B110*I60 -> 69667.741 | ... V110: =$B110*U60 -> 13649.149 | W110: =SUM(C110:V110) -> 83316.89
... A125: Longo | B125: =INDEX('Reference Sheet'!$G$9:$J$100,MATCH('Time Breakdown'!$A125,'Reference Sheet'!$F$9:$F$100),MATCH($A$97,'Reference Sheet'!$G$8:$J$8)) -> 91374.4 | C125: =$B125*B75 -> 0 | D125: =$B125*C75 -> 0 | E125: =$B125*D75 -> 0 | F125: =$B125*E75 -> 0 | G125: =$B125*F75 -> 13792.531 | H125: =$B125*G75 -> 0 | I125: =$B125*H75 -> 0 | J125: =$B125*I75 -> 0 | ... V125: =$B125*U75 -> 0 | W125: =SUM(C125:V125) -> 91374.4
A126: Micco | B126: =INDEX('Reference Sheet'!$G$9:$J$100,MATCH('Time Breakdown'!$A126,'Reference Sheet'!$F$9:$F$100),MATCH($A$97,'Reference Sheet'!$G$8:$J$8)) -> 5059.17 | C126: =$B126*B77 -> 0 | D126: =$B126*C77 -> 0 | E126: =$B126*D77 -> 0 | F126: =$B126*E77 -> 0 | G126: =$B126*F77 -> 0 | H126: =$B126*G77 -> 0 | I126: =$B126*H77 -> 0 | J126: =$B126*I77 -> 5059.17 | ... V126: =$B126*U77 -> 0 | W126: =SUM(C126:V126) -> 5059.17
A127: Moreno | B127: =INDEX('Reference Sheet'!$G$9:$J$100,MATCH('Time Breakdown'!$A127,'Reference Sheet'!$F$9:$F$100),MATCH($A$97,'Reference Sheet'!$G$8:$J$8)) -> 1375.74 | C127: =$B127*B78 -> 0 | D127: =$B127*C78 -> 0 | E127: =$B127*D78 -> 0 | F127: =$B127*E78 -> 0 | G127: =$B127*F78 -> 0 | H127: =$B127*G78 -> 0 | I127: =$B127*H78 -> 0 | J127: =$B127*I78 -> 1375.74 | ... V127: =$B127*U78 -> 0 | W127: =SUM(C127:V127) -> 1375.74
A128: Negro | B128: =INDEX('Reference Sheet'!$G$9:$J$100,MATCH('Time Breakdown'!$A128,'Reference Sheet'!$F$9:$F$100),MATCH($A$97,'Reference Sheet'!$G$8:$J$8)) -> 76312.09 | C128: =$B128*B79 -> 0 | D128: =$B128*C79 -> 0 | E128: =$B128*D79 -> 0 | F128: =$B128*E79 -> 0 | G128: =$B128*F79 -> 0 | H128: =$B128*G79 -> 0 | I128: =$B128*H79 -> 35322.374 | J128: =$B128*I79 -> 0 | ... V128: =$B128*U79 -> 0 | W128: =SUM(C128:V128) -> 76312.09
A129: Pasha | B129: =INDEX('Reference Sheet'!$G$9:$J$100,MATCH('Time Breakdown'!$A129,'Reference Sheet'!$F$9:$F$100),MATCH($A$97,'Reference Sheet'!$G$8:$J$8)) -> 40670.05 | C129: =$B129*B80 -> 0 | D129: =$B129*C80 -> 0 | E129: =$B129*D80 -> 0 | F129: =$B129*E80 -> 0 | G129: =$B129*F80 -> 0 | H129: =$B129*G80 -> 0 | I129: =$B129*H80 -> 0 | J129: =$B129*I80 -> 39678.098 | ... V129: =$B129*U80 -> 0 | W129: =SUM(C129:V129) -> 40670.05
A130: Payich | B130: =INDEX('Reference Sheet'!$G$9:$J$100,MATCH('Time Breakdown'!$A130,'Reference Sheet'!$F$9:$F$100),MATCH($A$97,'Reference Sheet'!$G$8:$J$8)) -> 66222.22 | C130: =$B130*B81 -> 0 | D130: =$B130*C81 -> 0 | E130: =$B130*D81 -> 0 | F130: =$B130*E81 -> 0 | G130: =$B130*F81 -> 0 | H130: =$B130*G81 -> 0 | I130: =$B130*H81 -> 0 | J130: =$B130*I81 -> 0 | ... V130: =$B130*U81 -> 0 | W130: =SUM(C130:V130) -> 66222.22
A131: Politsky | B131: =INDEX('Reference Sheet'!$G$9:$J$100,MATCH('Time Breakdown'!$A131,'Reference Sheet'!$F$9:$F$100),MATCH($A$97,'Reference Sheet'!$G$8:$J$8)) -> 68284.8 | C131: =$B131*B82 -> 0 | D131: =$B131*C82 -> 0 | E131: =$B131*D82 -> 0 | F131: =$B131*E82 -> 0 | G131: =$B131*F82 -> 0 | H131: =$B131*G82 -> 0 | I131: =$B131*H82 -> 0 | J131: =$B131*I82 -> 24903.507 | ... V131: =$B131*U82 -> 27209.387 | W131: =SUM(C131:V131) -> 68284.8
A132: Precurato | B132: =INDEX('Reference Sheet'!$G$9:$J$100,MATCH('Time Breakdown'!$A132,'Reference Sheet'!$F$9:$F$100),MATCH($A$97,'Reference Sheet'!$G$8:$J$8)) -> 3001.55 | C132: =$B132*B83 -> 0 | D132: =$B132*C83 -> 0 | E132: =$B132*D83 -> 0 | F132: =$B132*E83 -> 0 | G132: =$B132*F83 -> 0 | H132: =$B132*G83 -> 0 | I132: =$B132*H83 -> 0 | J132: =$B132*I83 -> 3001.55 | ... V132: =$B132*U83 -> 0 | W132: =SUM(C132:V132) -> 3001.55
A133: Rabenstine | B133: =INDEX('Reference Sheet'!$G$9:$J$100,MATCH('Time Breakdown'!$A133,'Reference Sheet'!$F$9:$F$100),MATCH($A$97,'Reference Sheet'!$G$8:$J$8)) -> 8988.92 | C133: =$B133*B84 -> 0 | D133: =$B133*C84 -> 0 | E133: =$B133*D84 -> 0 | F133: =$B133*E84 -> 0 | G133: =$B133*F84 -> 0 | H133: =$B133*G84 -> 0 | I133: =$B133*H84 -> 0 | J133: =$B133*I84 -> 8988.92 | ... V133: =$B133*U84 -> 0 | W133: =SUM(C133:V133) -> 8988.92
A134: Rhoades | B134: =INDEX('Reference Sheet'!$G$9:$J$100,MATCH('Time Breakdown'!$A134,'Reference Sheet'!$F$9:$F$100),MATCH($A$97,'Reference Sheet'!$G$8:$J$8)) -> 23538.44 | C134: =$B134*B85 -> 0 | D134: =$B134*C85 -> 0 | E134: =$B134*D85 -> 0 | F134: =$B134*E85 -> 0 | G134: =$B134*F85 -> 0 | H134: =$B134*G85 -> 0 | I134: =$B134*H85 -> 0 | J134: =$B134*I85 -> 21989.611 | ... V134: =$B134*U85 -> 1348.7526 | W134: =SUM(C134:V134) -> 23538.44
A135: Roch | B135: =INDEX('Reference Sheet'!$G$9:$J$100,MATCH('Time Breakdown'!$A135,'Reference Sheet'!$F$9:$F$100),MATCH($A$97,'Reference Sheet'!$G$8:$J$8)) -> 18563.16 | C135: =$B135*B86 -> 0 | D135: =$B135*C86 -> 0 | E135: =$B135*D86 -> 0 | F135: =$B135*E86 -> 0 | G135: =$B135*F86 -> 0 | H135: =$B135*G86 -> 0 | I135: =$B135*H86 -> 0 | J135: =$B135*I86 -> 18563.16 | ... V135: =$B135*U86 -> 0 | W135: =SUM(C135:V135) -> 18563.16
A136: Ruby | B136: =INDEX('Reference Sheet'!$G$9:$J$100,MATCH('Time Breakdown'!$A136,'Reference Sheet'!$F$9:$F$100),MATCH($A$97,'Reference Sheet'!$G$8:$J$8)) -> 112467.42 | C136: =$B136*B87 -> 0 | D136: =$B136*C87 -> 315.77189 | E136: =$B136*D87 -> 0 | F136: =$B136*E87 -> 0 | G136: =$B136*F87 -> 0 | H136: =$B136*G87 -> 0 | I136: =$B136*H87 -> 0 | J136: =$B136*I87 -> 26024.866 | ... V136: =$B136*U87 -> 52918.105 | W136: =SUM(C136:V136) -> 112467.42
A137: Shaulis | B137: =INDEX('Reference Sheet'!$G$9:$J$100,MATCH('Time Breakdown'!$A137,'Reference Sheet'!$F$9:$F$100),MATCH($A$97,'Reference Sheet'!$G$8:$J$8)) -> 41192.27 | C137: =$B137*B88 -> 0 | D137: =$B137*C88 -> 0 | E137: =$B137*D88 -> 0 | F137: =$B137*E88 -> 0 | G137: =$B137*F88 -> 0 | H137: =$B137*G88 -> 0 | I137: =$B137*H88 -> 0 | J137: =$B137*I88 -> 519.0226 | ... V137: =$B137*U88 -> 40673.247 | W137: =SUM(C137:V137) -> 41192.27
... A142: Wheeler | B142: =INDEX('Reference Sheet'!$G$9:$J$100,MATCH('Time Breakdown'!$A142,'Reference Sheet'!$F$9:$F$100),MATCH($A$97,'Reference Sheet'!$G$8:$J$8)) -> 83316.89 | C142: =$B142*B93 -> 0 | D142: =$B142*C93 -> 0 | E142: =$B142*D93 -> 0 | F142: =$B142*E93 -> 0 | G142: =$B142*F93 -> 0 | H142: =$B142*G93 -> 0 | I142: =$B142*H93 -> 0 | J142: =$B142*I93 -> 0 | ... V142: =$B142*U93 -> 0 | W142: =SUM(C142:V142) -> 83316.89
A143: JOB SUM: | C143: =SUM(C98:C142) -> 0 | D143: =SUM(D98:D142) -> 7129.6278 | E143: =SUM(E98:E142) -> 0 | F143: =SUM(F98:F142) -> 0 | G143: =SUM(G98:G142) -> 30700.461 | H143: =SUM(H98:H142) -> 400.98473 | I143: =SUM(I98:I142) -> 147310.09 | J143: =SUM(J98:J142) -> 561091.53 | ... W143: =SUM(W98:W142) -> 1834994
C144: =C143/$W$143 -> 0 | D144: =D143/$W$143 -> 0.0038853685 | E144: =E143/$W$143 -> 0 | F144: =F143/$W$143 -> 0 | G144: =G143/$W$143 -> 0.016730551 | H144: =H143/$W$143 -> 0.000218521 | I144: =I143/$W$143 -> 0.080278243 | J144: =J143/$W$143 -> 0.30577295 | ... W144: =W143/$W$143 -> 1
A146: 5202 Accounting
A147: Metzinger | B147: =INDEX('Reference Sheet'!$G$9:$J$100,MATCH('Time Breakdown'!$A147,'Reference Sheet'!$F$9:$F$100),MATCH($A$97,'Reference Sheet'!$G$8:$J$8)) -> 72375 | C147: =$B147*B76 -> 0 | D147: =$B147*C76 -> 0 | E147: =$B147*D76 -> 0 | F147: =$B147*E76 -> 0 | G147: =$B147*F76 -> 0 | H147: =$B147*G76 -> 0 | I147: =$B147*H76 -> 0 | J147: =$B147*I76 -> 3428.7772 | ... V147: =$B147*U76 -> 46705.506 | W147: =SUM(C147:V147) -> 72375
C148: =C147/$W$147 -> 0 | D148: =D147/$W$147 -> 0 | E148: =E147/$W$147 -> 0 | F148: =F147/$W$147 -> 0 | G148: =G147/$W$147 -> 0 | H148: =H147/$W$147 -> 0 | I148: =I147/$W$147 -> 0 | J148: =J147/$W$147 -> 0.04737516 | ... V148: =V147/$W$147 -> 0.6453265 | W148: =W147/$B$147 -> 1

Sheet 09.04.26 Time Total
A1: Year | B1: 2025
A3: Row Labels | B3: Sum of AAMEN | C3: Sum of AM Other | D3: Sum of Apex | E3: Sum of Dig Eng M7 | F3: Sum of DLA | G3: Sum of Drive AM | H3: Sum of ESP | I3: Sum of Fundraising | J3: Sum of Hub | K3: Sum of Hybrid | L3: Sum of IIOT | M3: Sum of LTM | N3: Sum of MBAC | O3: Sum of NavAir (AM-O) | P3: Sum of Rising Tides | Q3: Sum of VGV | R3: Sum of Xjet (AM-O) | S3: Sum of Youth | T3: Sum of YBI
A4: Anderson | N4: 100
A5: Baxter | H5: 100
A6: Bixel | H6: 100
A7: Byers | S7: 100
A8: Canton | H8: 100
A9: Chunn | H9: 100
A10: Davis | N10: 100
A11: Dively | H11: 100
A12: Dwyer | H12: 100
A13: Engel | G13: 1180 | M13: 948
A14: Ewing | H14: 1189.41 | I14: 126.32 | J14: 815 | K14: 57.6 | N14: 52.5 | P14: 2 | Q14: 6 | S14: 19.5 | T14: 353.62
A15: Fiffick | H15: 1739.25 | T15: 340.75
A16: Fries | H16: 100
A17: Gaffney | E17: 259 | G17: 554.5 | H17: 285 | J17: 627 | K17: 434 | M17: 178 | P17: 345
A18: Gordon | H18: 100
A19: Griffin | N19: 100
A20: Hurd | H20: 100
A21: Islam | H21: 100
A22: Jadue | I22: 50 | T22: 50
A23: Jafarli | H23: 100
A24: Jaric | F24: 11 | G24: 756 | K24: 56 | L24: 78 | M24: 131 | P24: 144 | T24: 953
A25: Kale | G25: 223 | H25: 1383 | J25: 1001 | P25: 40
A26: Kelly | C26: 35 | H26: 925 | I26: 31 | N26: 84 | Q26: 7.5 | S26: 49 | T26: 1038.5
A27: Kummari | H27: 100
A28: Lawrence | H28: 100
A29: Leonard | H29: 100
A30: Longo | E30: 316 | K30: 654 | P30: 1115
A31: Metzinger | H31: 37 | K31: 120 | P31: 120 | T31: 504
A32: Micco | H32: 100
A33: Moreno | H33: 100
A34: Negro | G34: 973 | P34: 664 | R34: 469
A35: Pasha | H35: 480 | N35: 12
A36: Payich | S36: 100
A37: Politsky | H37: 810 | I37: 526 | T37: 885
A38: Precurato | H38: 100
A39: Rabenstine | H39: 100
A40: Rhoades | H40: 93.42 | N40: 0.85 | T40: 5.73
A41: Roch | H41: 100
A42: Ruby | C42: 6 | H42: 494.5 | J42: 605 | N42: 26 | T42: 1005.5
A43: Shaulis | H43: 1.26 | T43: 98.74
A44: Sprowl | C44: 141.6 | G44: 33.75 | H44: 897 | I44: 209.03 | J44: 400 | M44: 47.75 | N44: 42.71 | P44: 155.32 | T44: 152.84
A45: Strock | H45: 100
A46: Taylor | H46: 100
A47: Unger | H47: 100
A48: Wheeler | N48: 100
A49: Grand Total | C49: 182.6 | E49: 575 | F49: 11 | G49: 3720.25 | H49: 10534.84 | I49: 942.35 | J49: 3448 | K49: 1321.6 | L49: 78 | M49: 1304.75 | N49: 618.06 | P49: 2585.32 | Q49: 13.5 | R49: 469 | S49: 268.5 | T49: 5387.68

Sheet Hours Log
A1: Name | B1: Month | C1: Year | D1: Hourly Rate | E1: Fringe Rate | F1: FB Rate | G1: AAMEN | H1: AM Other | I1: Apex | J1: CDBG | K1: Dig Eng M7 | L1: DLA | M1: Drive AM | N1: ESP | O1: Fundraising | P1: Hub | Q1: Hybrid | R1: IIOT | S1: LTM | T1: MBAC | U1: NavAir (AM-O) | V1: Rising Tides | W1: VGV | X1: Xjet (AM-O) | Y1: Youth | Z1: YBI | AA1: TS Hours | AB1: Allow Hours | AC1: Variance | AD1: Adj-AAMEN | AE1: Adj-AM Other | AF1: Adj-Apex | AG1: Adj-CDBG | AH1: Adj-Dig Eng M7 | AI1: Adj-DLA | AJ1: Adj-Drive AM | AK1: Adj-ESP | AL1: Adj-Fundraising | AM1: Adj-Hub | AN1: Adj-Hybrid | AO1: Adj-IIOT | AP1: Adj-LTM | AQ1: Adj-MBAC | AR1: Adj-NavAir | AS1: Adj-Rising Tides | AT1: Adj-VGV | AU1: Adj-Xjet | AV1: Adj-Youth | AW1: Adj-YBI | AX1: ADJ TS Hours | AY1: X-AAMEN | AZ1: X-AM Other | BA1: X-Apex | BB1: X=CDBG | BC1: X-Dig Eng M7 | BD1: X-DLA | BE1: X-Drive AM | BF1: X-ESP | BG1: X-Fundraising | BH1: X-Hub | BI1: X-Hybrid | BJ1: X-IIOT | BK1: X-LTM | BL1: X-MBAC | BM1: X-NavAir | BN1: X-Rising Tides | BO1: X-VGV | BP1: X-Xjet | BQ1: X-Youth | BR1: X-YBI
A2: Engel | B2: March | C2: 2024 | D2: =INDEX('Reference Sheet'!$G$9:$J$100, MATCH(A2,'Reference Sheet'!$F$9:$F$100,0), MATCH(C2,'Reference Sheet'!$G$8:$J$8,0))/2080 -> 35.239992 | E2: =VLOOKUP(C2,'Reference Sheet'!$A$2:$B$5,2) -> 0.1913 | F2: =D2*(1+E2) -> 41.981402 | M2: 80 | AA2: =SUM(G2:Z2) -> 80 | AB2: 80 | AC2: =AB2-AA2 -> 0 | AD2: =(G2/$AA2)*$AB2 -> 0 | AE2: =(H2/$AA2)*$AB2 -> 0 | AF2: =(I2/$AA2)*$AB2 -> 0 | AG2: =(J2/$AA2)*$AB2 -> 0 | AH2: =(K2/$AA2)*$AB2 -> 0 | AI2: =(L2/$AA2)*$AB2 -> 0 | AJ2: =(M2/$AA2)*$AB2 -> 80 | AK2: =(N2/$AA2)*$AB2 -> 0 | ... AW2: =(Z2/$AA2)*$AB2 -> 0 | AX2: =SUM(AF2:AW2) -> 80 | AY2: =$F2*AD2 -> 0 | AZ2: =$F2*AE2 -> 0 | BA2: =$F2*AF2 -> 0 | BB2: =$F2*AG2 -> 0 | BC2: =$F2*AH2 -> 0 | BD2: =$F2*AI2 -> 0 | BE2: =$F2*AJ2 -> 3358.5122 | BF2: =$F2*AK2 -> 0 | ... BR2: =$F2*AW2 -> 0
A3: Engel | B3: June | C3: 2024 | D3: =INDEX('Reference Sheet'!$G$9:$J$100, MATCH(A3,'Reference Sheet'!$F$9:$F$100,0), MATCH(C3,'Reference Sheet'!$G$8:$J$8,0))/2080 -> 35.239992 | E3: =VLOOKUP(C3,'Reference Sheet'!$A$2:$B$5,2) -> 0.1913 | F3: =D3*(1+E3) -> 41.981402 | M3: 168 | AA3: =SUM(G3:Z3) -> 168 | AB3: =IF(OR(B3="",C3=""),"",SUMIFS('Reference Sheet'!$D$9:$D$42,'Reference Sheet'!$A$9:$A$42,C3,'Reference Sheet'!$B$9:$B$42,B3)) -> 160 | AC3: =AB3-AA3 -> -8 | AD3: =(G3/$AA3)*$AB3 -> 0 | AE3: =(H3/$AA3)*$AB3 -> 0 | AF3: =(I3/$AA3)*$AB3 -> 0 | AG3: =(J3/$AA3)*$AB3 -> 0 | AH3: =(K3/$AA3)*$AB3 -> 0 | AI3: =(L3/$AA3)*$AB3 -> 0 | AJ3: =(M3/$AA3)*$AB3 -> 160 | AK3: =(N3/$AA3)*$AB3 -> 0 | ... AW3: =(Z3/$AA3)*$AB3 -> 0 | AX3: =SUM(AF3:AW3) -> 160 | AY3: =$F3*AD3 -> 0 | AZ3: =$F3*AE3 -> 0 | BA3: =$F3*AF3 -> 0 | BB3: =$F3*AG3 -> 0 | BC3: =$F3*AH3 -> 0 | BD3: =$F3*AI3 -> 0 | BE3: =$F3*AJ3 -> 6717.0244 | BF3: =$F3*AK3 -> 0 | ... BR3: =$F3*AW3 -> 0
A4: Engel | B4: September | C4: 2024 | D4: =INDEX('Reference Sheet'!$G$9:$J$100, MATCH(A4,'Reference Sheet'!$F$9:$F$100,0), MATCH(C4,'Reference Sheet'!$G$8:$J$8,0))/2080 -> 35.239992 | E4: =VLOOKUP(C4,'Reference Sheet'!$A$2:$B$5,2) -> 0.1913 | F4: =D4*(1+E4) -> 41.981402 | M4: 168 | AA4: =SUM(G4:Z4) -> 168 | AB4: =IF(OR(B4="",C4=""),"",SUMIFS('Reference Sheet'!$D$9:$D$42,'Reference Sheet'!$A$9:$A$42,C4,'Reference Sheet'!$B$9:$B$42,B4)) -> 168 | AC4: =AB4-AA4 -> 0 | AD4: =(G4/$AA4)*$AB4 -> 0 | AE4: =(H4/$AA4)*$AB4 -> 0 | AF4: =(I4/$AA4)*$AB4 -> 0 | AG4: =(J4/$AA4)*$AB4 -> 0 | AH4: =(K4/$AA4)*$AB4 -> 0 | AI4: =(L4/$AA4)*$AB4 -> 0 | AJ4: =(M4/$AA4)*$AB4 -> 168 | AK4: =(N4/$AA4)*$AB4 -> 0 | ... AW4: =(Z4/$AA4)*$AB4 -> 0 | AX4: =SUM(AF4:AW4) -> 168 | AY4: =$F4*AD4 -> 0 | AZ4: =$F4*AE4 -> 0 | BA4: =$F4*AF4 -> 0 | BB4: =$F4*AG4 -> 0 | BC4: =$F4*AH4 -> 0 | BD4: =$F4*AI4 -> 0 | BE4: =$F4*AJ4 -> 7052.8756 | BF4: =$F4*AK4 -> 0 | ... BR4: =$F4*AW4 -> 0
A5: Engel | B5: April | C5: 2024 | D5: =INDEX('Reference Sheet'!$G$9:$J$100, MATCH(A5,'Reference Sheet'!$F$9:$F$100,0), MATCH(C5,'Reference Sheet'!$G$8:$J$8,0))/2080 -> 35.239992 | E5: =VLOOKUP(C5,'Reference Sheet'!$A$2:$B$5,2) -> 0.1913 | F5: =D5*(1+E5) -> 41.981402 | M5: 176 | AA5: =SUM(G5:Z5) -> 176 | AB5: =IF(OR(B5="",C5=""),"",SUMIFS('Reference Sheet'!$D$9:$D$42,'Reference Sheet'!$A$9:$A$42,C5,'Reference Sheet'!$B$9:$B$42,B5)) -> 176 | AC5: =AB5-AA5 -> 0 | AD5: =(G5/$AA5)*$AB5 -> 0 | AE5: =(H5/$AA5)*$AB5 -> 0 | AF5: =(I5/$AA5)*$AB5 -> 0 | AG5: =(J5/$AA5)*$AB5 -> 0 | AH5: =(K5/$AA5)*$AB5 -> 0 | AI5: =(L5/$AA5)*$AB5 -> 0 | AJ5: =(M5/$AA5)*$AB5 -> 176 | AK5: =(N5/$AA5)*$AB5 -> 0 | ... AW5: =(Z5/$AA5)*$AB5 -> 0 | AX5: =SUM(AF5:AW5) -> 176 | AY5: =$F5*AD5 -> 0 | AZ5: =$F5*AE5 -> 0 | BA5: =$F5*AF5 -> 0 | BB5: =$F5*AG5 -> 0 | BC5: =$F5*AH5 -> 0 | BD5: =$F5*AI5 -> 0 | BE5: =$F5*AJ5 -> 7388.7268 | BF5: =$F5*AK5 -> 0 | ... BR5: =$F5*AW5 -> 0
A6: Engel | B6: August | C6: 2024 | D6: =INDEX('Reference Sheet'!$G$9:$J$100, MATCH(A6,'Reference Sheet'!$F$9:$F$100,0), MATCH(C6,'Reference Sheet'!$G$8:$J$8,0))/2080 -> 35.239992 | E6: =VLOOKUP(C6,'Reference Sheet'!$A$2:$B$5,2) -> 0.1913 | F6: =D6*(1+E6) -> 41.981402 | M6: 176 | AA6: =SUM(G6:Z6) -> 176 | AB6: =IF(OR(B6="",C6=""),"",SUMIFS('Reference Sheet'!$D$9:$D$42,'Reference Sheet'!$A$9:$A$42,C6,'Reference Sheet'!$B$9:$B$42,B6)) -> 176 | AC6: =AB6-AA6 -> 0 | AD6: =(G6/$AA6)*$AB6 -> 0 | AE6: =(H6/$AA6)*$AB6 -> 0 | AF6: =(I6/$AA6)*$AB6 -> 0 | AG6: =(J6/$AA6)*$AB6 -> 0 | AH6: =(K6/$AA6)*$AB6 -> 0 | AI6: =(L6/$AA6)*$AB6 -> 0 | AJ6: =(M6/$AA6)*$AB6 -> 176 | AK6: =(N6/$AA6)*$AB6 -> 0 | ... AW6: =(Z6/$AA6)*$AB6 -> 0 | AX6: =SUM(AF6:AW6) -> 176 | AY6: =$F6*AD6 -> 0 | AZ6: =$F6*AE6 -> 0 | BA6: =$F6*AF6 -> 0 | BB6: =$F6*AG6 -> 0 | BC6: =$F6*AH6 -> 0 | BD6: =$F6*AI6 -> 0 | BE6: =$F6*AJ6 -> 7388.7268 | BF6: =$F6*AK6 -> 0 | ... BR6: =$F6*AW6 -> 0
A7: Engel | B7: November | C7: 2024 | D7: =INDEX('Reference Sheet'!$G$9:$J$100, MATCH(A7,'Reference Sheet'!$F$9:$F$100,0), MATCH(C7,'Reference Sheet'!$G$8:$J$8,0))/2080 -> 35.239992 | E7: =VLOOKUP(C7,'Reference Sheet'!$A$2:$B$5,2) -> 0.1913 | F7: =D7*(1+E7) -> 41.981402 | M7: 100 | S7: 80 | AA7: =SUM(G7:Z7) -> 180 | AB7: =IF(OR(B7="",C7=""),"",SUMIFS('Reference Sheet'!$D$9:$D$42,'Reference Sheet'!$A$9:$A$42,C7,'Reference Sheet'!$B$9:$B$42,B7)) -> 168 | AC7: =AB7-AA7 -> -12 | AD7: =(G7/$AA7)*$AB7 -> 0 | AE7: =(H7/$AA7)*$AB7 -> 0 | AF7: =(I7/$AA7)*$AB7 -> 0 | AG7: =(J7/$AA7)*$AB7 -> 0 | AH7: =(K7/$AA7)*$AB7 -> 0 | AI7: =(L7/$AA7)*$AB7 -> 0 | AJ7: =(M7/$AA7)*$AB7 -> 93.333333 | AK7: =(N7/$AA7)*$AB7 -> 0 | ... AW7: =(Z7/$AA7)*$AB7 -> 0 | AX7: =SUM(AF7:AW7) -> 168 | AY7: =$F7*AD7 -> 0 | AZ7: =$F7*AE7 -> 0 | BA7: =$F7*AF7 -> 0 | BB7: =$F7*AG7 -> 0 | BC7: =$F7*AH7 -> 0 | BD7: =$F7*AI7 -> 0 | BE7: =$F7*AJ7 -> 3918.2642 | BF7: =$F7*AK7 -> 0 | ... BR7: =$F7*AW7 -> 0
A8: Engel | B8: December | C8: 2024 | D8: =INDEX('Reference Sheet'!$G$9:$J$100, MATCH(A8,'Reference Sheet'!$F$9:$F$100,0), MATCH(C8,'Reference Sheet'!$G$8:$J$8,0))/2080 -> 35.239992 | E8: =VLOOKUP(C8,'Reference Sheet'!$A$2:$B$5,2) -> 0.1913 | F8: =D8*(1+E8) -> 41.981402 | M8: 100 | S8: 80 | AA8: =SUM(G8:Z8) -> 180 | AB8: =IF(OR(B8="",C8=""),"",SUMIFS('Reference Sheet'!$D$9:$D$42,'Reference Sheet'!$A$9:$A$42,C8,'Reference Sheet'!$B$9:$B$42,B8)) -> 176 | AC8: =AB8-AA8 -> -4 | AD8: =(G8/$AA8)*$AB8 -> 0 | AE8: =(H8/$AA8)*$AB8 -> 0 | AF8: =(I8/$AA8)*$AB8 -> 0 | AG8: =(J8/$AA8)*$AB8 -> 0 | AH8: =(K8/$AA8)*$AB8 -> 0 | AI8: =(L8/$AA8)*$AB8 -> 0 | AJ8: =(M8/$AA8)*$AB8 -> 97.777778 | AK8: =(N8/$AA8)*$AB8 -> 0 | ... AW8: =(Z8/$AA8)*$AB8 -> 0 | AX8: =SUM(AF8:AW8) -> 176 | AY8: =$F8*AD8 -> 0 | AZ8: =$F8*AE8 -> 0 | BA8: =$F8*AF8 -> 0 | BB8: =$F8*AG8 -> 0 | BC8: =$F8*AH8 -> 0 | BD8: =$F8*AI8 -> 0 | BE8: =$F8*AJ8 -> 4104.8482 | BF8: =$F8*AK8 -> 0 | ... BR8: =$F8*AW8 -> 0
A9: Engel | B9: October | C9: 2024 | D9: =INDEX('Reference Sheet'!$G$9:$J$100, MATCH(A9,'Reference Sheet'!$F$9:$F$100,0), MATCH(C9,'Reference Sheet'!$G$8:$J$8,0))/2080 -> 35.239992 | E9: =VLOOKUP(C9,'Reference Sheet'!$A$2:$B$5,2) -> 0.1913 | F9: =D9*(1+E9) -> 41.981402 | M9: 100 | S9: 83 | AA9: =SUM(G9:Z9) -> 183 | AB9: =IF(OR(B9="",C9=""),"",SUMIFS('Reference Sheet'!$D$9:$D$42,'Reference Sheet'!$A$9:$A$42,C9,'Reference Sheet'!$B$9:$B$42,B9)) -> 184 | AC9: =AB9-AA9 -> 1 | AD9: =(G9/$AA9)*$AB9 -> 0 | AE9: =(H9/$AA9)*$AB9 -> 0 | AF9: =(I9/$AA9)*$AB9 -> 0 | AG9: =(J9/$AA9)*$AB9 -> 0 | AH9: =(K9/$AA9)*$AB9 -> 0 | AI9: =(L9/$AA9)*$AB9 -> 0 | AJ9: =(M9/$AA9)*$AB9 -> 100.54645 | AK9: =(N9/$AA9)*$AB9 -> 0 | ... AW9: =(Z9/$AA9)*$AB9 -> 0 | AX9: =SUM(AF9:AW9) -> 184 | AY9: =$F9*AD9 -> 0 | AZ9: =$F9*AE9 -> 0 | BA9: =$F9*AF9 -> 0 | BB9: =$F9*AG9 -> 0 | BC9: =$F9*AH9 -> 0 | BD9: =$F9*AI9 -> 0 | BE9: =$F9*AJ9 -> 4221.0809 | BF9: =$F9*AK9 -> 0 | ... BR9: =$F9*AW9 -> 0
A10: Engel | B10: May | C10: 2024 | D10: =INDEX('Reference Sheet'!$G$9:$J$100, MATCH(A10,'Reference Sheet'!$F$9:$F$100,0), MATCH(C10,'Reference Sheet'!$G$8:$J$8,0))/2080 -> 35.239992 | E10: =VLOOKUP(C10,'Reference Sheet'!$A$2:$B$5,2) -> 0.1913 | F10: =D10*(1+E10) -> 41.981402 | M10: 184 | AA10: =SUM(G10:Z10) -> 184 | AB10: =IF(OR(B10="",C10=""),"",SUMIFS('Reference Sheet'!$D$9:$D$42,'Reference Sheet'!$A$9:$A$42,C10,'Reference Sheet'!$B$9:$B$42,B10)) -> 184 | AC10: =AB10-AA10 -> 0 | AD10: =(G10/$AA10)*$AB10 -> 0 | AE10: =(H10/$AA10)*$AB10 -> 0 | AF10: =(I10/$AA10)*$AB10 -> 0 | AG10: =(J10/$AA10)*$AB10 -> 0 | AH10: =(K10/$AA10)*$AB10 -> 0 | AI10: =(L10/$AA10)*$AB10 -> 0 | AJ10: =(M10/$AA10)*$AB10 -> 184 | AK10: =(N10/$AA10)*$AB10 -> 0 | ... AW10: =(Z10/$AA10)*$AB10 -> 0 | AX10: =SUM(AF10:AW10) -> 184 | AY10: =$F10*AD10 -> 0 | AZ10: =$F10*AE10 -> 0 | BA10: =$F10*AF10 -> 0 | BB10: =$F10*AG10 -> 0 | BC10: =$F10*AH10 -> 0 | BD10: =$F10*AI10 -> 0 | BE10: =$F10*AJ10 -> 7724.578 | BF10: =$F10*AK10 -> 0 | ... BR10: =$F10*AW10 -> 0
A11: Engel | B11: July | C11: 2024 | D11: =INDEX('Reference Sheet'!$G$9:$J$100, MATCH(A11,'Reference Sheet'!$F$9:$F$100,0), MATCH(C11,'Reference Sheet'!$G$8:$J$8,0))/2080 -> 35.239992 | E11: =VLOOKUP(C11,'Reference Sheet'!$A$2:$B$5,2) -> 0.1913 | F11: =D11*(1+E11) -> 41.981402 | M11: 184 | AA11: =SUM(G11:Z11) -> 184 | AB11: =IF(OR(B11="",C11=""),"",SUMIFS('Reference Sheet'!$D$9:$D$42,'Reference Sheet'!$A$9:$A$42,C11,'Reference Sheet'!$B$9:$B$42,B11)) -> 184 | AC11: =AB11-AA11 -> 0 | AD11: =(G11/$AA11)*$AB11 -> 0 | AE11: =(H11/$AA11)*$AB11 -> 0 | AF11: =(I11/$AA11)*$AB11 -> 0 | AG11: =(J11/$AA11)*$AB11 -> 0 | AH11: =(K11/$AA11)*$AB11 -> 0 | AI11: =(L11/$AA11)*$AB11 -> 0 | AJ11: =(M11/$AA11)*$AB11 -> 184 | AK11: =(N11/$AA11)*$AB11 -> 0 | ... AW11: =(Z11/$AA11)*$AB11 -> 0 | AX11: =SUM(AF11:AW11) -> 184 | AY11: =$F11*AD11 -> 0 | AZ11: =$F11*AE11 -> 0 | BA11: =$F11*AF11 -> 0 | BB11: =$F11*AG11 -> 0 | BC11: =$F11*AH11 -> 0 | BD11: =$F11*AI11 -> 0 | BE11: =$F11*AJ11 -> 7724.578 | BF11: =$F11*AK11 -> 0 | ... BR11: =$F11*AW11 -> 0
A12: Engel | B12: May | C12: 2025 | D12: =INDEX('Reference Sheet'!$G$9:$J$100, MATCH(A12,'Reference Sheet'!$F$9:$F$100,0), MATCH(C12,'Reference Sheet'!$G$8:$J$8,0))/2080 -> 37.647947 | E12: =VLOOKUP(C12,'Reference Sheet'!$A$2:$B$5,2) -> 0.2245 | F12: =D12*(1+E12) -> 46.099911 | M12: 100 | S12: 56 | AA12: =SUM(G12:Z12) -> 156 | AB12: =IF(OR(B12="",C12=""),"",SUMIFS('Reference Sheet'!$D$9:$D$42,'Reference Sheet'!$A$9:$A$42,C12,'Reference Sheet'!$B$9:$B$42,B12)) -> 176 | AC12: =AB12-AA12 -> 20 | AD12: =(G12/$AA12)*$AB12 -> 0 | AE12: =(H12/$AA12)*$AB12 -> 0 | AF12: =(I12/$AA12)*$AB12 -> 0 | AG12: =(J12/$AA12)*$AB12 -> 0 | AH12: =(K12/$AA12)*$AB12 -> 0 | AI12: =(L12/$AA12)*$AB12 -> 0 | AJ12: =(M12/$AA12)*$AB12 -> 112.82051 | AK12: =(N12/$AA12)*$AB12 -> 0 | ... AW12: =(Z12/$AA12)*$AB12 -> 0 | AX12: =SUM(AF12:AW12) -> 176 | AY12: =$F12*AD12 -> 0 | AZ12: =$F12*AE12 -> 0 | BA12: =$F12*AF12 -> 0 | BB12: =$F12*AG12 -> 0 | BC12: =$F12*AH12 -> 0 | BD12: =$F12*AI12 -> 0 | BE12: =$F12*AJ12 -> 5201.0156 | BF12: =$F12*AK12 -> 0 | ... BR12: =$F12*AW12 -> 0
A13: Engel | B13: February | C13: 2025 | D13: =INDEX('Reference Sheet'!$G$9:$J$100, MATCH(A13,'Reference Sheet'!$F$9:$F$100,0), MATCH(C13,'Reference Sheet'!$G$8:$J$8,0))/2080 -> 37.647947 | E13: =VLOOKUP(C13,'Reference Sheet'!$A$2:$B$5,2) -> 0.2245 | F13: =D13*(1+E13) -> 46.099911 | M13: 80 | S13: 80 | AA13: =SUM(G13:Z13) -> 160 | AB13: =IF(OR(B13="",C13=""),"",SUMIFS('Reference Sheet'!$D$9:$D$42,'Reference Sheet'!$A$9:$A$42,C13,'Reference Sheet'!$B$9:$B$42,B13)) -> 160 | AC13: =AB13-AA13 -> 0 | AD13: =(G13/$AA13)*$AB13 -> 0 | AE13: =(H13/$AA13)*$AB13 -> 0 | AF13: =(I13/$AA13)*$AB13 -> 0 | AG13: =(J13/$AA13)*$AB13 -> 0 | AH13: =(K13/$AA13)*$AB13 -> 0 | AI13: =(L13/$AA13)*$AB13 -> 0 | AJ13: =(M13/$AA13)*$AB13 -> 80 | AK13: =(N13/$AA13)*$AB13 -> 0 | ... AW13: =(Z13/$AA13)*$AB13 -> 0 | AX13: =SUM(AF13:AW13) -> 160 | AY13: =$F13*AD13 -> 0 | AZ13: =$F13*AE13 -> 0 | BA13: =$F13*AF13 -> 0 | BB13: =$F13*AG13 -> 0 | BC13: =$F13*AH13 -> 0 | BD13: =$F13*AI13 -> 0 | BE13: =$F13*AJ13 -> 3687.9929 | BF13: =$F13*AK13 -> 0 | ... BR13: =$F13*AW13 -> 0
A14: Engel | B14: January | C14: 2025 | D14: =INDEX('Reference Sheet'!$G$9:$J$100, MATCH(A14,'Reference Sheet'!$F$9:$F$100,0), MATCH(C14,'Reference Sheet'!$G$8:$J$8,0))/2080 -> 37.647947 | E14: =VLOOKUP(C14,'Reference Sheet'!$A$2:$B$5,2) -> 0.2245 | F14: =D14*(1+E14) -> 46.099911 | M14: 100 | S14: 80 | AA14: =SUM(G14:Z14) -> 180 | AB14: =IF(OR(B14="",C14=""),"",SUMIFS('Reference Sheet'!$D$9:$D$42,'Reference Sheet'!$A$9:$A$42,C14,'Reference Sheet'!$B$9:$B$42,B14)) -> 184 | AC14: =AB14-AA14 -> 4 | AD14: =(G14/$AA14)*$AB14 -> 0 | AE14: =(H14/$AA14)*$AB14 -> 0 | AF14: =(I14/$AA14)*$AB14 -> 0 | AG14: =(J14/$AA14)*$AB14 -> 0 | AH14: =(K14/$AA14)*$AB14 -> 0 | AI14: =(L14/$AA14)*$AB14 -> 0 | AJ14: =(M14/$AA14)*$AB14 -> 102.22222 | AK14: =(N14/$AA14)*$AB14 -> 0 | ... AW14: =(Z14/$AA14)*$AB14 -> 0 | AX14: =SUM(AF14:AW14) -> 184 | AY14: =$F14*AD14 -> 0 | AZ14: =$F14*AE14 -> 0 | BA14: =$F14*AF14 -> 0 | BB14: =$F14*AG14 -> 0 | BC14: =$F14*AH14 -> 0 | BD14: =$F14*AI14 -> 0 | BE14: =$F14*AJ14 -> 4712.4354 | BF14: =$F14*AK14 -> 0 | ... BR14: =$F14*AW14 -> 0
A15: Engel | B15: March | C15: 2025 | D15: =INDEX('Reference Sheet'!$G$9:$J$100, MATCH(A15,'Reference Sheet'!$F$9:$F$100,0), MATCH(C15,'Reference Sheet'!$G$8:$J$8,0))/2080 -> 37.647947 | E15: =VLOOKUP(C15,'Reference Sheet'!$A$2:$B$5,2) -> 0.2245 | F15: =D15*(1+E15) -> 46.099911 | M15: 100 | S15: 80 | AA15: =SUM(G15:Z15) -> 180 | AB15: =IF(OR(B15="",C15=""),"",SUMIFS('Reference Sheet'!$D$9:$D$42,'Reference Sheet'!$A$9:$A$42,C15,'Reference Sheet'!$B$9:$B$42,B15)) -> 168 | AC15: =AB15-AA15 -> -12 | AD15: =(G15/$AA15)*$AB15 -> 0 | AE15: =(H15/$AA15)*$AB15 -> 0 | AF15: =(I15/$AA15)*$AB15 -> 0 | AG15: =(J15/$AA15)*$AB15 -> 0 | AH15: =(K15/$AA15)*$AB15 -> 0 | AI15: =(L15/$AA15)*$AB15 -> 0 | AJ15: =(M15/$AA15)*$AB15 -> 93.333333 | AK15: =(N15/$AA15)*$AB15 -> 0 | ... AW15: =(Z15/$AA15)*$AB15 -> 0 | AX15: =SUM(AF15:AW15) -> 168 | AY15: =$F15*AD15 -> 0 | AZ15: =$F15*AE15 -> 0 | BA15: =$F15*AF15 -> 0 | BB15: =$F15*AG15 -> 0 | BC15: =$F15*AH15 -> 0 | BD15: =$F15*AI15 -> 0 | BE15: =$F15*AJ15 -> 4302.6584 | BF15: =$F15*AK15 -> 0 | ... BR15: =$F15*AW15 -> 0
A16: Engel | B16: April | C16: 2025 | D16: =INDEX('Reference Sheet'!$G$9:$J$100, MATCH(A16,'Reference Sheet'!$F$9:$F$100,0), MATCH(C16,'Reference Sheet'!$G$8:$J$8,0))/2080 -> 37.647947 | E16: =VLOOKUP(C16,'Reference Sheet'!$A$2:$B$5,2) -> 0.2245 | F16: =D16*(1+E16) -> 46.099911 | M16: 100 | S16: 80 | AA16: =SUM(G16:Z16) -> 180 | AB16: =IF(OR(B16="",C16=""),"",SUMIFS('Reference Sheet'!$D$9:$D$42,'Reference Sheet'!$A$9:$A$42,C16,'Reference Sheet'!$B$9:$B$42,B16)) -> 176 | AC16: =AB16-AA16 -> -4 | AD16: =(G16/$AA16)*$AB16 -> 0 | AE16: =(H16/$AA16)*$AB16 -> 0 | AF16: =(I16/$AA16)*$AB16 -> 0 | AG16: =(J16/$AA16)*$AB16 -> 0 | AH16: =(K16/$AA16)*$AB16 -> 0 | AI16: =(L16/$AA16)*$AB16 -> 0 | AJ16: =(M16/$AA16)*$AB16 -> 97.777778 | AK16: =(N16/$AA16)*$AB16 -> 0 | ... AW16: =(Z16/$AA16)*$AB16 -> 0 | AX16: =SUM(AF16:AW16) -> 176 | AY16: =$F16*AD16 -> 0 | AZ16: =$F16*AE16 -> 0 | BA16: =$F16*AF16 -> 0 | BB16: =$F16*AG16 -> 0 | BC16: =$F16*AH16 -> 0 | BD16: =$F16*AI16 -> 0 | BE16: =$F16*AJ16 -> 4507.5469 | BF16: =$F16*AK16 -> 0 | ... BR16: =$F16*AW16 -> 0
A17: Engel | B17: July | C17: 2025 | D17: =INDEX('Reference Sheet'!$G$9:$J$100, MATCH(A17,'Reference Sheet'!$F$9:$F$100,0), MATCH(C17,'Reference Sheet'!$G$8:$J$8,0))/2080 -> 37.647947 | E17: =VLOOKUP(C17,'Reference Sheet'!$A$2:$B$5,2) -> 0.2245 | F17: =D17*(1+E17) -> 46.099911 | M17: 100 | S17: 80 | AA17: =SUM(G17:Z17) -> 180 | AB17: =IF(OR(B17="",C17=""),"",SUMIFS('Reference Sheet'!$D$9:$D$42,'Reference Sheet'!$A$9:$A$42,C17,'Reference Sheet'!$B$9:$B$42,B17)) -> 184 | AC17: =AB17-AA17 -> 4 | AD17: =(G17/$AA17)*$AB17 -> 0 | AE17: =(H17/$AA17)*$AB17 -> 0 | AF17: =(I17/$AA17)*$AB17 -> 0 | AG17: =(J17/$AA17)*$AB17 -> 0 | AH17: =(K17/$AA17)*$AB17 -> 0 | AI17: =(L17/$AA17)*$AB17 -> 0 | AJ17: =(M17/$AA17)*$AB17 -> 102.22222 | AK17: =(N17/$AA17)*$AB17 -> 0 | ... AW17: =(Z17/$AA17)*$AB17 -> 0 | AX17: =SUM(AF17:AW17) -> 184 | AY17: =$F17*AD17 -> 0 | AZ17: =$F17*AE17 -> 0 | BA17: =$F17*AF17 -> 0 | BB17: =$F17*AG17 -> 0 | BC17: =$F17*AH17 -> 0 | BD17: =$F17*AI17 -> 0 | BE17: =$F17*AJ17 -> 4712.4354 | BF17: =$F17*AK17 -> 0 | ... BR17: =$F17*AW17 -> 0
A18: Engel | B18: August | C18: 2025 | D18: =INDEX('Reference Sheet'!$G$9:$J$100, MATCH(A18,'Reference Sheet'!$F$9:$F$100,0), MATCH(C18,'Reference Sheet'!$G$8:$J$8,0))/2080 -> 37.647947 | E18: =VLOOKUP(C18,'Reference Sheet'!$A$2:$B$5,2) -> 0.2245 | F18: =D18*(1+E18) -> 46.099911 | M18: 100 | S18: 80 | AA18: =SUM(G18:Z18) -> 180 | AB18: =IF(OR(B18="",C18=""),"",SUMIFS('Reference Sheet'!$D$9:$D$42,'Reference Sheet'!$A$9:$A$42,C18,'Reference Sheet'!$B$9:$B$42,B18)) -> 168 | AC18: =AB18-AA18 -> -12 | AD18: =(G18/$AA18)*$AB18 -> 0 | AE18: =(H18/$AA18)*$AB18 -> 0 | AF18: =(I18/$AA18)*$AB18 -> 0 | AG18: =(J18/$AA18)*$AB18 -> 0 | AH18: =(K18/$AA18)*$AB18 -> 0 | AI18: =(L18/$AA18)*$AB18 -> 0 | AJ18: =(M18/$AA18)*$AB18 -> 93.333333 | AK18: =(N18/$AA18)*$AB18 -> 0 | ... AW18: =(Z18/$AA18)*$AB18 -> 0 | AX18: =SUM(AF18:AW18) -> 168 | AY18: =$F18*AD18 -> 0 | AZ18: =$F18*AE18 -> 0 | BA18: =$F18*AF18 -> 0 | BB18: =$F18*AG18 -> 0 | BC18: =$F18*AH18 -> 0 | BD18: =$F18*AI18 -> 0 | BE18: =$F18*AJ18 -> 4302.6584 | BF18: =$F18*AK18 -> 0 | ... BR18: =$F18*AW18 -> 0
A19: Engel | B19: September | C19: 2025 | D19: =INDEX('Reference Sheet'!$G$9:$J$100, MATCH(A19,'Reference Sheet'!$F$9:$F$100,0), MATCH(C19,'Reference Sheet'!$G$8:$J$8,0))/2080 -> 37.647947 | E19: =VLOOKUP(C19,'Reference Sheet'!$A$2:$B$5,2) -> 0.2245 | F19: =D19*(1+E19) -> 46.099911 | M19: 100 | S19: 80 | AA19: =SUM(G19:Z19) -> 180 | AB19: =IF(OR(B19="",C19=""),"",SUMIFS('Reference Sheet'!$D$9:$D$42,'Reference Sheet'!$A$9:$A$42,C19,'Reference Sheet'!$B$9:$B$42,B19)) -> 176 | AC19: =AB19-AA19 -> -4 | AD19: =(G19/$AA19)*$AB19 -> 0 | AE19: =(H19/$AA19)*$AB19 -> 0 | AF19: =(I19/$AA19)*$AB19 -> 0 | AG19: =(J19/$AA19)*$AB19 -> 0 | AH19: =(K19/$AA19)*$AB19 -> 0 | AI19: =(L19/$AA19)*$AB19 -> 0 | AJ19: =(M19/$AA19)*$AB19 -> 97.777778 | AK19: =(N19/$AA19)*$AB19 -> 0 | ... AW19: =(Z19/$AA19)*$AB19 -> 0 | AX19: =SUM(AF19:AW19) -> 176 | AY19: =$F19*AD19 -> 0 | AZ19: =$F19*AE19 -> 0 | BA19: =$F19*AF19 -> 0 | BB19: =$F19*AG19 -> 0 | BC19: =$F19*AH19 -> 0 | BD19: =$F19*AI19 -> 0 | BE19: =$F19*AJ19 -> 4507.5469 | BF19: =$F19*AK19 -> 0 | ... BR19: =$F19*AW19 -> 0
A20: Engel | B20: October | C20: 2025 | D20: =INDEX('Reference Sheet'!$G$9:$J$100, MATCH(A20,'Reference Sheet'!$F$9:$F$100,0), MATCH(C20,'Reference Sheet'!$G$8:$J$8,0))/2080 -> 37.647947 | E20: =VLOOKUP(C20,'Reference Sheet'!$A$2:$B$5,2) -> 0.2245 | F20: =D20*(1+E20) -> 46.099911 | M20: 100 | S20: 80 | AA20: =SUM(G20:Z20) -> 180 | AB20: =IF(OR(B20="",C20=""),"",SUMIFS('Reference Sheet'!$D$9:$D$42,'Reference Sheet'!$A$9:$A$42,C20,'Reference Sheet'!$B$9:$B$42,B20)) -> 184 | AC20: =AB20-AA20 -> 4 | AD20: =(G20/$AA20)*$AB20 -> 0 | AE20: =(H20/$AA20)*$AB20 -> 0 | AF20: =(I20/$AA20)*$AB20 -> 0 | AG20: =(J20/$AA20)*$AB20 -> 0 | AH20: =(K20/$AA20)*$AB20 -> 0 | AI20: =(L20/$AA20)*$AB20 -> 0 | AJ20: =(M20/$AA20)*$AB20 -> 102.22222 | AK20: =(N20/$AA20)*$AB20 -> 0 | ... AW20: =(Z20/$AA20)*$AB20 -> 0 | AX20: =SUM(AF20:AW20) -> 184 | AY20: =$F20*AD20 -> 0 | AZ20: =$F20*AE20 -> 0 | BA20: =$F20*AF20 -> 0 | BB20: =$F20*AG20 -> 0 | BC20: =$F20*AH20 -> 0 | BD20: =$F20*AI20 -> 0 | BE20: =$F20*AJ20 -> 4712.4354 | BF20: =$F20*AK20 -> 0 | ... BR20: =$F20*AW20 -> 0
A21: Engel | B21: November | C21: 2025 | D21: =INDEX('Reference Sheet'!$G$9:$J$100, MATCH(A21,'Reference Sheet'!$F$9:$F$100,0), MATCH(C21,'Reference Sheet'!$G$8:$J$8,0))/2080 -> 37.647947 | E21: =VLOOKUP(C21,'Reference Sheet'!$A$2:$B$5,2) -> 0.2245 | F21: =D21*(1+E21) -> 46.099911 | M21: 100 | S21: 80 | AA21: =SUM(G21:Z21) -> 180 | AB21: =IF(OR(B21="",C21=""),"",SUMIFS('Reference Sheet'!$D$9:$D$42,'Reference Sheet'!$A$9:$A$42,C21,'Reference Sheet'!$B$9:$B$42,B21)) -> 160 | AC21: =AB21-AA21 -> -20 | AD21: =(G21/$AA21)*$AB21 -> 0 | AE21: =(H21/$AA21)*$AB21 -> 0 | AF21: =(I21/$AA21)*$AB21 -> 0 | AG21: =(J21/$AA21)*$AB21 -> 0 | AH21: =(K21/$AA21)*$AB21 -> 0 | AI21: =(L21/$AA21)*$AB21 -> 0 | AJ21: =(M21/$AA21)*$AB21 -> 88.888889 | AK21: =(N21/$AA21)*$AB21 -> 0 | ... AW21: =(Z21/$AA21)*$AB21 -> 0 | AX21: =SUM(AF21:AW21) -> 160 | AY21: =$F21*AD21 -> 0 | AZ21: =$F21*AE21 -> 0 | BA21: =$F21*AF21 -> 0 | BB21: =$F21*AG21 -> 0 | BC21: =$F21*AH21 -> 0 | BD21: =$F21*AI21 -> 0 | BE21: =$F21*AJ21 -> 4097.7699 | BF21: =$F21*AK21 -> 0 | ... BR21: =$F21*AW21 -> 0
A22: Engel | B22: December | C22: 2025 | D22: =INDEX('Reference Sheet'!$G$9:$J$100, MATCH(A22,'Reference Sheet'!$F$9:$F$100,0), MATCH(C22,'Reference Sheet'!$G$8:$J$8,0))/2080 -> 37.647947 | E22: =VLOOKUP(C22,'Reference Sheet'!$A$2:$B$5,2) -> 0.2245 | F22: =D22*(1+E22) -> 46.099911 | M22: 100 | S22: 80 | AA22: =SUM(G22:Z22) -> 180 | AB22: =IF(OR(B22="",C22=""),"",SUMIFS('Reference Sheet'!$D$9:$D$42,'Reference Sheet'!$A$9:$A$42,C22,'Reference Sheet'!$B$9:$B$42,B22)) -> 184 | AC22: =AB22-AA22 -> 4 | AD22: =(G22/$AA22)*$AB22 -> 0 | AE22: =(H22/$AA22)*$AB22 -> 0 | AF22: =(I22/$AA22)*$AB22 -> 0 | AG22: =(J22/$AA22)*$AB22 -> 0 | AH22: =(K22/$AA22)*$AB22 -> 0 | AI22: =(L22/$AA22)*$AB22 -> 0 | AJ22: =(M22/$AA22)*$AB22 -> 102.22222 | AK22: =(N22/$AA22)*$AB22 -> 0 | ... AW22: =(Z22/$AA22)*$AB22 -> 0 | AX22: =SUM(AF22:AW22) -> 184 | AY22: =$F22*AD22 -> 0 | AZ22: =$F22*AE22 -> 0 | BA22: =$F22*AF22 -> 0 | BB22: =$F22*AG22 -> 0 | BC22: =$F22*AH22 -> 0 | BD22: =$F22*AI22 -> 0 | BE22: =$F22*AJ22 -> 4712.4354 | BF22: =$F22*AK22 -> 0 | ... BR22: =$F22*AW22 -> 0
A23: Engel | B23: June | C23: 2025 | D23: =INDEX('Reference Sheet'!$G$9:$J$100, MATCH(A23,'Reference Sheet'!$F$9:$F$100,0), MATCH(C23,'Reference Sheet'!$G$8:$J$8,0))/2080 -> 37.647947 | E23: =VLOOKUP(C23,'Reference Sheet'!$A$2:$B$5,2) -> 0.2245 | F23: =D23*(1+E23) -> 46.099911 | M23: 100 | S23: 92 | AA23: =SUM(G23:Z23) -> 192 | AB23: =IF(OR(B23="",C23=""),"",SUMIFS('Reference Sheet'!$D$9:$D$42,'Reference Sheet'!$A$9:$A$42,C23,'Reference Sheet'!$B$9:$B$42,B23)) -> 168 | AC23: =AB23-AA23 -> -24 | AD23: =(G23/$AA23)*$AB23 -> 0 | AE23: =(H23/$AA23)*$AB23 -> 0 | AF23: =(I23/$AA23)*$AB23 -> 0 | AG23: =(J23/$AA23)*$AB23 -> 0 | AH23: =(K23/$AA23)*$AB23 -> 0 | AI23: =(L23/$AA23)*$AB23 -> 0 | AJ23: =(M23/$AA23)*$AB23 -> 87.5 | AK23: =(N23/$AA23)*$AB23 -> 0 | ... AW23: =(Z23/$AA23)*$AB23 -> 0 | AX23: =SUM(AF23:AW23) -> 168 | AY23: =$F23*AD23 -> 0 | AZ23: =$F23*AE23 -> 0 | BA23: =$F23*AF23 -> 0 | BB23: =$F23*AG23 -> 0 | BC23: =$F23*AH23 -> 0 | BD23: =$F23*AI23 -> 0 | BE23: =$F23*AJ23 -> 4033.7422 | BF23: =$F23*AK23 -> 0 | ... BR23: =$F23*AW23 -> 0
... A30: Engel | B30: July | C30: 2026 | D30: =INDEX('Reference Sheet'!$G$9:$J$100, MATCH(A30,'Reference Sheet'!$F$9:$F$100,0), MATCH(C30,'Reference Sheet'!$G$8:$J$8,0))/2080 -> 38.942308 | E30: =VLOOKUP(C30,'Reference Sheet'!$A$2:$B$5,2) -> 0.2363 | F30: =D30*(1+E30) -> 48.144375 | M30: 8 | S30: 188 | AA30: =SUM(G30:Z30) -> 196 | AB30: =IF(OR(B30="",C30=""),"",SUMIFS('Reference Sheet'!$D$9:$D$42,'Reference Sheet'!$A$9:$A$42,C30,'Reference Sheet'!$B$9:$B$42,B30)) -> 184 | AC30: =AB30-AA30 -> -12 | AD30: =(G30/$AA30)*$AB30 -> 0 | AE30: =(H30/$AA30)*$AB30 -> 0 | AF30: =(I30/$AA30)*$AB30 -> 0 | AG30: =(J30/$AA30)*$AB30 -> 0 | AH30: =(K30/$AA30)*$AB30 -> 0 | AI30: =(L30/$AA30)*$AB30 -> 0 | AJ30: =(M30/$AA30)*$AB30 -> 7.5102041 | AK30: =(N30/$AA30)*$AB30 -> 0 | ... AW30: =(Z30/$AA30)*$AB30 -> 0 | AX30: =SUM(AF30:AW30) -> 184 | AY30: =$F30*AD30 -> 0 | AZ30: =$F30*AE30 -> 0 | BA30: =$F30*AF30 -> 0 | BB30: =$F30*AG30 -> 0 | BC30: =$F30*AH30 -> 0 | BD30: =$F30*AI30 -> 0 | BE30: =$F30*AJ30 -> 361.57408 | BF30: =$F30*AK30 -> 0 | ... BR30: =$F30*AW30 -> 0
A31: Engel | B31: August | C31: 2026 | D31: =INDEX('Reference Sheet'!$G$9:$J$100, MATCH(A31,'Reference Sheet'!$F$9:$F$100,0), MATCH(C31,'Reference Sheet'!$G$8:$J$8,0))/2080 -> 38.942308 | E31: =VLOOKUP(C31,'Reference Sheet'!$A$2:$B$5,2) -> 0.2363 | F31: =D31*(1+E31) -> 48.144375 | M31: 22 | S31: 156 | AA31: =SUM(G31:Z31) -> 178 | AB31: =IF(OR(B31="",C31=""),"",SUMIFS('Reference Sheet'!$D$9:$D$44,'Reference Sheet'!$A$9:$A$44,C31,'Reference Sheet'!$B$9:$B$44,B31)) -> 176 | AC31: =AB31-AA31 -> -2 | AD31: =(G31/$AA31)*$AB31 -> 0 | AE31: =(H31/$AA31)*$AB31 -> 0 | AF31: =(I31/$AA31)*$AB31 -> 0 | AG31: =(J31/$AA31)*$AB31 -> 0 | AH31: =(K31/$AA31)*$AB31 -> 0 | AI31: =(L31/$AA31)*$AB31 -> 0 | AJ31: =(M31/$AA31)*$AB31 -> 21.752809 | AK31: =(N31/$AA31)*$AB31 -> 0 | ... AW31: =(Z31/$AA31)*$AB31 -> 0 | AX31: =SUM(AF31:AW31) -> 176 | AY31: =$F31*AD31 -> 0 | AZ31: =$F31*AE31 -> 0 | BA31: =$F31*AF31 -> 0 | BB31: =$F31*AG31 -> 0 | BC31: =$F31*AH31 -> 0 | BD31: =$F31*AI31 -> 0 | BE31: =$F31*AJ31 -> 1047.2754 | BF31: =$F31*AK31 -> 0 | ... BR31: =$F31*AW31 -> 0
A32: Ewing | B32: October | C32: 2023 | D32: =INDEX('Reference Sheet'!$G$9:$J$100, MATCH(A32,'Reference Sheet'!$F$9:$F$100,0), MATCH(C32,'Reference Sheet'!$G$8:$J$8,0))/2080 -> 71.291462 | E32: =VLOOKUP(C32,'Reference Sheet'!$A$2:$B$5,2) -> 0.2136 | F32: =D32*(1+E32) -> 86.519318 | Q32: 4.8 | AA32: =SUM(G32:Z32) -> 4.8 | AB32: =AA32 -> 4.8 | AC32: =AB32-AA32 -> 0 | AD32: =(G32/$AA32)*$AB32 -> 0 | AE32: =(H32/$AA32)*$AB32 -> 0 | AF32: =(I32/$AA32)*$AB32 -> 0 | AG32: =(J32/$AA32)*$AB32 -> 0 | AH32: =(K32/$AA32)*$AB32 -> 0 | AI32: =(L32/$AA32)*$AB32 -> 0 | AJ32: =(M32/$AA32)*$AB32 -> 0 | AK32: =(N32/$AA32)*$AB32 -> 0 | ... AW32: =(Z32/$AA32)*$AB32 -> 0 | AX32: =SUM(AF32:AW32) -> 4.8 | AY32: =$F32*AD32 -> 0 | AZ32: =$F32*AE32 -> 0 | BA32: =$F32*AF32 -> 0 | BB32: =$F32*AG32 -> 0 | BC32: =$F32*AH32 -> 0 | BD32: =$F32*AI32 -> 0 | BE32: =$F32*AJ32 -> 0 | BF32: =$F32*AK32 -> 0 | ... BR32: =$F32*AW32 -> 0
A33: Ewing | B33: November | C33: 2023 | D33: =INDEX('Reference Sheet'!$G$9:$J$100, MATCH(A33,'Reference Sheet'!$F$9:$F$100,0), MATCH(C33,'Reference Sheet'!$G$8:$J$8,0))/2080 -> 71.291462 | E33: =VLOOKUP(C33,'Reference Sheet'!$A$2:$B$5,2) -> 0.2136 | F33: =D33*(1+E33) -> 86.519318 | Q33: 4.8 | AA33: =SUM(G33:Z33) -> 4.8 | AB33: =AA33 -> 4.8 | AC33: =AB33-AA33 -> 0 | AD33: =(G33/$AA33)*$AB33 -> 0 | AE33: =(H33/$AA33)*$AB33 -> 0 | AF33: =(I33/$AA33)*$AB33 -> 0 | AG33: =(J33/$AA33)*$AB33 -> 0 | AH33: =(K33/$AA33)*$AB33 -> 0 | AI33: =(L33/$AA33)*$AB33 -> 0 | AJ33: =(M33/$AA33)*$AB33 -> 0 | AK33: =(N33/$AA33)*$AB33 -> 0 | ... AW33: =(Z33/$AA33)*$AB33 -> 0 | AX33: =SUM(AF33:AW33) -> 4.8 | AY33: =$F33*AD33 -> 0 | AZ33: =$F33*AE33 -> 0 | BA33: =$F33*AF33 -> 0 | BB33: =$F33*AG33 -> 0 | BC33: =$F33*AH33 -> 0 | BD33: =$F33*AI33 -> 0 | BE33: =$F33*AJ33 -> 0 | BF33: =$F33*AK33 -> 0 | ... BR33: =$F33*AW33 -> 0
A34: Ewing | B34: December | C34: 2023 | D34: =INDEX('Reference Sheet'!$G$9:$J$100, MATCH(A34,'Reference Sheet'!$F$9:$F$100,0), MATCH(C34,'Reference Sheet'!$G$8:$J$8,0))/2080 -> 71.291462 | E34: =VLOOKUP(C34,'Reference Sheet'!$A$2:$B$5,2) -> 0.2136 | F34: =D34*(1+E34) -> 86.519318 | Q34: 4.8 | AA34: =SUM(G34:Z34) -> 4.8 | AB34: =AA34 -> 4.8 | AC34: =AB34-AA34 -> 0 | AD34: =(G34/$AA34)*$AB34 -> 0 | AE34: =(H34/$AA34)*$AB34 -> 0 | AF34: =(I34/$AA34)*$AB34 -> 0 | AG34: =(J34/$AA34)*$AB34 -> 0 | AH34: =(K34/$AA34)*$AB34 -> 0 | AI34: =(L34/$AA34)*$AB34 -> 0 | AJ34: =(M34/$AA34)*$AB34 -> 0 | AK34: =(N34/$AA34)*$AB34 -> 0 | ... AW34: =(Z34/$AA34)*$AB34 -> 0 | AX34: =SUM(AF34:AW34) -> 4.8 | AY34: =$F34*AD34 -> 0 | AZ34: =$F34*AE34 -> 0 | BA34: =$F34*AF34 -> 0 | BB34: =$F34*AG34 -> 0 | BC34: =$F34*AH34 -> 0 | BD34: =$F34*AI34 -> 0 | BE34: =$F34*AJ34 -> 0 | BF34: =$F34*AK34 -> 0 | ... BR34: =$F34*AW34 -> 0
A35: Ewing | B35: January | C35: 2024 | D35: =INDEX('Reference Sheet'!$G$9:$J$100, MATCH(A35,'Reference Sheet'!$F$9:$F$100,0), MATCH(C35,'Reference Sheet'!$G$8:$J$8,0))/2080 -> 81.091389 | E35: =VLOOKUP(C35,'Reference Sheet'!$A$2:$B$5,2) -> 0.1913 | F35: =D35*(1+E35) -> 96.604172 | Q35: 4.8 | AA35: =SUM(G35:Z35) -> 4.8 | AB35: =AA35 -> 4.8 | AC35: =AB35-AA35 -> 0 | AD35: =(G35/$AA35)*$AB35 -> 0 | AE35: =(H35/$AA35)*$AB35 -> 0 | AF35: =(I35/$AA35)*$AB35 -> 0 | AG35: =(J35/$AA35)*$AB35 -> 0 | AH35: =(K35/$AA35)*$AB35 -> 0 | AI35: =(L35/$AA35)*$AB35 -> 0 | AJ35: =(M35/$AA35)*$AB35 -> 0 | AK35: =(N35/$AA35)*$AB35 -> 0 | ... AW35: =(Z35/$AA35)*$AB35 -> 0 | AX35: =SUM(AF35:AW35) -> 4.8 | AY35: =$F35*AD35 -> 0 | AZ35: =$F35*AE35 -> 0 | BA35: =$F35*AF35 -> 0 | BB35: =$F35*AG35 -> 0 | BC35: =$F35*AH35 -> 0 | BD35: =$F35*AI35 -> 0 | BE35: =$F35*AJ35 -> 0 | BF35: =$F35*AK35 -> 0 | ... BR35: =$F35*AW35 -> 0
A36: Ewing | B36: February | C36: 2024 | D36: =INDEX('Reference Sheet'!$G$9:$J$100, MATCH(A36,'Reference Sheet'!$F$9:$F$100,0), MATCH(C36,'Reference Sheet'!$G$8:$J$8,0))/2080 -> 81.091389 | E36: =VLOOKUP(C36,'Reference Sheet'!$A$2:$B$5,2) -> 0.1913 | F36: =D36*(1+E36) -> 96.604172 | Q36: 4.8 | AA36: =SUM(G36:Z36) -> 4.8 | AB36: =AA36 -> 4.8 | AC36: =AB36-AA36 -> 0 | AD36: =(G36/$AA36)*$AB36 -> 0 | AE36: =(H36/$AA36)*$AB36 -> 0 | AF36: =(I36/$AA36)*$AB36 -> 0 | AG36: =(J36/$AA36)*$AB36 -> 0 | AH36: =(K36/$AA36)*$AB36 -> 0 | AI36: =(L36/$AA36)*$AB36 -> 0 | AJ36: =(M36/$AA36)*$AB36 -> 0 | AK36: =(N36/$AA36)*$AB36 -> 0 | ... AW36: =(Z36/$AA36)*$AB36 -> 0 | AX36: =SUM(AF36:AW36) -> 4.8 | AY36: =$F36*AD36 -> 0 | AZ36: =$F36*AE36 -> 0 | BA36: =$F36*AF36 -> 0 | BB36: =$F36*AG36 -> 0 | BC36: =$F36*AH36 -> 0 | BD36: =$F36*AI36 -> 0 | BE36: =$F36*AJ36 -> 0 | BF36: =$F36*AK36 -> 0 | ... BR36: =$F36*AW36 -> 0
A37: Ewing | B37: March | C37: 2024 | D37: =INDEX('Reference Sheet'!$G$9:$J$100, MATCH(A37,'Reference Sheet'!$F$9:$F$100,0), MATCH(C37,'Reference Sheet'!$G$8:$J$8,0))/2080 -> 81.091389 | E37: =VLOOKUP(C37,'Reference Sheet'!$A$2:$B$5,2) -> 0.1913 | F37: =D37*(1+E37) -> 96.604172 | Q37: 4.8 | AA37: =SUM(G37:Z37) -> 4.8 | AB37: =AA37 -> 4.8 | AC37: =AB37-AA37 -> 0 | AD37: =(G37/$AA37)*$AB37 -> 0 | AE37: =(H37/$AA37)*$AB37 -> 0 | AF37: =(I37/$AA37)*$AB37 -> 0 | AG37: =(J37/$AA37)*$AB37 -> 0 | AH37: =(K37/$AA37)*$AB37 -> 0 | AI37: =(L37/$AA37)*$AB37 -> 0 | AJ37: =(M37/$AA37)*$AB37 -> 0 | AK37: =(N37/$AA37)*$AB37 -> 0 | ... AW37: =(Z37/$AA37)*$AB37 -> 0 | AX37: =SUM(AF37:AW37) -> 4.8 | AY37: =$F37*AD37 -> 0 | AZ37: =$F37*AE37 -> 0 | BA37: =$F37*AF37 -> 0 | BB37: =$F37*AG37 -> 0 | BC37: =$F37*AH37 -> 0 | BD37: =$F37*AI37 -> 0 | BE37: =$F37*AJ37 -> 0 | BF37: =$F37*AK37 -> 0 | ... BR37: =$F37*AW37 -> 0
A38: Ewing | B38: April | C38: 2024 | D38: =INDEX('Reference Sheet'!$G$9:$J$100, MATCH(A38,'Reference Sheet'!$F$9:$F$100,0), MATCH(C38,'Reference Sheet'!$G$8:$J$8,0))/2080 -> 81.091389 | E38: =VLOOKUP(C38,'Reference Sheet'!$A$2:$B$5,2) -> 0.1913 | F38: =D38*(1+E38) -> 96.604172 | Q38: 4.8 | AA38: =SUM(G38:Z38) -> 4.8 | AB38: =AA38 -> 4.8 | AC38: =AB38-AA38 -> 0 | AD38: =(G38/$AA38)*$AB38 -> 0 | AE38: =(H38/$AA38)*$AB38 -> 0 | AF38: =(I38/$AA38)*$AB38 -> 0 | AG38: =(J38/$AA38)*$AB38 -> 0 | AH38: =(K38/$AA38)*$AB38 -> 0 | AI38: =(L38/$AA38)*$AB38 -> 0 | AJ38: =(M38/$AA38)*$AB38 -> 0 | AK38: =(N38/$AA38)*$AB38 -> 0 | ... AW38: =(Z38/$AA38)*$AB38 -> 0 | AX38: =SUM(AF38:AW38) -> 4.8 | AY38: =$F38*AD38 -> 0 | AZ38: =$F38*AE38 -> 0 | BA38: =$F38*AF38 -> 0 | BB38: =$F38*AG38 -> 0 | BC38: =$F38*AH38 -> 0 | BD38: =$F38*AI38 -> 0 | BE38: =$F38*AJ38 -> 0 | BF38: =$F38*AK38 -> 0 | ... BR38: =$F38*AW38 -> 0
A39: Ewing | B39: May | C39: 2024 | D39: =INDEX('Reference Sheet'!$G$9:$J$100, MATCH(A39,'Reference Sheet'!$F$9:$F$100,0), MATCH(C39,'Reference Sheet'!$G$8:$J$8,0))/2080 -> 81.091389 | E39: =VLOOKUP(C39,'Reference Sheet'!$A$2:$B$5,2) -> 0.1913 | F39: =D39*(1+E39) -> 96.604172 | Q39: 4.8 | AA39: =SUM(G39:Z39) -> 4.8 | AB39: =AA39 -> 4.8 | AC39: =AB39-AA39 -> 0 | AD39: =(G39/$AA39)*$AB39 -> 0 | AE39: =(H39/$AA39)*$AB39 -> 0 | AF39: =(I39/$AA39)*$AB39 -> 0 | AG39: =(J39/$AA39)*$AB39 -> 0 | AH39: =(K39/$AA39)*$AB39 -> 0 | AI39: =(L39/$AA39)*$AB39 -> 0 | AJ39: =(M39/$AA39)*$AB39 -> 0 | AK39: =(N39/$AA39)*$AB39 -> 0 | ... AW39: =(Z39/$AA39)*$AB39 -> 0 | AX39: =SUM(AF39:AW39) -> 4.8 | AY39: =$F39*AD39 -> 0 | AZ39: =$F39*AE39 -> 0 | BA39: =$F39*AF39 -> 0 | BB39: =$F39*AG39 -> 0 | BC39: =$F39*AH39 -> 0 | BD39: =$F39*AI39 -> 0 | BE39: =$F39*AJ39 -> 0 | BF39: =$F39*AK39 -> 0 | ... BR39: =$F39*AW39 -> 0
A40: Ewing | B40: June | C40: 2024 | D40: =INDEX('Reference Sheet'!$G$9:$J$100, MATCH(A40,'Reference Sheet'!$F$9:$F$100,0), MATCH(C40,'Reference Sheet'!$G$8:$J$8,0))/2080 -> 81.091389 | E40: =VLOOKUP(C40,'Reference Sheet'!$A$2:$B$5,2) -> 0.1913 | F40: =D40*(1+E40) -> 96.604172 | Q40: 4.8 | AA40: =SUM(G40:Z40) -> 4.8 | AB40: =AA40 -> 4.8 | AC40: =AB40-AA40 -> 0 | AD40: =(G40/$AA40)*$AB40 -> 0 | AE40: =(H40/$AA40)*$AB40 -> 0 | AF40: =(I40/$AA40)*$AB40 -> 0 | AG40: =(J40/$AA40)*$AB40 -> 0 | AH40: =(K40/$AA40)*$AB40 -> 0 | AI40: =(L40/$AA40)*$AB40 -> 0 | AJ40: =(M40/$AA40)*$AB40 -> 0 | AK40: =(N40/$AA40)*$AB40 -> 0 | ... AW40: =(Z40/$AA40)*$AB40 -> 0 | AX40: =SUM(AF40:AW40) -> 4.8 | AY40: =$F40*AD40 -> 0 | AZ40: =$F40*AE40 -> 0 | BA40: =$F40*AF40 -> 0 | BB40: =$F40*AG40 -> 0 | BC40: =$F40*AH40 -> 0 | BD40: =$F40*AI40 -> 0 | BE40: =$F40*AJ40 -> 0 | BF40: =$F40*AK40 -> 0 | ... BR40: =$F40*AW40 -> 0
A41: Ewing | B41: July | C41: 2024 | D41: =INDEX('Reference Sheet'!$G$9:$J$100, MATCH(A41,'Reference Sheet'!$F$9:$F$100,0), MATCH(C41,'Reference Sheet'!$G$8:$J$8,0))/2080 -> 81.091389 | E41: =VLOOKUP(C41,'Reference Sheet'!$A$2:$B$5,2) -> 0.1913 | F41: =D41*(1+E41) -> 96.604172 | Q41: 4.8 | AA41: =SUM(G41:Z41) -> 4.8 | AB41: =AA41 -> 4.8 | AC41: =AB41-AA41 -> 0 | AD41: =(G41/$AA41)*$AB41 -> 0 | AE41: =(H41/$AA41)*$AB41 -> 0 | AF41: =(I41/$AA41)*$AB41 -> 0 | AG41: =(J41/$AA41)*$AB41 -> 0 | AH41: =(K41/$AA41)*$AB41 -> 0 | AI41: =(L41/$AA41)*$AB41 -> 0 | AJ41: =(M41/$AA41)*$AB41 -> 0 | AK41: =(N41/$AA41)*$AB41 -> 0 | ... AW41: =(Z41/$AA41)*$AB41 -> 0 | AX41: =SUM(AF41:AW41) -> 4.8 | AY41: =$F41*AD41 -> 0 | AZ41: =$F41*AE41 -> 0 | BA41: =$F41*AF41 -> 0 | BB41: =$F41*AG41 -> 0 | BC41: =$F41*AH41 -> 0 | BD41: =$F41*AI41 -> 0 | BE41: =$F41*AJ41 -> 0 | BF41: =$F41*AK41 -> 0 | ... BR41: =$F41*AW41 -> 0
A42: Ewing | B42: August | C42: 2024 | D42: =INDEX('Reference Sheet'!$G$9:$J$100, MATCH(A42,'Reference Sheet'!$F$9:$F$100,0), MATCH(C42,'Reference Sheet'!$G$8:$J$8,0))/2080 -> 81.091389 | E42: =VLOOKUP(C42,'Reference Sheet'!$A$2:$B$5,2) -> 0.1913 | F42: =D42*(1+E42) -> 96.604172 | Q42: 4.8 | AA42: =SUM(G42:Z42) -> 4.8 | AB42: =AA42 -> 4.8 | AC42: =AB42-AA42 -> 0 | AD42: =(G42/$AA42)*$AB42 -> 0 | AE42: =(H42/$AA42)*$AB42 -> 0 | AF42: =(I42/$AA42)*$AB42 -> 0 | AG42: =(J42/$AA42)*$AB42 -> 0 | AH42: =(K42/$AA42)*$AB42 -> 0 | AI42: =(L42/$AA42)*$AB42 -> 0 | AJ42: =(M42/$AA42)*$AB42 -> 0 | AK42: =(N42/$AA42)*$AB42 -> 0 | ... AW42: =(Z42/$AA42)*$AB42 -> 0 | AX42: =SUM(AF42:AW42) -> 4.8 | AY42: =$F42*AD42 -> 0 | AZ42: =$F42*AE42 -> 0 | BA42: =$F42*AF42 -> 0 | BB42: =$F42*AG42 -> 0 | BC42: =$F42*AH42 -> 0 | BD42: =$F42*AI42 -> 0 | BE42: =$F42*AJ42 -> 0 | BF42: =$F42*AK42 -> 0 | ... BR42: =$F42*AW42 -> 0
A43: Ewing | B43: September | C43: 2024 | D43: =INDEX('Reference Sheet'!$G$9:$J$100, MATCH(A43,'Reference Sheet'!$F$9:$F$100,0), MATCH(C43,'Reference Sheet'!$G$8:$J$8,0))/2080 -> 81.091389 | E43: =VLOOKUP(C43,'Reference Sheet'!$A$2:$B$5,2) -> 0.1913 | F43: =D43*(1+E43) -> 96.604172 | Q43: 4.8 | AA43: =SUM(G43:Z43) -> 4.8 | AB43: =AA43 -> 4.8 | AC43: =AB43-AA43 -> 0 | AD43: =(G43/$AA43)*$AB43 -> 0 | AE43: =(H43/$AA43)*$AB43 -> 0 | AF43: =(I43/$AA43)*$AB43 -> 0 | AG43: =(J43/$AA43)*$AB43 -> 0 | AH43: =(K43/$AA43)*$AB43 -> 0 | AI43: =(L43/$AA43)*$AB43 -> 0 | AJ43: =(M43/$AA43)*$AB43 -> 0 | AK43: =(N43/$AA43)*$AB43 -> 0 | ... AW43: =(Z43/$AA43)*$AB43 -> 0 | AX43: =SUM(AF43:AW43) -> 4.8 | AY43: =$F43*AD43 -> 0 | AZ43: =$F43*AE43 -> 0 | BA43: =$F43*AF43 -> 0 | BB43: =$F43*AG43 -> 0 | BC43: =$F43*AH43 -> 0 | BD43: =$F43*AI43 -> 0 | BE43: =$F43*AJ43 -> 0 | BF43: =$F43*AK43 -> 0 | ... BR43: =$F43*AW43 -> 0
... A46: Ewing | B46: December | C46: 2024 | D46: =INDEX('Reference Sheet'!$G$9:$J$100, MATCH(A46,'Reference Sheet'!$F$9:$F$100,0), MATCH(C46,'Reference Sheet'!$G$8:$J$8,0))/2080 -> 81.091389 | E46: =VLOOKUP(C46,'Reference Sheet'!$A$2:$B$5,2) -> 0.1913 | F46: =D46*(1+E46) -> 96.604172 | Q46: 4.8 | AA46: =SUM(G46:Z46) -> 4.8 | AB46: =AA46 -> 4.8 | AC46: =AB46-AA46 -> 0 | AD46: =(G46/$AA46)*$AB46 -> 0 | AE46: =(H46/$AA46)*$AB46 -> 0 | AF46: =(I46/$AA46)*$AB46 -> 0 | AG46: =(J46/$AA46)*$AB46 -> 0 | AH46: =(K46/$AA46)*$AB46 -> 0 | AI46: =(L46/$AA46)*$AB46 -> 0 | AJ46: =(M46/$AA46)*$AB46 -> 0 | AK46: =(N46/$AA46)*$AB46 -> 0 | ... AW46: =(Z46/$AA46)*$AB46 -> 0 | AX46: =SUM(AF46:AW46) -> 4.8 | AY46: =$F46*AD46 -> 0 | AZ46: =$F46*AE46 -> 0 | BA46: =$F46*AF46 -> 0 | BB46: =$F46*AG46 -> 0 | BC46: =$F46*AH46 -> 0 | BD46: =$F46*AI46 -> 0 | BE46: =$F46*AJ46 -> 0 | BF46: =$F46*AK46 -> 0 | ... BR46: =$F46*AW46 -> 0
A47: Ewing | B47: January | C47: 2025 | D47: =INDEX('Reference Sheet'!$G$9:$J$100, MATCH(A47,'Reference Sheet'!$F$9:$F$100,0), MATCH(C47,'Reference Sheet'!$G$8:$J$8,0))/2080 -> 92.349582 | E47: =VLOOKUP(C47,'Reference Sheet'!$A$2:$B$5,2) -> 0.2245 | F47: =D47*(1+E47) -> 113.08206 | N47: 99.12 | O47: 10.53 | P47: 55 | Q47: 4.8 | T47: 4.375 | Y47: 1.625 | Z47: 29.47 | AA47: =SUM(G47:Z47) -> 204.92 | AB47: =IF(OR(B47="",C47=""),"",SUMIFS('Reference Sheet'!$D$9:$D$42,'Reference Sheet'!$A$9:$A$42,C47,'Reference Sheet'!$B$9:$B$42,B47)) -> 184 | AC47: =AB47-AA47 -> -20.92 | AD47: =(G47/$AA47)*$AB47 -> 0 | AE47: =(H47/$AA47)*$AB47 -> 0 | AF47: =(I47/$AA47)*$AB47 -> 0 | AG47: =(J47/$AA47)*$AB47 -> 0 | AH47: =(K47/$AA47)*$AB47 -> 0 | AI47: =(L47/$AA47)*$AB47 -> 0 | AJ47: =(M47/$AA47)*$AB47 -> 0 | AK47: =(N47/$AA47)*$AB47 -> 89.000976 | ... AW47: =(Z47/$AA47)*$AB47 -> 26.461448 | AX47: =SUM(AF47:AW47) -> 184 | AY47: =$F47*AD47 -> 0 | AZ47: =$F47*AE47 -> 0 | BA47: =$F47*AF47 -> 0 | BB47: =$F47*AG47 -> 0 | BC47: =$F47*AH47 -> 0 | BD47: =$F47*AI47 -> 0 | BE47: =$F47*AJ47 -> 0 | BF47: =$F47*AK47 -> 10064.414 | ... BR47: =$F47*AW47 -> 2992.3152
A48: Ewing | B48: February | C48: 2025 | D48: =INDEX('Reference Sheet'!$G$9:$J$100, MATCH(A48,'Reference Sheet'!$F$9:$F$100,0), MATCH(C48,'Reference Sheet'!$G$8:$J$8,0))/2080 -> 92.349582 | E48: =VLOOKUP(C48,'Reference Sheet'!$A$2:$B$5,2) -> 0.2245 | F48: =D48*(1+E48) -> 113.08206 | N48: 99.12 | O48: 10.53 | P48: 55 | Q48: 4.8 | T48: 4.375 | Y48: 1.625 | Z48: 29.47 | AA48: =SUM(G48:Z48) -> 204.92 | AB48: =IF(OR(B48="",C48=""),"",SUMIFS('Reference Sheet'!$D$9:$D$42,'Reference Sheet'!$A$9:$A$42,C48,'Reference Sheet'!$B$9:$B$42,B48)) -> 160 | AC48: =AB48-AA48 -> -44.92 | AD48: =(G48/$AA48)*$AB48 -> 0 | AE48: =(H48/$AA48)*$AB48 -> 0 | AF48: =(I48/$AA48)*$AB48 -> 0 | AG48: =(J48/$AA48)*$AB48 -> 0 | AH48: =(K48/$AA48)*$AB48 -> 0 | AI48: =(L48/$AA48)*$AB48 -> 0 | AJ48: =(M48/$AA48)*$AB48 -> 0 | AK48: =(N48/$AA48)*$AB48 -> 77.392153 | ... AW48: =(Z48/$AA48)*$AB48 -> 23.009955 | AX48: =SUM(AF48:AW48) -> 160 | AY48: =$F48*AD48 -> 0 | AZ48: =$F48*AE48 -> 0 | BA48: =$F48*AF48 -> 0 | BB48: =$F48*AG48 -> 0 | BC48: =$F48*AH48 -> 0 | BD48: =$F48*AI48 -> 0 | BE48: =$F48*AJ48 -> 0 | BF48: =$F48*AK48 -> 8751.6643 | ... BR48: =$F48*AW48 -> 2602.0132
A49: Ewing | B49: March | C49: 2025 | D49: =INDEX('Reference Sheet'!$G$9:$J$100, MATCH(A49,'Reference Sheet'!$F$9:$F$100,0), MATCH(C49,'Reference Sheet'!$G$8:$J$8,0))/2080 -> 92.349582 | E49: =VLOOKUP(C49,'Reference Sheet'!$A$2:$B$5,2) -> 0.2245 | F49: =D49*(1+E49) -> 113.08206 | N49: 99.12 | O49: 10.53 | P49: 55 | Q49: 4.8 | T49: 4.375 | Y49: 1.625 | Z49: 29.47 | AA49: =SUM(G49:Z49) -> 204.92 | AB49: =IF(OR(B49="",C49=""),"",SUMIFS('Reference Sheet'!$D$9:$D$42,'Reference Sheet'!$A$9:$A$42,C49,'Reference Sheet'!$B$9:$B$42,B49)) -> 168 | AC49: =AB49-AA49 -> -36.92 | AD49: =(G49/$AA49)*$AB49 -> 0 | AE49: =(H49/$AA49)*$AB49 -> 0 | AF49: =(I49/$AA49)*$AB49 -> 0 | AG49: =(J49/$AA49)*$AB49 -> 0 | AH49: =(K49/$AA49)*$AB49 -> 0 | AI49: =(L49/$AA49)*$AB49 -> 0 | AJ49: =(M49/$AA49)*$AB49 -> 0 | AK49: =(N49/$AA49)*$AB49 -> 81.261761 | ... AW49: =(Z49/$AA49)*$AB49 -> 24.160453 | AX49: =SUM(AF49:AW49) -> 168 | AY49: =$F49*AD49 -> 0 | AZ49: =$F49*AE49 -> 0 | BA49: =$F49*AF49 -> 0 | BB49: =$F49*AG49 -> 0 | BC49: =$F49*AH49 -> 0 | BD49: =$F49*AI49 -> 0 | BE49: =$F49*AJ49 -> 0 | BF49: =$F49*AK49 -> 9189.2475 | ... BR49: =$F49*AW49 -> 2732.1138
A50: Ewing | B50: April | C50: 2025 | D50: =INDEX('Reference Sheet'!$G$9:$J$100, MATCH(A50,'Reference Sheet'!$F$9:$F$100,0), MATCH(C50,'Reference Sheet'!$G$8:$J$8,0))/2080 -> 92.349582 | E50: =VLOOKUP(C50,'Reference Sheet'!$A$2:$B$5,2) -> 0.2245 | F50: =D50*(1+E50) -> 113.08206 | N50: 99.12 | O50: 10.53 | P50: 55 | Q50: 4.8 | T50: 4.375 | Y50: 1.625 | Z50: 29.47 | AA50: =SUM(G50:Z50) -> 204.92 | AB50: =IF(OR(B50="",C50=""),"",SUMIFS('Reference Sheet'!$D$9:$D$42,'Reference Sheet'!$A$9:$A$42,C50,'Reference Sheet'!$B$9:$B$42,B50)) -> 176 | AC50: =AB50-AA50 -> -28.92 | AD50: =(G50/$AA50)*$AB50 -> 0 | AE50: =(H50/$AA50)*$AB50 -> 0 | AF50: =(I50/$AA50)*$AB50 -> 0 | AG50: =(J50/$AA50)*$AB50 -> 0 | AH50: =(K50/$AA50)*$AB50 -> 0 | AI50: =(L50/$AA50)*$AB50 -> 0 | AJ50: =(M50/$AA50)*$AB50 -> 0 | AK50: =(N50/$AA50)*$AB50 -> 85.131368 | ... AW50: =(Z50/$AA50)*$AB50 -> 25.310951 | AX50: =SUM(AF50:AW50) -> 176 | AY50: =$F50*AD50 -> 0 | AZ50: =$F50*AE50 -> 0 | BA50: =$F50*AF50 -> 0 | BB50: =$F50*AG50 -> 0 | BC50: =$F50*AH50 -> 0 | BD50: =$F50*AI50 -> 0 | BE50: =$F50*AJ50 -> 0 | BF50: =$F50*AK50 -> 9626.8307 | ... BR50: =$F50*AW50 -> 2862.2145
A51: Ewing | B51: May | C51: 2025 | D51: =INDEX('Reference Sheet'!$G$9:$J$100, MATCH(A51,'Reference Sheet'!$F$9:$F$100,0), MATCH(C51,'Reference Sheet'!$G$8:$J$8,0))/2080 -> 92.349582 | E51: =VLOOKUP(C51,'Reference Sheet'!$A$2:$B$5,2) -> 0.2245 | F51: =D51*(1+E51) -> 113.08206 | N51: 99.12 | O51: 10.53 | P51: 55 | Q51: 4.8 | T51: 4.375 | Y51: 1.625 | Z51: 29.47 | AA51: =SUM(G51:Z51) -> 204.92 | AB51: =IF(OR(B51="",C51=""),"",SUMIFS('Reference Sheet'!$D$9:$D$42,'Reference Sheet'!$A$9:$A$42,C51,'Reference Sheet'!$B$9:$B$42,B51)) -> 176 | AC51: =AB51-AA51 -> -28.92 | AD51: =(G51/$AA51)*$AB51 -> 0 | AE51: =(H51/$AA51)*$AB51 -> 0 | AF51: =(I51/$AA51)*$AB51 -> 0 | AG51: =(J51/$AA51)*$AB51 -> 0 | AH51: =(K51/$AA51)*$AB51 -> 0 | AI51: =(L51/$AA51)*$AB51 -> 0 | AJ51: =(M51/$AA51)*$AB51 -> 0 | AK51: =(N51/$AA51)*$AB51 -> 85.131368 | ... AW51: =(Z51/$AA51)*$AB51 -> 25.310951 | AX51: =SUM(AF51:AW51) -> 176 | AY51: =$F51*AD51 -> 0 | AZ51: =$F51*AE51 -> 0 | BA51: =$F51*AF51 -> 0 | BB51: =$F51*AG51 -> 0 | BC51: =$F51*AH51 -> 0 | BD51: =$F51*AI51 -> 0 | BE51: =$F51*AJ51 -> 0 | BF51: =$F51*AK51 -> 9626.8307 | ... BR51: =$F51*AW51 -> 2862.2145
A52: Ewing | B52: June | C52: 2025 | D52: =INDEX('Reference Sheet'!$G$9:$J$100, MATCH(A52,'Reference Sheet'!$F$9:$F$100,0), MATCH(C52,'Reference Sheet'!$G$8:$J$8,0))/2080 -> 92.349582 | E52: =VLOOKUP(C52,'Reference Sheet'!$A$2:$B$5,2) -> 0.2245 | F52: =D52*(1+E52) -> 113.08206 | N52: 99.12 | O52: 10.53 | P52: 55 | Q52: 4.8 | T52: 4.375 | V52: 1.5 | W52: 6 | Y52: 1.625 | Z52: 29.47 | AA52: =SUM(G52:Z52) -> 212.42 | AB52: =IF(OR(B52="",C52=""),"",SUMIFS('Reference Sheet'!$D$9:$D$42,'Reference Sheet'!$A$9:$A$42,C52,'Reference Sheet'!$B$9:$B$42,B52)) -> 168 | AC52: =AB52-AA52 -> -44.42 | AD52: =(G52/$AA52)*$AB52 -> 0 | AE52: =(H52/$AA52)*$AB52 -> 0 | AF52: =(I52/$AA52)*$AB52 -> 0 | AG52: =(J52/$AA52)*$AB52 -> 0 | AH52: =(K52/$AA52)*$AB52 -> 0 | AI52: =(L52/$AA52)*$AB52 -> 0 | AJ52: =(M52/$AA52)*$AB52 -> 0 | AK52: =(N52/$AA52)*$AB52 -> 78.392618 | ... AW52: =(Z52/$AA52)*$AB52 -> 23.30741 | AX52: =SUM(AF52:AW52) -> 168 | AY52: =$F52*AD52 -> 0 | AZ52: =$F52*AE52 -> 0 | BA52: =$F52*AF52 -> 0 | BB52: =$F52*AG52 -> 0 | BC52: =$F52*AH52 -> 0 | BD52: =$F52*AI52 -> 0 | BE52: =$F52*AJ52 -> 0 | BF52: =$F52*AK52 -> 8864.799 | ... BR52: =$F52*AW52 -> 2635.65
A53: Ewing | B53: July | C53: 2025 | D53: =INDEX('Reference Sheet'!$G$9:$J$100, MATCH(A53,'Reference Sheet'!$F$9:$F$100,0), MATCH(C53,'Reference Sheet'!$G$8:$J$8,0))/2080 -> 92.349582 | E53: =VLOOKUP(C53,'Reference Sheet'!$A$2:$B$5,2) -> 0.2245 | F53: =D53*(1+E53) -> 113.08206 | N53: 99.12 | O53: 10.53 | P53: 55 | Q53: 4.8 | T53: 4.375 | Y53: 1.625 | Z53: 29.47 | AA53: =SUM(G53:Z53) -> 204.92 | AB53: =IF(OR(B53="",C53=""),"",SUMIFS('Reference Sheet'!$D$9:$D$42,'Reference Sheet'!$A$9:$A$42,C53,'Reference Sheet'!$B$9:$B$42,B53)) -> 184 | AC53: =AB53-AA53 -> -20.92 | AD53: =(G53/$AA53)*$AB53 -> 0 | AE53: =(H53/$AA53)*$AB53 -> 0 | AF53: =(I53/$AA53)*$AB53 -> 0 | AG53: =(J53/$AA53)*$AB53 -> 0 | AH53: =(K53/$AA53)*$AB53 -> 0 | AI53: =(L53/$AA53)*$AB53 -> 0 | AJ53: =(M53/$AA53)*$AB53 -> 0 | AK53: =(N53/$AA53)*$AB53 -> 89.000976 | ... AW53: =(Z53/$AA53)*$AB53 -> 26.461448 | AX53: =SUM(AF53:AW53) -> 184 | AY53: =$F53*AD53 -> 0 | AZ53: =$F53*AE53 -> 0 | BA53: =$F53*AF53 -> 0 | BB53: =$F53*AG53 -> 0 | BC53: =$F53*AH53 -> 0 | BD53: =$F53*AI53 -> 0 | BE53: =$F53*AJ53 -> 0 | BF53: =$F53*AK53 -> 10064.414 | ... BR53: =$F53*AW53 -> 2992.3152
A54: Ewing | B54: August | C54: 2025 | D54: =INDEX('Reference Sheet'!$G$9:$J$100, MATCH(A54,'Reference Sheet'!$F$9:$F$100,0), MATCH(C54,'Reference Sheet'!$G$8:$J$8,0))/2080 -> 92.349582 | E54: =VLOOKUP(C54,'Reference Sheet'!$A$2:$B$5,2) -> 0.2245 | F54: =D54*(1+E54) -> 113.08206 | N54: 99.12 | O54: 10.53 | P54: 80 | Q54: 4.8 | T54: 4.375 | V54: 0.5 | Y54: 1.625 | Z54: 29.47 | AA54: =SUM(G54:Z54) -> 230.42 | AB54: =IF(OR(B54="",C54=""),"",SUMIFS('Reference Sheet'!$D$9:$D$42,'Reference Sheet'!$A$9:$A$42,C54,'Reference Sheet'!$B$9:$B$42,B54)) -> 168 | AC54: =AB54-AA54 -> -62.42 | AD54: =(G54/$AA54)*$AB54 -> 0 | AE54: =(H54/$AA54)*$AB54 -> 0 | AF54: =(I54/$AA54)*$AB54 -> 0 | AG54: =(J54/$AA54)*$AB54 -> 0 | AH54: =(K54/$AA54)*$AB54 -> 0 | AI54: =(L54/$AA54)*$AB54 -> 0 | AJ54: =(M54/$AA54)*$AB54 -> 0 | AK54: =(N54/$AA54)*$AB54 -> 72.268727 | ... AW54: =(Z54/$AA54)*$AB54 -> 21.486677 | AX54: =SUM(AF54:AW54) -> 168 | AY54: =$F54*AD54 -> 0 | AZ54: =$F54*AE54 -> 0 | BA54: =$F54*AF54 -> 0 | BB54: =$F54*AG54 -> 0 | BC54: =$F54*AH54 -> 0 | BD54: =$F54*AI54 -> 0 | BE54: =$F54*AJ54 -> 0 | BF54: =$F54*AK54 -> 8172.2967 | ... BR54: =$F54*AW54 -> 2429.7577
A55: Ewing | B55: September | C55: 2025 | D55: =INDEX('Reference Sheet'!$G$9:$J$100, MATCH(A55,'Reference Sheet'!$F$9:$F$100,0), MATCH(C55,'Reference Sheet'!$G$8:$J$8,0))/2080 -> 92.349582 | E55: =VLOOKUP(C55,'Reference Sheet'!$A$2:$B$5,2) -> 0.2245 | F55: =D55*(1+E55) -> 113.08206 | N55: 99.12 | O55: 10.52 | P55: 80 | Q55: 4.8 | T55: 4.375 | Y55: 1.625 | Z55: 29.47 | AA55: =SUM(G55:Z55) -> 229.91 | AB55: =IF(OR(B55="",C55=""),"",SUMIFS('Reference Sheet'!$D$9:$D$42,'Reference Sheet'!$A$9:$A$42,C55,'Reference Sheet'!$B$9:$B$42,B55)) -> 176 | AC55: =AB55-AA55 -> -53.91 | AD55: =(G55/$AA55)*$AB55 -> 0 | AE55: =(H55/$AA55)*$AB55 -> 0 | AF55: =(I55/$AA55)*$AB55 -> 0 | AG55: =(J55/$AA55)*$AB55 -> 0 | AH55: =(K55/$AA55)*$AB55 -> 0 | AI55: =(L55/$AA55)*$AB55 -> 0 | AJ55: =(M55/$AA55)*$AB55 -> 0 | AK55: =(N55/$AA55)*$AB55 -> 75.878039 | ... AW55: =(Z55/$AA55)*$AB55 -> 22.559784 | AX55: =SUM(AF55:AW55) -> 176 | AY55: =$F55*AD55 -> 0 | AZ55: =$F55*AE55 -> 0 | BA55: =$F55*AF55 -> 0 | BB55: =$F55*AG55 -> 0 | BC55: =$F55*AH55 -> 0 | BD55: =$F55*AI55 -> 0 | BE55: =$F55*AJ55 -> 0 | BF55: =$F55*AK55 -> 8580.4452 | ... BR55: =$F55*AW55 -> 2551.1069
A56: Ewing | B56: October | C56: 2025 | D56: =INDEX('Reference Sheet'!$G$9:$J$100, MATCH(A56,'Reference Sheet'!$F$9:$F$100,0), MATCH(C56,'Reference Sheet'!$G$8:$J$8,0))/2080 -> 92.349582 | E56: =VLOOKUP(C56,'Reference Sheet'!$A$2:$B$5,2) -> 0.2245 | F56: =D56*(1+E56) -> 113.08206 | N56: 99.11 | O56: 10.52 | P56: 90 | Q56: 4.8 | T56: 4.375 | Y56: 1.625 | Z56: 29.47 | AA56: =SUM(G56:Z56) -> 239.9 | AB56: =IF(OR(B56="",C56=""),"",SUMIFS('Reference Sheet'!$D$9:$D$42,'Reference Sheet'!$A$9:$A$42,C56,'Reference Sheet'!$B$9:$B$42,B56)) -> 184 | AC56: =AB56-AA56 -> -55.9 | AD56: =(G56/$AA56)*$AB56 -> 0 | AE56: =(H56/$AA56)*$AB56 -> 0 | AF56: =(I56/$AA56)*$AB56 -> 0 | AG56: =(J56/$AA56)*$AB56 -> 0 | AH56: =(K56/$AA56)*$AB56 -> 0 | AI56: =(L56/$AA56)*$AB56 -> 0 | AJ56: =(M56/$AA56)*$AB56 -> 0 | AK56: =(N56/$AA56)*$AB56 -> 76.016007 | ... AW56: =(Z56/$AA56)*$AB56 -> 22.603085 | AX56: =SUM(AF56:AW56) -> 184 | AY56: =$F56*AD56 -> 0 | AZ56: =$F56*AE56 -> 0 | BA56: =$F56*AF56 -> 0 | BB56: =$F56*AG56 -> 0 | BC56: =$F56*AH56 -> 0 | BD56: =$F56*AI56 -> 0 | BE56: =$F56*AJ56 -> 0 | BF56: =$F56*AK56 -> 8596.0468 | ... BR56: =$F56*AW56 -> 2556.0034
A57: Ewing | B57: November | C57: 2025 | D57: =INDEX('Reference Sheet'!$G$9:$J$100, MATCH(A57,'Reference Sheet'!$F$9:$F$100,0), MATCH(C57,'Reference Sheet'!$G$8:$J$8,0))/2080 -> 92.349582 | E57: =VLOOKUP(C57,'Reference Sheet'!$A$2:$B$5,2) -> 0.2245 | F57: =D57*(1+E57) -> 113.08206 | N57: 99.11 | O57: 10.52 | P57: 90 | Q57: 4.8 | T57: 4.375 | Y57: 1.625 | Z57: 29.47 | AA57: =SUM(G57:Z57) -> 239.9 | AB57: =IF(OR(B57="",C57=""),"",SUMIFS('Reference Sheet'!$D$9:$D$42,'Reference Sheet'!$A$9:$A$42,C57,'Reference Sheet'!$B$9:$B$42,B57)) -> 160 | AC57: =AB57-AA57 -> -79.9 | AD57: =(G57/$AA57)*$AB57 -> 0 | AE57: =(H57/$AA57)*$AB57 -> 0 | AF57: =(I57/$AA57)*$AB57 -> 0 | AG57: =(J57/$AA57)*$AB57 -> 0 | AH57: =(K57/$AA57)*$AB57 -> 0 | AI57: =(L57/$AA57)*$AB57 -> 0 | AJ57: =(M57/$AA57)*$AB57 -> 0 | AK57: =(N57/$AA57)*$AB57 -> 66.100875 | ... AW57: =(Z57/$AA57)*$AB57 -> 19.654856 | AX57: =SUM(AF57:AW57) -> 160 | AY57: =$F57*AD57 -> 0 | AZ57: =$F57*AE57 -> 0 | BA57: =$F57*AF57 -> 0 | BB57: =$F57*AG57 -> 0 | BC57: =$F57*AH57 -> 0 | BD57: =$F57*AI57 -> 0 | BE57: =$F57*AJ57 -> 0 | BF57: =$F57*AK57 -> 7474.8233 | ... BR57: =$F57*AW57 -> 2222.6117
A58: Ewing | B58: December | C58: 2025 | D58: =INDEX('Reference Sheet'!$G$9:$J$100, MATCH(A58,'Reference Sheet'!$F$9:$F$100,0), MATCH(C58,'Reference Sheet'!$G$8:$J$8,0))/2080 -> 92.349582 | E58: =VLOOKUP(C58,'Reference Sheet'!$A$2:$B$5,2) -> 0.2245 | F58: =D58*(1+E58) -> 113.08206 | N58: 99.11 | O58: 10.52 | P58: 90 | Q58: 4.8 | T58: 4.375 | Y58: 1.625 | Z58: 29.45 | AA58: =SUM(G58:Z58) -> 239.88 | AB58: =IF(OR(B58="",C58=""),"",SUMIFS('Reference Sheet'!$D$9:$D$42,'Reference Sheet'!$A$9:$A$42,C58,'Reference Sheet'!$B$9:$B$42,B58)) -> 184 | AC58: =AB58-AA58 -> -55.88 | AD58: =(G58/$AA58)*$AB58 -> 0 | AE58: =(H58/$AA58)*$AB58 -> 0 | AF58: =(I58/$AA58)*$AB58 -> 0 | AG58: =(J58/$AA58)*$AB58 -> 0 | AH58: =(K58/$AA58)*$AB58 -> 0 | AI58: =(L58/$AA58)*$AB58 -> 0 | AJ58: =(M58/$AA58)*$AB58 -> 0 | AK58: =(N58/$AA58)*$AB58 -> 76.022345 | ... AW58: =(Z58/$AA58)*$AB58 -> 22.589628 | AX58: =SUM(AF58:AW58) -> 184 | AY58: =$F58*AD58 -> 0 | AZ58: =$F58*AE58 -> 0 | BA58: =$F58*AF58 -> 0 | BB58: =$F58*AG58 -> 0 | BC58: =$F58*AH58 -> 0 | BD58: =$F58*AI58 -> 0 | BE58: =$F58*AJ58 -> 0 | BF58: =$F58*AK58 -> 8596.7635 | ... BR58: =$F58*AW58 -> 2554.4817
A59: Ewing | B59: January | C59: 2026 | D59: =INDEX('Reference Sheet'!$G$9:$J$100, MATCH(A59,'Reference Sheet'!$F$9:$F$100,0), MATCH(C59,'Reference Sheet'!$G$8:$J$8,0))/2080 -> 100.96154 | E59: =VLOOKUP(C59,'Reference Sheet'!$A$2:$B$5,2) -> 0.2363 | F59: =D59*(1+E59) -> 124.81875 | Q59: 4.8 | AA59: =SUM(G59:Z59) -> 4.8 | AB59: =AA59 -> 4.8 | AC59: =AB59-AA59 -> 0 | AD59: =(G59/$AA59)*$AB59 -> 0 | AE59: =(H59/$AA59)*$AB59 -> 0 | AF59: =(I59/$AA59)*$AB59 -> 0 | AG59: =(J59/$AA59)*$AB59 -> 0 | AH59: =(K59/$AA59)*$AB59 -> 0 | AI59: =(L59/$AA59)*$AB59 -> 0 | AJ59: =(M59/$AA59)*$AB59 -> 0 | AK59: =(N59/$AA59)*$AB59 -> 0 | ... AW59: =(Z59/$AA59)*$AB59 -> 0 | AX59: =SUM(AF59:AW59) -> 4.8 | AY59: =$F59*AD59 -> 0 | AZ59: =$F59*AE59 -> 0 | BA59: =$F59*AF59 -> 0 | BB59: =$F59*AG59 -> 0 | BC59: =$F59*AH59 -> 0 | BD59: =$F59*AI59 -> 0 | BE59: =$F59*AJ59 -> 0 | BF59: =$F59*AK59 -> 0 | ... BR59: =$F59*AW59 -> 0
A60: Ewing | B60: February | C60: 2026 | D60: =INDEX('Reference Sheet'!$G$9:$J$100, MATCH(A60,'Reference Sheet'!$F$9:$F$100,0), MATCH(C60,'Reference Sheet'!$G$8:$J$8,0))/2080 -> 100.96154 | E60: =VLOOKUP(C60,'Reference Sheet'!$A$2:$B$5,2) -> 0.2363 | F60: =D60*(1+E60) -> 124.81875 | Q60: 4.8 | AA60: =SUM(G60:Z60) -> 4.8 | AB60: =AA60 -> 4.8 | AC60: =AB60-AA60 -> 0 | AD60: =(G60/$AA60)*$AB60 -> 0 | AE60: =(H60/$AA60)*$AB60 -> 0 | AF60: =(I60/$AA60)*$AB60 -> 0 | AG60: =(J60/$AA60)*$AB60 -> 0 | AH60: =(K60/$AA60)*$AB60 -> 0 | AI60: =(L60/$AA60)*$AB60 -> 0 | AJ60: =(M60/$AA60)*$AB60 -> 0 | AK60: =(N60/$AA60)*$AB60 -> 0 | ... AW60: =(Z60/$AA60)*$AB60 -> 0 | AX60: =SUM(AF60:AW60) -> 4.8 | AY60: =$F60*AD60 -> 0 | AZ60: =$F60*AE60 -> 0 | BA60: =$F60*AF60 -> 0 | BB60: =$F60*AG60 -> 0 | BC60: =$F60*AH60 -> 0 | BD60: =$F60*AI60 -> 0 | BE60: =$F60*AJ60 -> 0 | BF60: =$F60*AK60 -> 0 | ... BR60: =$F60*AW60 -> 0
A61: Ewing | B61: March | C61: 2026 | D61: =INDEX('Reference Sheet'!$G$9:$J$100, MATCH(A61,'Reference Sheet'!$F$9:$F$100,0), MATCH(C61,'Reference Sheet'!$G$8:$J$8,0))/2080 -> 100.96154 | E61: =VLOOKUP(C61,'Reference Sheet'!$A$2:$B$5,2) -> 0.2363 | F61: =D61*(1+E61) -> 124.81875 | Q61: 4.8 | AA61: =SUM(G61:Z61) -> 4.8 | AB61: =AA61 -> 4.8 | AC61: =AB61-AA61 -> 0 | AD61: =(G61/$AA61)*$AB61 -> 0 | AE61: =(H61/$AA61)*$AB61 -> 0 | AF61: =(I61/$AA61)*$AB61 -> 0 | AG61: =(J61/$AA61)*$AB61 -> 0 | AH61: =(K61/$AA61)*$AB61 -> 0 | AI61: =(L61/$AA61)*$AB61 -> 0 | AJ61: =(M61/$AA61)*$AB61 -> 0 | AK61: =(N61/$AA61)*$AB61 -> 0 | ... AW61: =(Z61/$AA61)*$AB61 -> 0 | AX61: =SUM(AF61:AW61) -> 4.8 | AY61: =$F61*AD61 -> 0 | AZ61: =$F61*AE61 -> 0 | BA61: =$F61*AF61 -> 0 | BB61: =$F61*AG61 -> 0 | BC61: =$F61*AH61 -> 0 | BD61: =$F61*AI61 -> 0 | BE61: =$F61*AJ61 -> 0 | BF61: =$F61*AK61 -> 0 | ... BR61: =$F61*AW61 -> 0
A62: Ewing | B62: April | C62: 2026 | D62: =INDEX('Reference Sheet'!$G$9:$J$100, MATCH(A62,'Reference Sheet'!$F$9:$F$100,0), MATCH(C62,'Reference Sheet'!$G$8:$J$8,0))/2080 -> 100.96154 | E62: =VLOOKUP(C62,'Reference Sheet'!$A$2:$B$5,2) -> 0.2363 | F62: =D62*(1+E62) -> 124.81875 | Q62: 4.8 | AA62: =SUM(G62:Z62) -> 4.8 | AB62: =AA62 -> 4.8 | AC62: =AB62-AA62 -> 0 | AD62: =(G62/$AA62)*$AB62 -> 0 | AE62: =(H62/$AA62)*$AB62 -> 0 | AF62: =(I62/$AA62)*$AB62 -> 0 | AG62: =(J62/$AA62)*$AB62 -> 0 | AH62: =(K62/$AA62)*$AB62 -> 0 | AI62: =(L62/$AA62)*$AB62 -> 0 | AJ62: =(M62/$AA62)*$AB62 -> 0 | AK62: =(N62/$AA62)*$AB62 -> 0 | ... AW62: =(Z62/$AA62)*$AB62 -> 0 | AX62: =SUM(AF62:AW62) -> 4.8 | AY62: =$F62*AD62 -> 0 | AZ62: =$F62*AE62 -> 0 | BA62: =$F62*AF62 -> 0 | BB62: =$F62*AG62 -> 0 | BC62: =$F62*AH62 -> 0 | BD62: =$F62*AI62 -> 0 | BE62: =$F62*AJ62 -> 0 | BF62: =$F62*AK62 -> 0 | ... BR62: =$F62*AW62 -> 0
A63: Ewing | B63: May | C63: 2026 | D63: =INDEX('Reference Sheet'!$G$9:$J$100, MATCH(A63,'Reference Sheet'!$F$9:$F$100,0), MATCH(C63,'Reference Sheet'!$G$8:$J$8,0))/2080 -> 100.96154 | E63: =VLOOKUP(C63,'Reference Sheet'!$A$2:$B$5,2) -> 0.2363 | F63: =D63*(1+E63) -> 124.81875 | Q63: 4.8 | AA63: =SUM(G63:Z63) -> 4.8 | AB63: =AA63 -> 4.8 | AC63: =AB63-AA63 -> 0 | AD63: =(G63/$AA63)*$AB63 -> 0 | AE63: =(H63/$AA63)*$AB63 -> 0 | AF63: =(I63/$AA63)*$AB63 -> 0 | AG63: =(J63/$AA63)*$AB63 -> 0 | AH63: =(K63/$AA63)*$AB63 -> 0 | AI63: =(L63/$AA63)*$AB63 -> 0 | AJ63: =(M63/$AA63)*$AB63 -> 0 | AK63: =(N63/$AA63)*$AB63 -> 0 | ... AW63: =(Z63/$AA63)*$AB63 -> 0 | AX63: =SUM(AF63:AW63) -> 4.8 | AY63: =$F63*AD63 -> 0 | AZ63: =$F63*AE63 -> 0 | BA63: =$F63*AF63 -> 0 | BB63: =$F63*AG63 -> 0 | BC63: =$F63*AH63 -> 0 | BD63: =$F63*AI63 -> 0 | BE63: =$F63*AJ63 -> 0 | BF63: =$F63*AK63 -> 0 | ... BR63: =$F63*AW63 -> 0
A64: Ewing | B64: June | C64: 2026 | D64: =INDEX('Reference Sheet'!$G$9:$J$100, MATCH(A64,'Reference Sheet'!$F$9:$F$100,0), MATCH(C64,'Reference Sheet'!$G$8:$J$8,0))/2080 -> 100.96154 | E64: =VLOOKUP(C64,'Reference Sheet'!$A$2:$B$5,2) -> 0.2363 | F64: =D64*(1+E64) -> 124.81875 | Q64: 4.8 | AA64: =SUM(G64:Z64) -> 4.8 | AB64: =AA64 -> 4.8 | AC64: =AB64-AA64 -> 0 | AD64: =(G64/$AA64)*$AB64 -> 0 | AE64: =(H64/$AA64)*$AB64 -> 0 | AF64: =(I64/$AA64)*$AB64 -> 0 | AG64: =(J64/$AA64)*$AB64 -> 0 | AH64: =(K64/$AA64)*$AB64 -> 0 | AI64: =(L64/$AA64)*$AB64 -> 0 | AJ64: =(M64/$AA64)*$AB64 -> 0 | AK64: =(N64/$AA64)*$AB64 -> 0 | ... AW64: =(Z64/$AA64)*$AB64 -> 0 | AX64: =SUM(AF64:AW64) -> 4.8 | AY64: =$F64*AD64 -> 0 | AZ64: =$F64*AE64 -> 0 | BA64: =$F64*AF64 -> 0 | BB64: =$F64*AG64 -> 0 | BC64: =$F64*AH64 -> 0 | BD64: =$F64*AI64 -> 0 | BE64: =$F64*AJ64 -> 0 | BF64: =$F64*AK64 -> 0 | ... BR64: =$F64*AW64 -> 0
A65: Gaffney | B65: December | C65: 2023 | D65: =INDEX('Reference Sheet'!$G$9:$J$100, MATCH(A65,'Reference Sheet'!$F$9:$F$100,0), MATCH(C65,'Reference Sheet'!$G$8:$J$8,0))/2080 -> 57.206375 | E65: =VLOOKUP(C65,'Reference Sheet'!$A$2:$B$5,2) -> 0.2136 | F65: =D65*(1+E65) -> 69.425657 | I65: 9 | L65: 10.5 | Q65: 20 | R65: 30 | Z65: 30 | AA65: =SUM(G65:Z65) -> 99.5 | AB65: =IF(OR(B65="",C65=""),"",SUMIFS('Reference Sheet'!$D$9:$D$42,'Reference Sheet'!$A$9:$A$42,C65,'Reference Sheet'!$B$9:$B$42,B65)) -> 168 | AC65: =AB65-AA65 -> 68.5 | AD65: =(G65/$AA65)*$AB65 -> 0 | AE65: =(H65/$AA65)*$AB65 -> 0 | AF65: =(I65/$AA65)*$AB65 -> 15.19598 | AG65: =(J65/$AA65)*$AB65 -> 0 | AH65: =(K65/$AA65)*$AB65 -> 0 | AI65: =(L65/$AA65)*$AB65 -> 17.728643 | AJ65: =(M65/$AA65)*$AB65 -> 0 | AK65: =(N65/$AA65)*$AB65 -> 0 | ... AW65: =(Z65/$AA65)*$AB65 -> 50.653266 | AX65: =SUM(AF65:AW65) -> 168 | AY65: =$F65*AD65 -> 0 | AZ65: =$F65*AE65 -> 0 | BA65: =$F65*AF65 -> 1054.9909 | BB65: =$F65*AG65 -> 0 | BC65: =$F65*AH65 -> 0 | BD65: =$F65*AI65 -> 1230.8227 | BE65: =$F65*AJ65 -> 0 | BF65: =$F65*AK65 -> 0 | ... BR65: =$F65*AW65 -> 3516.6363
A66: Gaffney | B66: November | C66: 2023 | D66: =INDEX('Reference Sheet'!$G$9:$J$100, MATCH(A66,'Reference Sheet'!$F$9:$F$100,0), MATCH(C66,'Reference Sheet'!$G$8:$J$8,0))/2080 -> 57.206375 | E66: =VLOOKUP(C66,'Reference Sheet'!$A$2:$B$5,2) -> 0.2136 | F66: =D66*(1+E66) -> 69.425657 | I66: 22 | L66: 17.5 | Q66: 40 | R66: 40 | Z66: 40 | AA66: =SUM(G66:Z66) -> 159.5 | AB66: =IF(OR(B66="",C66=""),"",SUMIFS('Reference Sheet'!$D$9:$D$42,'Reference Sheet'!$A$9:$A$42,C66,'Reference Sheet'!$B$9:$B$42,B66)) -> 176 | AC66: =AB66-AA66 -> 16.5 | AD66: =(G66/$AA66)*$AB66 -> 0 | AE66: =(H66/$AA66)*$AB66 -> 0 | AF66: =(I66/$AA66)*$AB66 -> 24.275862 | AG66: =(J66/$AA66)*$AB66 -> 0 | AH66: =(K66/$AA66)*$AB66 -> 0 | AI66: =(L66/$AA66)*$AB66 -> 19.310345 | AJ66: =(M66/$AA66)*$AB66 -> 0 | AK66: =(N66/$AA66)*$AB66 -> 0 | ... AW66: =(Z66/$AA66)*$AB66 -> 44.137931 | AX66: =SUM(AF66:AW66) -> 176 | AY66: =$F66*AD66 -> 0 | AZ66: =$F66*AE66 -> 0 | BA66: =$F66*AF66 -> 1685.3677 | BB66: =$F66*AG66 -> 0 | BC66: =$F66*AH66 -> 0 | BD66: =$F66*AI66 -> 1340.6334 | BE66: =$F66*AJ66 -> 0 | BF66: =$F66*AK66 -> 0 | ... BR66: =$F66*AW66 -> 3064.3048
A67: Gaffney | B67: October | C67: 2023 | D67: =INDEX('Reference Sheet'!$G$9:$J$100, MATCH(A67,'Reference Sheet'!$F$9:$F$100,0), MATCH(C67,'Reference Sheet'!$G$8:$J$8,0))/2080 -> 57.206375 | E67: =VLOOKUP(C67,'Reference Sheet'!$A$2:$B$5,2) -> 0.2136 | F67: =D67*(1+E67) -> 69.425657 | I67: 32.5 | L67: 15.5 | Q67: 30 | R67: 50 | Z67: 40 | AA67: =SUM(G67:Z67) -> 168 | AB67: =IF(OR(B67="",C67=""),"",SUMIFS('Reference Sheet'!$D$9:$D$42,'Reference Sheet'!$A$9:$A$42,C67,'Reference Sheet'!$B$9:$B$42,B67)) -> 176 | AC67: =AB67-AA67 -> 8 | AD67: =(G67/$AA67)*$AB67 -> 0 | AE67: =(H67/$AA67)*$AB67 -> 0 | AF67: =(I67/$AA67)*$AB67 -> 34.047619 | AG67: =(J67/$AA67)*$AB67 -> 0 | AH67: =(K67/$AA67)*$AB67 -> 0 | AI67: =(L67/$AA67)*$AB67 -> 16.238095 | AJ67: =(M67/$AA67)*$AB67 -> 0 | AK67: =(N67/$AA67)*$AB67 -> 0 | ... AW67: =(Z67/$AA67)*$AB67 -> 41.904762 | AX67: =SUM(AF67:AW67) -> 176 | AY67: =$F67*AD67 -> 0 | AZ67: =$F67*AE67 -> 0 | BA67: =$F67*AF67 -> 2363.7783 | BB67: =$F67*AG67 -> 0 | BC67: =$F67*AH67 -> 0 | BD67: =$F67*AI67 -> 1127.3404 | BE67: =$F67*AJ67 -> 0 | BF67: =$F67*AK67 -> 0 | ... BR67: =$F67*AW67 -> 2909.2656
A68: Gaffney | B68: December | C68: 2024 | D68: =INDEX('Reference Sheet'!$G$9:$J$100, MATCH(A68,'Reference Sheet'!$F$9:$F$100,0), MATCH(C68,'Reference Sheet'!$G$8:$J$8,0))/2080 -> 64.663457 | E68: =VLOOKUP(C68,'Reference Sheet'!$A$2:$B$5,2) -> 0.1913 | F68: =D68*(1+E68) -> 77.033576 | K68: 5 | L68: 9 | M68: 30 | R68: 20 | S68: 26 | V68: 25 | Z68: 5 | AA68: =SUM(G68:Z68) -> 120 | AB68: =IF(OR(B68="",C68=""),"",SUMIFS('Reference Sheet'!$D$9:$D$42,'Reference Sheet'!$A$9:$A$42,C68,'Reference Sheet'!$B$9:$B$42,B68)) -> 176 | AC68: =AB68-AA68 -> 56 | AD68: =(G68/$AA68)*$AB68 -> 0 | AE68: =(H68/$AA68)*$AB68 -> 0 | AF68: =(I68/$AA68)*$AB68 -> 0 | AG68: =(J68/$AA68)*$AB68 -> 0 | AH68: =(K68/$AA68)*$AB68 -> 7.3333333 | AI68: =(L68/$AA68)*$AB68 -> 13.2 | AJ68: =(M68/$AA68)*$AB68 -> 44 | AK68: =(N68/$AA68)*$AB68 -> 0 | ... AW68: =(Z68/$AA68)*$AB68 -> 7.3333333 | AX68: =SUM(AF68:AW68) -> 176 | AY68: =$F68*AD68 -> 0 | AZ68: =$F68*AE68 -> 0 | BA68: =$F68*AF68 -> 0 | BB68: =$F68*AG68 -> 0 | BC68: =$F68*AH68 -> 564.91289 | BD68: =$F68*AI68 -> 1016.8432 | BE68: =$F68*AJ68 -> 3389.4773 | BF68: =$F68*AK68 -> 0 | ... BR68: =$F68*AW68 -> 564.91289
A69: Gaffney | B69: November | C69: 2024 | D69: =INDEX('Reference Sheet'!$G$9:$J$100, MATCH(A69,'Reference Sheet'!$F$9:$F$100,0), MATCH(C69,'Reference Sheet'!$G$8:$J$8,0))/2080 -> 64.663457 | E69: =VLOOKUP(C69,'Reference Sheet'!$A$2:$B$5,2) -> 0.1913 | F69: =D69*(1+E69) -> 77.033576 | K69: 5 | L69: 12 | M69: 30 | R69: 40 | S69: 30 | V69: 30 | Z69: 5 | AA69: =SUM(G69:Z69) -> 152 | AB69: =IF(OR(B69="",C69=""),"",SUMIFS('Reference Sheet'!$D$9:$D$42,'Reference Sheet'!$A$9:$A$42,C69,'Reference Sheet'!$B$9:$B$42,B69)) -> 168 | AC69: =AB69-AA69 -> 16 | AD69: =(G69/$AA69)*$AB69 -> 0 | AE69: =(H69/$AA69)*$AB69 -> 0 | AF69: =(I69/$AA69)*$AB69 -> 0 | AG69: =(J69/$AA69)*$AB69 -> 0 | AH69: =(K69/$AA69)*$AB69 -> 5.5263158 | AI69: =(L69/$AA69)*$AB69 -> 13.263158 | AJ69: =(M69/$AA69)*$AB69 -> 33.157895 | AK69: =(N69/$AA69)*$AB69 -> 0 | ... AW69: =(Z69/$AA69)*$AB69 -> 5.5263158 | AX69: =SUM(AF69:AW69) -> 168 | AY69: =$F69*AD69 -> 0 | AZ69: =$F69*AE69 -> 0 | BA69: =$F69*AF69 -> 0 | BB69: =$F69*AG69 -> 0 | BC69: =$F69*AH69 -> 425.71187 | BD69: =$F69*AI69 -> 1021.7085 | BE69: =$F69*AJ69 -> 2554.2712 | BF69: =$F69*AK69 -> 0 | ... BR69: =$F69*AW69 -> 425.71187
A70: Gaffney | B70: June | C70: 2024 | D70: =INDEX('Reference Sheet'!$G$9:$J$100, MATCH(A70,'Reference Sheet'!$F$9:$F$100,0), MATCH(C70,'Reference Sheet'!$G$8:$J$8,0))/2080 -> 64.663457 | E70: =VLOOKUP(C70,'Reference Sheet'!$A$2:$B$5,2) -> 0.1913 | F70: =D70*(1+E70) -> 77.033576 | L70: 27 | M70: 42 | Q70: 40 | R70: 32 | Z70: 15 | AA70: =SUM(G70:Z70) -> 156 | AB70: =IF(OR(B70="",C70=""),"",SUMIFS('Reference Sheet'!$D$9:$D$42,'Reference Sheet'!$A$9:$A$42,C70,'Reference Sheet'!$B$9:$B$42,B70)) -> 160 | AC70: =AB70-AA70 -> 4 | AD70: =(G70/$AA70)*$AB70 -> 0 | AE70: =(H70/$AA70)*$AB70 -> 0 | AF70: =(I70/$AA70)*$AB70 -> 0 | AG70: =(J70/$AA70)*$AB70 -> 0 | AH70: =(K70/$AA70)*$AB70 -> 0 | AI70: =(L70/$AA70)*$AB70 -> 27.692308 | AJ70: =(M70/$AA70)*$AB70 -> 43.076923 | AK70: =(N70/$AA70)*$AB70 -> 0 | ... AW70: =(Z70/$AA70)*$AB70 -> 15.384615 | AX70: =SUM(AF70:AW70) -> 160 | AY70: =$F70*AD70 -> 0 | AZ70: =$F70*AE70 -> 0 | BA70: =$F70*AF70 -> 0 | BB70: =$F70*AG70 -> 0 | BC70: =$F70*AH70 -> 0 | BD70: =$F70*AI70 -> 2133.2375 | BE70: =$F70*AJ70 -> 3318.3694 | BF70: =$F70*AK70 -> 0 | ... BR70: =$F70*AW70 -> 1185.1319
A71: Gaffney | B71: March | C71: 2024 | D71: =INDEX('Reference Sheet'!$G$9:$J$100, MATCH(A71,'Reference Sheet'!$F$9:$F$100,0), MATCH(C71,'Reference Sheet'!$G$8:$J$8,0))/2080 -> 64.663457 | E71: =VLOOKUP(C71,'Reference Sheet'!$A$2:$B$5,2) -> 0.1913 | F71: =D71*(1+E71) -> 77.033576 | I71: 11 | L71: 19 | M71: 55 | Q71: 25 | R71: 30 | Z71: 20 | AA71: =SUM(G71:Z71) -> 160 | AB71: =IF(OR(B71="",C71=""),"",SUMIFS('Reference Sheet'!$D$9:$D$42,'Reference Sheet'!$A$9:$A$42,C71,'Reference Sheet'!$B$9:$B$42,B71)) -> 168 | AC71: =AB71-AA71 -> 8 | AD71: =(G71/$AA71)*$AB71 -> 0 | AE71: =(H71/$AA71)*$AB71 -> 0 | AF71: =(I71/$AA71)*$AB71 -> 11.55 | AG71: =(J71/$AA71)*$AB71 -> 0 | AH71: =(K71/$AA71)*$AB71 -> 0 | AI71: =(L71/$AA71)*$AB71 -> 19.95 | AJ71: =(M71/$AA71)*$AB71 -> 57.75 | AK71: =(N71/$AA71)*$AB71 -> 0 | ... AW71: =(Z71/$AA71)*$AB71 -> 21 | AX71: =SUM(AF71:AW71) -> 168 | AY71: =$F71*AD71 -> 0 | AZ71: =$F71*AE71 -> 0 | BA71: =$F71*AF71 -> 889.7378 | BB71: =$F71*AG71 -> 0 | BC71: =$F71*AH71 -> 0 | BD71: =$F71*AI71 -> 1536.8198 | BE71: =$F71*AJ71 -> 4448.689 | BF71: =$F71*AK71 -> 0 | ... BR71: =$F71*AW71 -> 1617.7051
A72: Gaffney | B72: August | C72: 2024 | D72: =INDEX('Reference Sheet'!$G$9:$J$100, MATCH(A72,'Reference Sheet'!$F$9:$F$100,0), MATCH(C72,'Reference Sheet'!$G$8:$J$8,0))/2080 -> 64.663457 | E72: =VLOOKUP(C72,'Reference Sheet'!$A$2:$B$5,2) -> 0.1913 | F72: =D72*(1+E72) -> 77.033576 | L72: 40 | M72: 33 | Q72: 30 | R72: 40 | Z72: 20 | AA72: =SUM(G72:Z72) -> 163 | AB72: =IF(OR(B72="",C72=""),"",SUMIFS('Reference Sheet'!$D$9:$D$42,'Reference Sheet'!$A$9:$A$42,C72,'Reference Sheet'!$B$9:$B$42,B72)) -> 176 | AC72: =AB72-AA72 -> 13 | AD72: =(G72/$AA72)*$AB72 -> 0 | AE72: =(H72/$AA72)*$AB72 -> 0 | AF72: =(I72/$AA72)*$AB72 -> 0 | AG72: =(J72/$AA72)*$AB72 -> 0 | AH72: =(K72/$AA72)*$AB72 -> 0 | AI72: =(L72/$AA72)*$AB72 -> 43.190184 | AJ72: =(M72/$AA72)*$AB72 -> 35.631902 | AK72: =(N72/$AA72)*$AB72 -> 0 | ... AW72: =(Z72/$AA72)*$AB72 -> 21.595092 | AX72: =SUM(AF72:AW72) -> 176 | AY72: =$F72*AD72 -> 0 | AZ72: =$F72*AE72 -> 0 | BA72: =$F72*AF72 -> 0 | BB72: =$F72*AG72 -> 0 | BC72: =$F72*AH72 -> 0 | BD72: =$F72*AI72 -> 3327.0943 | BE72: =$F72*AJ72 -> 2744.8528 | BF72: =$F72*AK72 -> 0 | ... BR72: =$F72*AW72 -> 1663.5472
A73: Gaffney | B73: February | C73: 2024 | D73: =INDEX('Reference Sheet'!$G$9:$J$100, MATCH(A73,'Reference Sheet'!$F$9:$F$100,0), MATCH(C73,'Reference Sheet'!$G$8:$J$8,0))/2080 -> 64.663457 | E73: =VLOOKUP(C73,'Reference Sheet'!$A$2:$B$5,2) -> 0.1913 | F73: =D73*(1+E73) -> 77.033576 | I73: 24 | L73: 25 | M73: 17 | Q73: 40 | R73: 30 | Z73: 30 | AA73: =SUM(G73:Z73) -> 166 | AB73: =IF(OR(B73="",C73=""),"",SUMIFS('Reference Sheet'!$D$9:$D$42,'Reference Sheet'!$A$9:$A$42,C73,'Reference Sheet'!$B$9:$B$42,B73)) -> 168 | AC73: =AB73-AA73 -> 2 | AD73: =(G73/$AA73)*$AB73 -> 0 | AE73: =(H73/$AA73)*$AB73 -> 0 | AF73: =(I73/$AA73)*$AB73 -> 24.289157 | AG73: =(J73/$AA73)*$AB73 -> 0 | AH73: =(K73/$AA73)*$AB73 -> 0 | AI73: =(L73/$AA73)*$AB73 -> 25.301205 | AJ73: =(M73/$AA73)*$AB73 -> 17.204819 | AK73: =(N73/$AA73)*$AB73 -> 0 | ... AW73: =(Z73/$AA73)*$AB73 -> 30.361446 | AX73: =SUM(AF73:AW73) -> 168 | AY73: =$F73*AD73 -> 0 | AZ73: =$F73*AE73 -> 0 | BA73: =$F73*AF73 -> 1871.0806 | BB73: =$F73*AG73 -> 0 | BC73: =$F73*AH73 -> 0 | BD73: =$F73*AI73 -> 1949.0423 | BE73: =$F73*AJ73 -> 1325.3488 | BF73: =$F73*AK73 -> 0 | ... BR73: =$F73*AW73 -> 2338.8507
A74: Gaffney | B74: September | C74: 2024 | D74: =INDEX('Reference Sheet'!$G$9:$J$100, MATCH(A74,'Reference Sheet'!$F$9:$F$100,0), MATCH(C74,'Reference Sheet'!$G$8:$J$8,0))/2080 -> 64.663457 | E74: =VLOOKUP(C74,'Reference Sheet'!$A$2:$B$5,2) -> 0.1913 | F74: =D74*(1+E74) -> 77.033576 | L74: 40 | M74: 60 | Q74: 20 | R74: 28 | Z74: 20 | AA74: =SUM(G74:Z74) -> 168 | AB74: =IF(OR(B74="",C74=""),"",SUMIFS('Reference Sheet'!$D$9:$D$42,'Reference Sheet'!$A$9:$A$42,C74,'Reference Sheet'!$B$9:$B$42,B74)) -> 168 | AC74: =AB74-AA74 -> 0 | AD74: =(G74/$AA74)*$AB74 -> 0 | AE74: =(H74/$AA74)*$AB74 -> 0 | AF74: =(I74/$AA74)*$AB74 -> 0 | AG74: =(J74/$AA74)*$AB74 -> 0 | AH74: =(K74/$AA74)*$AB74 -> 0 | AI74: =(L74/$AA74)*$AB74 -> 40 | AJ74: =(M74/$AA74)*$AB74 -> 60 | AK74: =(N74/$AA74)*$AB74 -> 0 | ... AW74: =(Z74/$AA74)*$AB74 -> 20 | AX74: =SUM(AF74:AW74) -> 168 | AY74: =$F74*AD74 -> 0 | AZ74: =$F74*AE74 -> 0 | BA74: =$F74*AF74 -> 0 | BB74: =$F74*AG74 -> 0 | BC74: =$F74*AH74 -> 0 | BD74: =$F74*AI74 -> 3081.343 | BE74: =$F74*AJ74 -> 4622.0146 | BF74: =$F74*AK74 -> 0 | ... BR74: =$F74*AW74 -> 1540.6715
A75: Gaffney | B75: April | C75: 2024 | D75: =INDEX('Reference Sheet'!$G$9:$J$100, MATCH(A75,'Reference Sheet'!$F$9:$F$100,0), MATCH(C75,'Reference Sheet'!$G$8:$J$8,0))/2080 -> 64.663457 | E75: =VLOOKUP(C75,'Reference Sheet'!$A$2:$B$5,2) -> 0.1913 | F75: =D75*(1+E75) -> 77.033576 | I75: 5 | L75: 31 | M75: 43 | Q75: 33 | R75: 35 | Z75: 25 | AA75: =SUM(G75:Z75) -> 172 | AB75: =IF(OR(B75="",C75=""),"",SUMIFS('Reference Sheet'!$D$9:$D$42,'Reference Sheet'!$A$9:$A$42,C75,'Reference Sheet'!$B$9:$B$42,B75)) -> 176 | AC75: =AB75-AA75 -> 4 | AD75: =(G75/$AA75)*$AB75 -> 0 | AE75: =(H75/$AA75)*$AB75 -> 0 | AF75: =(I75/$AA75)*$AB75 -> 5.1162791 | AG75: =(J75/$AA75)*$AB75 -> 0 | AH75: =(K75/$AA75)*$AB75 -> 0 | AI75: =(L75/$AA75)*$AB75 -> 31.72093 | AJ75: =(M75/$AA75)*$AB75 -> 44 | AK75: =(N75/$AA75)*$AB75 -> 0 | ... AW75: =(Z75/$AA75)*$AB75 -> 25.581395 | AX75: =SUM(AF75:AW75) -> 176 | AY75: =$F75*AD75 -> 0 | AZ75: =$F75*AE75 -> 0 | BA75: =$F75*AF75 -> 394.12527 | BB75: =$F75*AG75 -> 0 | BC75: =$F75*AH75 -> 0 | BD75: =$F75*AI75 -> 2443.5767 | BE75: =$F75*AJ75 -> 3389.4773 | BF75: =$F75*AK75 -> 0 | ... BR75: =$F75*AW75 -> 1970.6264
A76: Gaffney | B76: May | C76: 2024 | D76: =INDEX('Reference Sheet'!$G$9:$J$100, MATCH(A76,'Reference Sheet'!$F$9:$F$100,0), MATCH(C76,'Reference Sheet'!$G$8:$J$8,0))/2080 -> 64.663457 | E76: =VLOOKUP(C76,'Reference Sheet'!$A$2:$B$5,2) -> 0.1913 | F76: =D76*(1+E76) -> 77.033576 | L76: 34 | M76: 45 | Q76: 43 | R76: 34 | Z76: 20 | AA76: =SUM(G76:Z76) -> 176 | AB76: =IF(OR(B76="",C76=""),"",SUMIFS('Reference Sheet'!$D$9:$D$42,'Reference Sheet'!$A$9:$A$42,C76,'Reference Sheet'!$B$9:$B$42,B76)) -> 184 | AC76: =AB76-AA76 -> 8 | AD76: =(G76/$AA76)*$AB76 -> 0 | AE76: =(H76/$AA76)*$AB76 -> 0 | AF76: =(I76/$AA76)*$AB76 -> 0 | AG76: =(J76/$AA76)*$AB76 -> 0 | AH76: =(K76/$AA76)*$AB76 -> 0 | AI76: =(L76/$AA76)*$AB76 -> 35.545455 | AJ76: =(M76/$AA76)*$AB76 -> 47.045455 | AK76: =(N76/$AA76)*$AB76 -> 0 | ... AW76: =(Z76/$AA76)*$AB76 -> 20.909091 | AX76: =SUM(AF76:AW76) -> 184 | AY76: =$F76*AD76 -> 0 | AZ76: =$F76*AE76 -> 0 | BA76: =$F76*AF76 -> 0 | BB76: =$F76*AG76 -> 0 | BC76: =$F76*AH76 -> 0 | BD76: =$F76*AI76 -> 2738.1935 | BE76: =$F76*AJ76 -> 3624.0796 | BF76: =$F76*AK76 -> 0 | ... BR76: =$F76*AW76 -> 1610.702
A77: Gaffney | B77: July | C77: 2024 | D77: =INDEX('Reference Sheet'!$G$9:$J$100, MATCH(A77,'Reference Sheet'!$F$9:$F$100,0), MATCH(C77,'Reference Sheet'!$G$8:$J$8,0))/2080 -> 64.663457 | E77: =VLOOKUP(C77,'Reference Sheet'!$A$2:$B$5,2) -> 0.1913 | F77: =D77*(1+E77) -> 77.033576 | L77: 22 | M77: 45 | Q77: 43 | R77: 44 | Z77: 22 | AA77: =SUM(G77:Z77) -> 176 | AB77: =IF(OR(B77="",C77=""),"",SUMIFS('Reference Sheet'!$D$9:$D$42,'Reference Sheet'!$A$9:$A$42,C77,'Reference Sheet'!$B$9:$B$42,B77)) -> 184 | AC77: =AB77-AA77 -> 8 | AD77: =(G77/$AA77)*$AB77 -> 0 | AE77: =(H77/$AA77)*$AB77 -> 0 | AF77: =(I77/$AA77)*$AB77 -> 0 | AG77: =(J77/$AA77)*$AB77 -> 0 | AH77: =(K77/$AA77)*$AB77 -> 0 | AI77: =(L77/$AA77)*$AB77 -> 23 | AJ77: =(M77/$AA77)*$AB77 -> 47.045455 | AK77: =(N77/$AA77)*$AB77 -> 0 | ... AW77: =(Z77/$AA77)*$AB77 -> 23 | AX77: =SUM(AF77:AW77) -> 184 | AY77: =$F77*AD77 -> 0 | AZ77: =$F77*AE77 -> 0 | BA77: =$F77*AF77 -> 0 | BB77: =$F77*AG77 -> 0 | BC77: =$F77*AH77 -> 0 | BD77: =$F77*AI77 -> 1771.7722 | BE77: =$F77*AJ77 -> 3624.0796 | BF77: =$F77*AK77 -> 0 | ... BR77: =$F77*AW77 -> 1771.7722
A78: Gaffney | B78: January | C78: 2024 | D78: =INDEX('Reference Sheet'!$G$9:$J$100, MATCH(A78,'Reference Sheet'!$F$9:$F$100,0), MATCH(C78,'Reference Sheet'!$G$8:$J$8,0))/2080 -> 64.663457 | E78: =VLOOKUP(C78,'Reference Sheet'!$A$2:$B$5,2) -> 0.1913 | F78: =D78*(1+E78) -> 77.033576 | I78: 17 | L78: 22 | M78: 15 | Q78: 50 | R78: 60 | Z78: 20 | AA78: =SUM(G78:Z78) -> 184 | AB78: =IF(OR(B78="",C78=""),"",SUMIFS('Reference Sheet'!$D$9:$D$42,'Reference Sheet'!$A$9:$A$42,C78,'Reference Sheet'!$B$9:$B$42,B78)) -> 184 | AC78: =AB78-AA78 -> 0 | AD78: =(G78/$AA78)*$AB78 -> 0 | AE78: =(H78/$AA78)*$AB78 -> 0 | AF78: =(I78/$AA78)*$AB78 -> 17 | AG78: =(J78/$AA78)*$AB78 -> 0 | AH78: =(K78/$AA78)*$AB78 -> 0 | AI78: =(L78/$AA78)*$AB78 -> 22 | AJ78: =(M78/$AA78)*$AB78 -> 15 | AK78: =(N78/$AA78)*$AB78 -> 0 | ... AW78: =(Z78/$AA78)*$AB78 -> 20 | AX78: =SUM(AF78:AW78) -> 184 | AY78: =$F78*AD78 -> 0 | AZ78: =$F78*AE78 -> 0 | BA78: =$F78*AF78 -> 1309.5708 | BB78: =$F78*AG78 -> 0 | BC78: =$F78*AH78 -> 0 | BD78: =$F78*AI78 -> 1694.7387 | BE78: =$F78*AJ78 -> 1155.5036 | BF78: =$F78*AK78 -> 0 | ... BR78: =$F78*AW78 -> 1540.6715
A79: Gaffney | B79: October | C79: 2024 | D79: =INDEX('Reference Sheet'!$G$9:$J$100, MATCH(A79,'Reference Sheet'!$F$9:$F$100,0), MATCH(C79,'Reference Sheet'!$G$8:$J$8,0))/2080 -> 64.663457 | E79: =VLOOKUP(C79,'Reference Sheet'!$A$2:$B$5,2) -> 0.1913 | F79: =D79*(1+E79) -> 77.033576 | I79: 20 | L79: 18 | M79: 40 | Q79: 35 | R79: 46 | Z79: 25 | AA79: =SUM(G79:Z79) -> 184 | AB79: =IF(OR(B79="",C79=""),"",SUMIFS('Reference Sheet'!$D$9:$D$42,'Reference Sheet'!$A$9:$A$42,C79,'Reference Sheet'!$B$9:$B$42,B79)) -> 184 | AC79: =AB79-AA79 -> 0 | AD79: =(G79/$AA79)*$AB79 -> 0 | AE79: =(H79/$AA79)*$AB79 -> 0 | AF79: =(I79/$AA79)*$AB79 -> 20 | AG79: =(J79/$AA79)*$AB79 -> 0 | AH79: =(K79/$AA79)*$AB79 -> 0 | AI79: =(L79/$AA79)*$AB79 -> 18 | AJ79: =(M79/$AA79)*$AB79 -> 40 | AK79: =(N79/$AA79)*$AB79 -> 0 | ... AW79: =(Z79/$AA79)*$AB79 -> 25 | AX79: =SUM(AF79:AW79) -> 184 | AY79: =$F79*AD79 -> 0 | AZ79: =$F79*AE79 -> 0 | BA79: =$F79*AF79 -> 1540.6715 | BB79: =$F79*AG79 -> 0 | BC79: =$F79*AH79 -> 0 | BD79: =$F79*AI79 -> 1386.6044 | BE79: =$F79*AJ79 -> 3081.343 | BF79: =$F79*AK79 -> 0 | ... BR79: =$F79*AW79 -> 1925.8394
A80: Gaffney | B80: February | C80: 2025 | D80: =INDEX('Reference Sheet'!$G$9:$J$100, MATCH(A80,'Reference Sheet'!$F$9:$F$100,0), MATCH(C80,'Reference Sheet'!$G$8:$J$8,0))/2080 -> 82.595702 | E80: =VLOOKUP(C80,'Reference Sheet'!$A$2:$B$5,2) -> 0.2245 | F80: =D80*(1+E80) -> 101.13844 | K80: 24 | M80: 56 | N80: 23.75 | Q80: 66 | S80: 6 | V80: 30 | AA80: =SUM(G80:Z80) -> 205.75 | AB80: =IF(OR(B80="",C80=""),"",SUMIFS('Reference Sheet'!$D$9:$D$42,'Reference Sheet'!$A$9:$A$42,C80,'Reference Sheet'!$B$9:$B$42,B80)) -> 160 | AC80: =AB80-AA80 -> -45.75 | AD80: =(G80/$AA80)*$AB80 -> 0 | AE80: =(H80/$AA80)*$AB80 -> 0 | AF80: =(I80/$AA80)*$AB80 -> 0 | AG80: =(J80/$AA80)*$AB80 -> 0 | AH80: =(K80/$AA80)*$AB80 -> 18.663426 | AI80: =(L80/$AA80)*$AB80 -> 0 | AJ80: =(M80/$AA80)*$AB80 -> 43.547995 | AK80: =(N80/$AA80)*$AB80 -> 18.469016 | ... AW80: =(Z80/$AA80)*$AB80 -> 0 | AX80: =SUM(AF80:AW80) -> 160 | AY80: =$F80*AD80 -> 0 | AZ80: =$F80*AE80 -> 0 | BA80: =$F80*AF80 -> 0 | BB80: =$F80*AG80 -> 0 | BC80: =$F80*AH80 -> 1887.5898 | BD80: =$F80*AI80 -> 0 | BE80: =$F80*AJ80 -> 4404.3762 | BF80: =$F80*AK80 -> 1867.9274 | ... BR80: =$F80*AW80 -> 0
A81: Gaffney | B81: March | C81: 2025 | D81: =INDEX('Reference Sheet'!$G$9:$J$100, MATCH(A81,'Reference Sheet'!$F$9:$F$100,0), MATCH(C81,'Reference Sheet'!$G$8:$J$8,0))/2080 -> 82.595702 | E81: =VLOOKUP(C81,'Reference Sheet'!$A$2:$B$5,2) -> 0.2245 | F81: =D81*(1+E81) -> 101.13844 | K81: 26 | M81: 38 | N81: 23.75 | P81: 35 | Q81: 43 | S81: 17 | V81: 26 | AA81: =SUM(G81:Z81) -> 208.75 | AB81: =IF(OR(B81="",C81=""),"",SUMIFS('Reference Sheet'!$D$9:$D$42,'Reference Sheet'!$A$9:$A$42,C81,'Reference Sheet'!$B$9:$B$42,B81)) -> 168 | AC81: =AB81-AA81 -> -40.75 | AD81: =(G81/$AA81)*$AB81 -> 0 | AE81: =(H81/$AA81)*$AB81 -> 0 | AF81: =(I81/$AA81)*$AB81 -> 0 | AG81: =(J81/$AA81)*$AB81 -> 0 | AH81: =(K81/$AA81)*$AB81 -> 20.924551 | AI81: =(L81/$AA81)*$AB81 -> 0 | AJ81: =(M81/$AA81)*$AB81 -> 30.582036 | AK81: =(N81/$AA81)*$AB81 -> 19.113772 | ... AW81: =(Z81/$AA81)*$AB81 -> 0 | AX81: =SUM(AF81:AW81) -> 168 | AY81: =$F81*AD81 -> 0 | AZ81: =$F81*AE81 -> 0 | BA81: =$F81*AF81 -> 0 | BB81: =$F81*AG81 -> 0 | BC81: =$F81*AH81 -> 2116.2764 | BD81: =$F81*AI81 -> 0 | BE81: =$F81*AJ81 -> 3093.0193 | BF81: =$F81*AK81 -> 1933.1371 | ... BR81: =$F81*AW81 -> 0
A82: Gaffney | B82: July | C82: 2025 | D82: =INDEX('Reference Sheet'!$G$9:$J$100, MATCH(A82,'Reference Sheet'!$F$9:$F$100,0), MATCH(C82,'Reference Sheet'!$G$8:$J$8,0))/2080 -> 82.595702 | E82: =VLOOKUP(C82,'Reference Sheet'!$A$2:$B$5,2) -> 0.2245 | F82: =D82*(1+E82) -> 101.13844 | K82: 23 | M82: 33 | N82: 23.75 | P82: 50 | Q82: 33 | S82: 25.5 | V82: 26 | AA82: =SUM(G82:Z82) -> 214.25 | AB82: =IF(OR(B82="",C82=""),"",SUMIFS('Reference Sheet'!$D$9:$D$42,'Reference Sheet'!$A$9:$A$42,C82,'Reference Sheet'!$B$9:$B$42,B82)) -> 184 | AC82: =AB82-AA82 -> -30.25 | AD82: =(G82/$AA82)*$AB82 -> 0 | AE82: =(H82/$AA82)*$AB82 -> 0 | AF82: =(I82/$AA82)*$AB82 -> 0 | AG82: =(J82/$AA82)*$AB82 -> 0 | AH82: =(K82/$AA82)*$AB82 -> 19.752625 | AI82: =(L82/$AA82)*$AB82 -> 0 | AJ82: =(M82/$AA82)*$AB82 -> 28.340723 | AK82: =(N82/$AA82)*$AB82 -> 20.396733 | ... AW82: =(Z82/$AA82)*$AB82 -> 0 | AX82: =SUM(AF82:AW82) -> 184 | AY82: =$F82*AD82 -> 0 | AZ82: =$F82*AE82 -> 0 | BA82: =$F82*AF82 -> 0 | BB82: =$F82*AG82 -> 0 | BC82: =$F82*AH82 -> 1997.7497 | BD82: =$F82*AI82 -> 0 | BE82: =$F82*AJ82 -> 2866.3365 | BF82: =$F82*AK82 -> 2062.8937 | ... BR82: =$F82*AW82 -> 0
A83: Gaffney | B83: June | C83: 2025 | D83: =INDEX('Reference Sheet'!$G$9:$J$100, MATCH(A83,'Reference Sheet'!$F$9:$F$100,0), MATCH(C83,'Reference Sheet'!$G$8:$J$8,0))/2080 -> 82.595702 | E83: =VLOOKUP(C83,'Reference Sheet'!$A$2:$B$5,2) -> 0.2245 | F83: =D83*(1+E83) -> 101.13844 | K83: 26 | M83: 33 | N83: 23.75 | P83: 37 | Q83: 42 | S83: 13 | V83: 42 | AA83: =SUM(G83:Z83) -> 216.75 | AB83: =IF(OR(B83="",C83=""),"",SUMIFS('Reference Sheet'!$D$9:$D$42,'Reference Sheet'!$A$9:$A$42,C83,'Reference Sheet'!$B$9:$B$42,B83)) -> 168 | AC83: =AB83-AA83 -> -48.75 | AD83: =(G83/$AA83)*$AB83 -> 0 | AE83: =(H83/$AA83)*$AB83 -> 0 | AF83: =(I83/$AA83)*$AB83 -> 0 | AG83: =(J83/$AA83)*$AB83 -> 0 | AH83: =(K83/$AA83)*$AB83 -> 20.152249 | AI83: =(L83/$AA83)*$AB83 -> 0 | AJ83: =(M83/$AA83)*$AB83 -> 25.577855 | AK83: =(N83/$AA83)*$AB83 -> 18.408304 | ... AW83: =(Z83/$AA83)*$AB83 -> 0 | AX83: =SUM(AF83:AW83) -> 168 | AY83: =$F83*AD83 -> 0 | AZ83: =$F83*AE83 -> 0 | BA83: =$F83*AF83 -> 0 | BB83: =$F83*AG83 -> 0 | BC83: =$F83*AH83 -> 2038.167 | BD83: =$F83*AI83 -> 0 | BE83: =$F83*AJ83 -> 2586.9042 | BF83: =$F83*AK83 -> 1861.7871 | ... BR83: =$F83*AW83 -> 0
A84: Gaffney | B84: April | C84: 2025 | D84: =INDEX('Reference Sheet'!$G$9:$J$100, MATCH(A84,'Reference Sheet'!$F$9:$F$100,0), MATCH(C84,'Reference Sheet'!$G$8:$J$8,0))/2080 -> 82.595702 | E84: =VLOOKUP(C84,'Reference Sheet'!$A$2:$B$5,2) -> 0.2245 | F84: =D84*(1+E84) -> 101.13844 | K84: 63 | M84: 27 | N84: 23.75 | P84: 38 | Q84: 34 | S84: 8.5 | V84: 27.5 | AA84: =SUM(G84:Z84) -> 221.75 | AB84: =IF(OR(B84="",C84=""),"",SUMIFS('Reference Sheet'!$D$9:$D$42,'Reference Sheet'!$A$9:$A$42,C84,'Reference Sheet'!$B$9:$B$42,B84)) -> 176 | AC84: =AB84-AA84 -> -45.75 | AD84: =(G84/$AA84)*$AB84 -> 0 | AE84: =(H84/$AA84)*$AB84 -> 0 | AF84: =(I84/$AA84)*$AB84 -> 0 | AG84: =(J84/$AA84)*$AB84 -> 0 | AH84: =(K84/$AA84)*$AB84 -> 50.002255 | AI84: =(L84/$AA84)*$AB84 -> 0 | AJ84: =(M84/$AA84)*$AB84 -> 21.429538 | AK84: =(N84/$AA84)*$AB84 -> 18.850056 | ... AW84: =(Z84/$AA84)*$AB84 -> 0 | AX84: =SUM(AF84:AW84) -> 176 | AY84: =$F84*AD84 -> 0 | AZ84: =$F84*AE84 -> 0 | BA84: =$F84*AF84 -> 0 | BB84: =$F84*AG84 -> 0 | BC84: =$F84*AH84 -> 5057.1499 | BD84: =$F84*AI84 -> 0 | BE84: =$F84*AJ84 -> 2167.35 | BF84: =$F84*AK84 -> 1906.4652 | ... BR84: =$F84*AW84 -> 0
A85: Gaffney | B85: September | C85: 2025 | D85: =INDEX('Reference Sheet'!$G$9:$J$100, MATCH(A85,'Reference Sheet'!$F$9:$F$100,0), MATCH(C85,'Reference Sheet'!$G$8:$J$8,0))/2080 -> 82.595702 | E85: =VLOOKUP(C85,'Reference Sheet'!$A$2:$B$5,2) -> 0.2245 | F85: =D85*(1+E85) -> 101.13844 | M85: 32 | N85: 23.75 | P85: 75 | Q85: 50 | S85: 22 | V85: 23 | AA85: =SUM(G85:Z85) -> 225.75 | AB85: =IF(OR(B85="",C85=""),"",SUMIFS('Reference Sheet'!$D$9:$D$42,'Reference Sheet'!$A$9:$A$42,C85,'Reference Sheet'!$B$9:$B$42,B85)) -> 176 | AC85: =AB85-AA85 -> -49.75 | AD85: =(G85/$AA85)*$AB85 -> 0 | AE85: =(H85/$AA85)*$AB85 -> 0 | AF85: =(I85/$AA85)*$AB85 -> 0 | AG85: =(J85/$AA85)*$AB85 -> 0 | AH85: =(K85/$AA85)*$AB85 -> 0 | AI85: =(L85/$AA85)*$AB85 -> 0 | AJ85: =(M85/$AA85)*$AB85 -> 24.947951 | AK85: =(N85/$AA85)*$AB85 -> 18.516058 | ... AW85: =(Z85/$AA85)*$AB85 -> 0 | AX85: =SUM(AF85:AW85) -> 176 | AY85: =$F85*AD85 -> 0 | AZ85: =$F85*AE85 -> 0 | BA85: =$F85*AF85 -> 0 | BB85: =$F85*AG85 -> 0 | BC85: =$F85*AH85 -> 0 | BD85: =$F85*AI85 -> 0 | BE85: =$F85*AJ85 -> 2523.1968 | BF85: =$F85*AK85 -> 1872.6851 | ... BR85: =$F85*AW85 -> 0
A86: Gaffney | B86: May | C86: 2025 | D86: =INDEX('Reference Sheet'!$G$9:$J$100, MATCH(A86,'Reference Sheet'!$F$9:$F$100,0), MATCH(C86,'Reference Sheet'!$G$8:$J$8,0))/2080 -> 82.595702 | E86: =VLOOKUP(C86,'Reference Sheet'!$A$2:$B$5,2) -> 0.2245 | F86: =D86*(1+E86) -> 101.13844 | K86: 41 | M86: 40.5 | N86: 23.75 | P86: 37 | Q86: 45 | S86: 8.5 | V86: 31 | AA86: =SUM(G86:Z86) -> 226.75 | AB86: =IF(OR(B86="",C86=""),"",SUMIFS('Reference Sheet'!$D$9:$D$42,'Reference Sheet'!$A$9:$A$42,C86,'Reference Sheet'!$B$9:$B$42,B86)) -> 176 | AC86: =AB86-AA86 -> -50.75 | AD86: =(G86/$AA86)*$AB86 -> 0 | AE86: =(H86/$AA86)*$AB86 -> 0 | AF86: =(I86/$AA86)*$AB86 -> 0 | AG86: =(J86/$AA86)*$AB86 -> 0 | AH86: =(K86/$AA86)*$AB86 -> 31.823594 | AI86: =(L86/$AA86)*$AB86 -> 0 | AJ86: =(M86/$AA86)*$AB86 -> 31.435502 | AK86: =(N86/$AA86)*$AB86 -> 18.434399 | ... AW86: =(Z86/$AA86)*$AB86 -> 0 | AX86: =SUM(AF86:AW86) -> 176 | AY86: =$F86*AD86 -> 0 | AZ86: =$F86*AE86 -> 0 | BA86: =$F86*AF86 -> 0 | BB86: =$F86*AG86 -> 0 | BC86: =$F86*AH86 -> 3218.5886 | BD86: =$F86*AI86 -> 0 | BE86: =$F86*AJ86 -> 3179.3375 | BF86: =$F86*AK86 -> 1864.4263 | ... BR86: =$F86*AW86 -> 0
A87: Gaffney | B87: August | C87: 2025 | D87: =INDEX('Reference Sheet'!$G$9:$J$100, MATCH(A87,'Reference Sheet'!$F$9:$F$100,0), MATCH(C87,'Reference Sheet'!$G$8:$J$8,0))/2080 -> 82.595702 | E87: =VLOOKUP(C87,'Reference Sheet'!$A$2:$B$5,2) -> 0.2245 | F87: =D87*(1+E87) -> 101.13844 | M87: 24 | N87: 23.75 | P87: 75 | Q87: 54 | S87: 25.5 | V87: 25 | AA87: =SUM(G87:Z87) -> 227.25 | AB87: =IF(OR(B87="",C87=""),"",SUMIFS('Reference Sheet'!$D$9:$D$42,'Reference Sheet'!$A$9:$A$42,C87,'Reference Sheet'!$B$9:$B$42,B87)) -> 168 | AC87: =AB87-AA87 -> -59.25 | AD87: =(G87/$AA87)*$AB87 -> 0 | AE87: =(H87/$AA87)*$AB87 -> 0 | AF87: =(I87/$AA87)*$AB87 -> 0 | AG87: =(J87/$AA87)*$AB87 -> 0 | AH87: =(K87/$AA87)*$AB87 -> 0 | AI87: =(L87/$AA87)*$AB87 -> 0 | AJ87: =(M87/$AA87)*$AB87 -> 17.742574 | AK87: =(N87/$AA87)*$AB87 -> 17.557756 | ... AW87: =(Z87/$AA87)*$AB87 -> 0 | AX87: =SUM(AF87:AW87) -> 168 | AY87: =$F87*AD87 -> 0 | AZ87: =$F87*AE87 -> 0 | BA87: =$F87*AF87 -> 0 | BB87: =$F87*AG87 -> 0 | BC87: =$F87*AH87 -> 0 | BD87: =$F87*AI87 -> 0 | BE87: =$F87*AJ87 -> 1794.4562 | BF87: =$F87*AK87 -> 1775.764 | ... BR87: =$F87*AW87 -> 0
A88: Gaffney | B88: November | C88: 2025 | D88: =INDEX('Reference Sheet'!$G$9:$J$100, MATCH(A88,'Reference Sheet'!$F$9:$F$100,0), MATCH(C88,'Reference Sheet'!$G$8:$J$8,0))/2080 -> 82.595702 | E88: =VLOOKUP(C88,'Reference Sheet'!$A$2:$B$5,2) -> 0.2245 | F88: =D88*(1+E88) -> 101.13844 | M88: 69 | N88: 23.75 | P88: 95 | Q88: 4 | S88: 12 | V88: 25 | AA88: =SUM(G88:Z88) -> 228.75 | AB88: =IF(OR(B88="",C88=""),"",SUMIFS('Reference Sheet'!$D$9:$D$42,'Reference Sheet'!$A$9:$A$42,C88,'Reference Sheet'!$B$9:$B$42,B88)) -> 160 | AC88: =AB88-AA88 -> -68.75 | AD88: =(G88/$AA88)*$AB88 -> 0 | AE88: =(H88/$AA88)*$AB88 -> 0 | AF88: =(I88/$AA88)*$AB88 -> 0 | AG88: =(J88/$AA88)*$AB88 -> 0 | AH88: =(K88/$AA88)*$AB88 -> 0 | AI88: =(L88/$AA88)*$AB88 -> 0 | AJ88: =(M88/$AA88)*$AB88 -> 48.262295 | AK88: =(N88/$AA88)*$AB88 -> 16.612022 | ... AW88: =(Z88/$AA88)*$AB88 -> 0 | AX88: =SUM(AF88:AW88) -> 160 | AY88: =$F88*AD88 -> 0 | AZ88: =$F88*AE88 -> 0 | BA88: =$F88*AF88 -> 0 | BB88: =$F88*AG88 -> 0 | BC88: =$F88*AH88 -> 0 | BD88: =$F88*AI88 -> 0 | BE88: =$F88*AJ88 -> 4881.1731 | BF88: =$F88*AK88 -> 1680.1139 | ... BR88: =$F88*AW88 -> 0
A89: Gaffney | B89: January | C89: 2025 | D89: =INDEX('Reference Sheet'!$G$9:$J$100, MATCH(A89,'Reference Sheet'!$F$9:$F$100,0), MATCH(C89,'Reference Sheet'!$G$8:$J$8,0))/2080 -> 82.595702 | E89: =VLOOKUP(C89,'Reference Sheet'!$A$2:$B$5,2) -> 0.2245 | F89: =D89*(1+E89) -> 101.13844 | K89: 56 | M89: 60 | N89: 23.75 | Q89: 55 | S89: 6 | V89: 32.5 | AA89: =SUM(G89:Z89) -> 233.25 | AB89: =IF(OR(B89="",C89=""),"",SUMIFS('Reference Sheet'!$D$9:$D$42,'Reference Sheet'!$A$9:$A$42,C89,'Reference Sheet'!$B$9:$B$42,B89)) -> 184 | AC89: =AB89-AA89 -> -49.25 | AD89: =(G89/$AA89)*$AB89 -> 0 | AE89: =(H89/$AA89)*$AB89 -> 0 | AF89: =(I89/$AA89)*$AB89 -> 0 | AG89: =(J89/$AA89)*$AB89 -> 0 | AH89: =(K89/$AA89)*$AB89 -> 44.175777 | AI89: =(L89/$AA89)*$AB89 -> 0 | AJ89: =(M89/$AA89)*$AB89 -> 47.33119 | AK89: =(N89/$AA89)*$AB89 -> 18.735263 | ... AW89: =(Z89/$AA89)*$AB89 -> 0 | AX89: =SUM(AF89:AW89) -> 184 | AY89: =$F89*AD89 -> 0 | AZ89: =$F89*AE89 -> 0 | BA89: =$F89*AF89 -> 0 | BB89: =$F89*AG89 -> 0 | BC89: =$F89*AH89 -> 4467.869 | BD89: =$F89*AI89 -> 0 | BE89: =$F89*AJ89 -> 4787.0025 | BF89: =$F89*AK89 -> 1894.8552 | ... BR89: =$F89*AW89 -> 0
A90: Gaffney | B90: December | C90: 2025 | D90: =INDEX('Reference Sheet'!$G$9:$J$100, MATCH(A90,'Reference Sheet'!$F$9:$F$100,0), MATCH(C90,'Reference Sheet'!$G$8:$J$8,0))/2080 -> 82.595702 | E90: =VLOOKUP(C90,'Reference Sheet'!$A$2:$B$5,2) -> 0.2245 | F90: =D90*(1+E90) -> 101.13844 | M90: 80 | N90: 23.75 | P90: 90 | Q90: 4 | S90: 12 | V90: 25 | AA90: =SUM(G90:Z90) -> 234.75 | AB90: =IF(OR(B90="",C90=""),"",SUMIFS('Reference Sheet'!$D$9:$D$42,'Reference Sheet'!$A$9:$A$42,C90,'Reference Sheet'!$B$9:$B$42,B90)) -> 184 | AC90: =AB90-AA90 -> -50.75 | AD90: =(G90/$AA90)*$AB90 -> 0 | AE90: =(H90/$AA90)*$AB90 -> 0 | AF90: =(I90/$AA90)*$AB90 -> 0 | AG90: =(J90/$AA90)*$AB90 -> 0 | AH90: =(K90/$AA90)*$AB90 -> 0 | AI90: =(L90/$AA90)*$AB90 -> 0 | AJ90: =(M90/$AA90)*$AB90 -> 62.705005 | AK90: =(N90/$AA90)*$AB90 -> 18.615548 | ... AW90: =(Z90/$AA90)*$AB90 -> 0 | AX90: =SUM(AF90:AW90) -> 184 | AY90: =$F90*AD90 -> 0 | AZ90: =$F90*AE90 -> 0 | BA90: =$F90*AF90 -> 0 | BB90: =$F90*AG90 -> 0 | BC90: =$F90*AH90 -> 0 | BD90: =$F90*AI90 -> 0 | BE90: =$F90*AJ90 -> 6341.8862 | BF90: =$F90*AK90 -> 1882.7475 | ... BR90: =$F90*AW90 -> 0
A91: Gaffney | B91: October | C91: 2025 | D91: =INDEX('Reference Sheet'!$G$9:$J$100, MATCH(A91,'Reference Sheet'!$F$9:$F$100,0), MATCH(C91,'Reference Sheet'!$G$8:$J$8,0))/2080 -> 82.595702 | E91: =VLOOKUP(C91,'Reference Sheet'!$A$2:$B$5,2) -> 0.2245 | F91: =D91*(1+E91) -> 101.13844 | M91: 62 | N91: 23.75 | P91: 95 | Q91: 4 | S91: 22 | V91: 32 | AA91: =SUM(G91:Z91) -> 238.75 | AB91: =IF(OR(B91="",C91=""),"",SUMIFS('Reference Sheet'!$D$9:$D$42,'Reference Sheet'!$A$9:$A$42,C91,'Reference Sheet'!$B$9:$B$42,B91)) -> 184 | AC91: =AB91-AA91 -> -54.75 | AD91: =(G91/$AA91)*$AB91 -> 0 | AE91: =(H91/$AA91)*$AB91 -> 0 | AF91: =(I91/$AA91)*$AB91 -> 0 | AG91: =(J91/$AA91)*$AB91 -> 0 | AH91: =(K91/$AA91)*$AB91 -> 0 | AI91: =(L91/$AA91)*$AB91 -> 0 | AJ91: =(M91/$AA91)*$AB91 -> 47.782199 | AK91: =(N91/$AA91)*$AB91 -> 18.303665 | ... AW91: =(Z91/$AA91)*$AB91 -> 0 | AX91: =SUM(AF91:AW91) -> 184 | AY91: =$F91*AD91 -> 0 | AZ91: =$F91*AE91 -> 0 | BA91: =$F91*AF91 -> 0 | BB91: =$F91*AG91 -> 0 | BC91: =$F91*AH91 -> 0 | BD91: =$F91*AI91 -> 0 | BE91: =$F91*AJ91 -> 4832.6169 | BF91: =$F91*AK91 -> 1851.2041 | ... BR91: =$F91*AW91 -> 0
A92: Gaffney | B92: February | C92: 2026 | D92: =INDEX('Reference Sheet'!$G$9:$J$100, MATCH(A92,'Reference Sheet'!$F$9:$F$100,0), MATCH(C92,'Reference Sheet'!$G$8:$J$8,0))/2080 -> 91.165865 | E92: =VLOOKUP(C92,'Reference Sheet'!$A$2:$B$5,2) -> 0.2363 | F92: =D92*(1+E92) -> 112.70836 | M92: 52 | P92: 90 | S92: 19 | V92: 28 | AA92: =SUM(G92:Z92) -> 189 | AB92: =IF(OR(B92="",C92=""),"",SUMIFS('Reference Sheet'!$D$9:$D$42,'Reference Sheet'!$A$9:$A$42,C92,'Reference Sheet'!$B$9:$B$42,B92)) -> 160 | AC92: =AB92-AA92 -> -29 | AD92: =(G92/$AA92)*$AB92 -> 0 | AE92: =(H92/$AA92)*$AB92 -> 0 | AF92: =(I92/$AA92)*$AB92 -> 0 | AG92: =(J92/$AA92)*$AB92 -> 0 | AH92: =(K92/$AA92)*$AB92 -> 0 | AI92: =(L92/$AA92)*$AB92 -> 0 | AJ92: =(M92/$AA92)*$AB92 -> 44.021164 | AK92: =(N92/$AA92)*$AB92 -> 0 | ... AW92: =(Z92/$AA92)*$AB92 -> 0 | AX92: =SUM(AF92:AW92) -> 160 | AY92: =$F92*AD92 -> 0 | AZ92: =$F92*AE92 -> 0 | BA92: =$F92*AF92 -> 0 | BB92: =$F92*AG92 -> 0 | BC92: =$F92*AH92 -> 0 | BD92: =$F92*AI92 -> 0 | BE92: =$F92*AJ92 -> 4961.5532 | BF92: =$F92*AK92 -> 0 | ... BR92: =$F92*AW92 -> 0
A93: Gaffney | B93: March | C93: 2026 | D93: =INDEX('Reference Sheet'!$G$9:$J$100, MATCH(A93,'Reference Sheet'!$F$9:$F$100,0), MATCH(C93,'Reference Sheet'!$G$8:$J$8,0))/2080 -> 91.165865 | E93: =VLOOKUP(C93,'Reference Sheet'!$A$2:$B$5,2) -> 0.2363 | F93: =D93*(1+E93) -> 112.70836 | M93: 54 | P93: 90 | S93: 12 | V93: 33 | AA93: =SUM(G93:Z93) -> 189 | AB93: =IF(OR(B93="",C93=""),"",SUMIFS('Reference Sheet'!$D$9:$D$42,'Reference Sheet'!$A$9:$A$42,C93,'Reference Sheet'!$B$9:$B$42,B93)) -> 176 | AC93: =AB93-AA93 -> -13 | AD93: =(G93/$AA93)*$AB93 -> 0 | AE93: =(H93/$AA93)*$AB93 -> 0 | AF93: =(I93/$AA93)*$AB93 -> 0 | AG93: =(J93/$AA93)*$AB93 -> 0 | AH93: =(K93/$AA93)*$AB93 -> 0 | AI93: =(L93/$AA93)*$AB93 -> 0 | AJ93: =(M93/$AA93)*$AB93 -> 50.285714 | AK93: =(N93/$AA93)*$AB93 -> 0 | ... AW93: =(Z93/$AA93)*$AB93 -> 0 | AX93: =SUM(AF93:AW93) -> 176 | AY93: =$F93*AD93 -> 0 | AZ93: =$F93*AE93 -> 0 | BA93: =$F93*AF93 -> 0 | BB93: =$F93*AG93 -> 0 | BC93: =$F93*AH93 -> 0 | BD93: =$F93*AI93 -> 0 | BE93: =$F93*AJ93 -> 5667.6204 | BF93: =$F93*AK93 -> 0 | ... BR93: =$F93*AW93 -> 0
A94: Gaffney | B94: June | C94: 2026 | D94: =INDEX('Reference Sheet'!$G$9:$J$100, MATCH(A94,'Reference Sheet'!$F$9:$F$100,0), MATCH(C94,'Reference Sheet'!$G$8:$J$8,0))/2080 -> 91.165865 | E94: =VLOOKUP(C94,'Reference Sheet'!$A$2:$B$5,2) -> 0.2363 | F94: =D94*(1+E94) -> 112.70836 | M94: 35 | P94: 120 | S94: 10 | V94: 24 | AA94: =SUM(G94:Z94) -> 189 | AB94: =IF(OR(B94="",C94=""),"",SUMIFS('Reference Sheet'!$D$9:$D$42,'Reference Sheet'!$A$9:$A$42,C94,'Reference Sheet'!$B$9:$B$42,B94)) -> 176 | AC94: =AB94-AA94 -> -13 | AD94: =(G94/$AA94)*$AB94 -> 0 | AE94: =(H94/$AA94)*$AB94 -> 0 | AF94: =(I94/$AA94)*$AB94 -> 0 | AG94: =(J94/$AA94)*$AB94 -> 0 | AH94: =(K94/$AA94)*$AB94 -> 0 | AI94: =(L94/$AA94)*$AB94 -> 0 | AJ94: =(M94/$AA94)*$AB94 -> 32.592593 | AK94: =(N94/$AA94)*$AB94 -> 0 | ... AW94: =(Z94/$AA94)*$AB94 -> 0 | AX94: =SUM(AF94:AW94) -> 176 | AY94: =$F94*AD94 -> 0 | AZ94: =$F94*AE94 -> 0 | BA94: =$F94*AF94 -> 0 | BB94: =$F94*AG94 -> 0 | BC94: =$F94*AH94 -> 0 | BD94: =$F94*AI94 -> 0 | BE94: =$F94*AJ94 -> 3673.4576 | BF94: =$F94*AK94 -> 0 | ... BR94: =$F94*AW94 -> 0
A95: Gaffney | B95: May | C95: 2026 | D95: =INDEX('Reference Sheet'!$G$9:$J$100, MATCH(A95,'Reference Sheet'!$F$9:$F$100,0), MATCH(C95,'Reference Sheet'!$G$8:$J$8,0))/2080 -> 91.165865 | E95: =VLOOKUP(C95,'Reference Sheet'!$A$2:$B$5,2) -> 0.2363 | F95: =D95*(1+E95) -> 112.70836 | M95: 41 | P95: 120 | S95: 9 | V95: 22 | AA95: =SUM(G95:Z95) -> 192 | AB95: =IF(OR(B95="",C95=""),"",SUMIFS('Reference Sheet'!$D$9:$D$42,'Reference Sheet'!$A$9:$A$42,C95,'Reference Sheet'!$B$9:$B$42,B95)) -> 168 | AC95: =AB95-AA95 -> -24 | AD95: =(G95/$AA95)*$AB95 -> 0 | AE95: =(H95/$AA95)*$AB95 -> 0 | AF95: =(I95/$AA95)*$AB95 -> 0 | AG95: =(J95/$AA95)*$AB95 -> 0 | AH95: =(K95/$AA95)*$AB95 -> 0 | AI95: =(L95/$AA95)*$AB95 -> 0 | AJ95: =(M95/$AA95)*$AB95 -> 35.875 | AK95: =(N95/$AA95)*$AB95 -> 0 | ... AW95: =(Z95/$AA95)*$AB95 -> 0 | AX95: =SUM(AF95:AW95) -> 168 | AY95: =$F95*AD95 -> 0 | AZ95: =$F95*AE95 -> 0 | BA95: =$F95*AF95 -> 0 | BB95: =$F95*AG95 -> 0 | BC95: =$F95*AH95 -> 0 | BD95: =$F95*AI95 -> 0 | BE95: =$F95*AJ95 -> 4043.4124 | BF95: =$F95*AK95 -> 0 | ... BR95: =$F95*AW95 -> 0
A96: Gaffney | B96: July | C96: 2026 | D96: =INDEX('Reference Sheet'!$G$9:$J$100, MATCH(A96,'Reference Sheet'!$F$9:$F$100,0), MATCH(C96,'Reference Sheet'!$G$8:$J$8,0))/2080 -> 91.165865 | E96: =VLOOKUP(C96,'Reference Sheet'!$A$2:$B$5,2) -> 0.2363 | F96: =D96*(1+E96) -> 112.70836 | M96: 43 | P96: 120 | S96: 11 | V96: 21 | AA96: =SUM(G96:Z96) -> 195 | AB96: =IF(OR(B96="",C96=""),"",SUMIFS('Reference Sheet'!$D$9:$D$42,'Reference Sheet'!$A$9:$A$42,C96,'Reference Sheet'!$B$9:$B$42,B96)) -> 184 | AC96: =AB96-AA96 -> -11 | AD96: =(G96/$AA96)*$AB96 -> 0 | AE96: =(H96/$AA96)*$AB96 -> 0 | AF96: =(I96/$AA96)*$AB96 -> 0 | AG96: =(J96/$AA96)*$AB96 -> 0 | AH96: =(K96/$AA96)*$AB96 -> 0 | AI96: =(L96/$AA96)*$AB96 -> 0 | AJ96: =(M96/$AA96)*$AB96 -> 40.574359 | AK96: =(N96/$AA96)*$AB96 -> 0 | ... AW96: =(Z96/$AA96)*$AB96 -> 0 | AX96: =SUM(AF96:AW96) -> 184 | AY96: =$F96*AD96 -> 0 | AZ96: =$F96*AE96 -> 0 | BA96: =$F96*AF96 -> 0 | BB96: =$F96*AG96 -> 0 | BC96: =$F96*AH96 -> 0 | BD96: =$F96*AI96 -> 0 | BE96: =$F96*AJ96 -> 4573.0694 | BF96: =$F96*AK96 -> 0 | ... BR96: =$F96*AW96 -> 0
A97: Gaffney | B97: January | C97: 2026 | D97: =INDEX('Reference Sheet'!$G$9:$J$100, MATCH(A97,'Reference Sheet'!$F$9:$F$100,0), MATCH(C97,'Reference Sheet'!$G$8:$J$8,0))/2080 -> 91.165865 | E97: =VLOOKUP(C97,'Reference Sheet'!$A$2:$B$5,2) -> 0.2363 | F97: =D97*(1+E97) -> 112.70836 | M97: 67 | P97: 92 | S97: 14 | V97: 31 | AA97: =SUM(G97:Z97) -> 204 | AB97: =IF(OR(B97="",C97=""),"",SUMIFS('Reference Sheet'!$D$9:$D$42,'Reference Sheet'!$A$9:$A$42,C97,'Reference Sheet'!$B$9:$B$42,B97)) -> 176 | AC97: =AB97-AA97 -> -28 | AD97: =(G97/$AA97)*$AB97 -> 0 | AE97: =(H97/$AA97)*$AB97 -> 0 | AF97: =(I97/$AA97)*$AB97 -> 0 | AG97: =(J97/$AA97)*$AB97 -> 0 | AH97: =(K97/$AA97)*$AB97 -> 0 | AI97: =(L97/$AA97)*$AB97 -> 0 | AJ97: =(M97/$AA97)*$AB97 -> 57.803922 | AK97: =(N97/$AA97)*$AB97 -> 0 | ... AW97: =(Z97/$AA97)*$AB97 -> 0 | AX97: =SUM(AF97:AW97) -> 176 | AY97: =$F97*AD97 -> 0 | AZ97: =$F97*AE97 -> 0 | BA97: =$F97*AF97 -> 0 | BB97: =$F97*AG97 -> 0 | BC97: =$F97*AH97 -> 0 | BD97: =$F97*AI97 -> 0 | BE97: =$F97*AJ97 -> 6514.9852 | BF97: =$F97*AK97 -> 0 | ... BR97: =$F97*AW97 -> 0
A98: Gaffney | B98: April | C98: 2026 | D98: =INDEX('Reference Sheet'!$G$9:$J$100, MATCH(A98,'Reference Sheet'!$F$9:$F$100,0), MATCH(C98,'Reference Sheet'!$G$8:$J$8,0))/2080 -> 91.165865 | E98: =VLOOKUP(C98,'Reference Sheet'!$A$2:$B$5,2) -> 0.2363 | F98: =D98*(1+E98) -> 112.70836 | M98: 34 | P98: 120 | S98: 38 | V98: 25 | AA98: =SUM(G98:Z98) -> 217 | AB98: =IF(OR(B98="",C98=""),"",SUMIFS('Reference Sheet'!$D$9:$D$42,'Reference Sheet'!$A$9:$A$42,C98,'Reference Sheet'!$B$9:$B$42,B98)) -> 176 | AC98: =AB98-AA98 -> -41 | AD98: =(G98/$AA98)*$AB98 -> 0 | AE98: =(H98/$AA98)*$AB98 -> 0 | AF98: =(I98/$AA98)*$AB98 -> 0 | AG98: =(J98/$AA98)*$AB98 -> 0 | AH98: =(K98/$AA98)*$AB98 -> 0 | AI98: =(L98/$AA98)*$AB98 -> 0 | AJ98: =(M98/$AA98)*$AB98 -> 27.576037 | AK98: =(N98/$AA98)*$AB98 -> 0 | ... AW98: =(Z98/$AA98)*$AB98 -> 0 | AX98: =SUM(AF98:AW98) -> 176 | AY98: =$F98*AD98 -> 0 | AZ98: =$F98*AE98 -> 0 | BA98: =$F98*AF98 -> 0 | BB98: =$F98*AG98 -> 0 | BC98: =$F98*AH98 -> 0 | BD98: =$F98*AI98 -> 0 | BE98: =$F98*AJ98 -> 3108.0499 | BF98: =$F98*AK98 -> 0 | ... BR98: =$F98*AW98 -> 0
A99: Jaric | B99: October | C99: 2023 | D99: =INDEX('Reference Sheet'!$G$9:$J$100, MATCH(A99,'Reference Sheet'!$F$9:$F$100,0), MATCH(C99,'Reference Sheet'!$G$8:$J$8,0))/2080 -> 32.516567 | E99: =VLOOKUP(C99,'Reference Sheet'!$A$2:$B$5,2) -> 0.2136 | F99: =D99*(1+E99) -> 39.462106 | L99: 9 | Q99: 32.5 | Z99: 103 | AA99: =SUM(G99:Z99) -> 144.5 | AB99: =IF(OR(B99="",C99=""),"",SUMIFS('Reference Sheet'!$D$9:$D$42,'Reference Sheet'!$A$9:$A$42,C99,'Reference Sheet'!$B$9:$B$42,B99)) -> 176 | AC99: =AB99-AA99 -> 31.5 | AD99: =(G99/$AA99)*$AB99 -> 0 | AE99: =(H99/$AA99)*$AB99 -> 0 | AF99: =(I99/$AA99)*$AB99 -> 0 | AG99: =(J99/$AA99)*$AB99 -> 0 | AH99: =(K99/$AA99)*$AB99 -> 0 | AI99: =(L99/$AA99)*$AB99 -> 10.961938 | AJ99: =(M99/$AA99)*$AB99 -> 0 | AK99: =(N99/$AA99)*$AB99 -> 0 | ... AW99: =(Z99/$AA99)*$AB99 -> 125.45329 | AX99: =SUM(AF99:AW99) -> 176 | AY99: =$F99*AD99 -> 0 | AZ99: =$F99*AE99 -> 0 | BA99: =$F99*AF99 -> 0 | BB99: =$F99*AG99 -> 0 | BC99: =$F99*AH99 -> 0 | BD99: =$F99*AI99 -> 432.58115 | BE99: =$F99*AJ99 -> 0 | BF99: =$F99*AK99 -> 0 | ... BR99: =$F99*AW99 -> 4950.6509
A100: Jaric | B100: November | C100: 2023 | D100: =INDEX('Reference Sheet'!$G$9:$J$100, MATCH(A100,'Reference Sheet'!$F$9:$F$100,0), MATCH(C100,'Reference Sheet'!$G$8:$J$8,0))/2080 -> 32.516567 | E100: =VLOOKUP(C100,'Reference Sheet'!$A$2:$B$5,2) -> 0.2136 | F100: =D100*(1+E100) -> 39.462106 | L100: 9.5 | Q100: 36 | Z100: 100.5 | AA100: =SUM(G100:Z100) -> 146 | AB100: =IF(OR(B100="",C100=""),"",SUMIFS('Reference Sheet'!$D$9:$D$42,'Reference Sheet'!$A$9:$A$42,C100,'Reference Sheet'!$B$9:$B$42,B100)) -> 176 | AC100: =AB100-AA100 -> 30 | AD100: =(G100/$AA100)*$AB100 -> 0 | AE100: =(H100/$AA100)*$AB100 -> 0 | AF100: =(I100/$AA100)*$AB100 -> 0 | AG100: =(J100/$AA100)*$AB100 -> 0 | AH100: =(K100/$AA100)*$AB100 -> 0 | AI100: =(L100/$AA100)*$AB100 -> 11.452055 | AJ100: =(M100/$AA100)*$AB100 -> 0 | AK100: =(N100/$AA100)*$AB100 -> 0 | ... AW100: =(Z100/$AA100)*$AB100 -> 121.15068 | AX100: =SUM(AF100:AW100) -> 176 | AY100: =$F100*AD100 -> 0 | AZ100: =$F100*AE100 -> 0 | BA100: =$F100*AF100 -> 0 | BB100: =$F100*AG100 -> 0 | BC100: =$F100*AH100 -> 0 | BD100: =$F100*AI100 -> 451.9222 | BE100: =$F100*AJ100 -> 0 | BF100: =$F100*AK100 -> 0 | ... BR100: =$F100*AW100 -> 4780.8612
A101: Jaric | B101: December | C101: 2023 | D101: =INDEX('Reference Sheet'!$G$9:$J$100, MATCH(A101,'Reference Sheet'!$F$9:$F$100,0), MATCH(C101,'Reference Sheet'!$G$8:$J$8,0))/2080 -> 32.516567 | E101: =VLOOKUP(C101,'Reference Sheet'!$A$2:$B$5,2) -> 0.2136 | F101: =D101*(1+E101) -> 39.462106 | L101: 3 | Q101: 13.5 | Z101: 137 | AA101: =SUM(G101:Z101) -> 153.5 | AB101: =IF(OR(B101="",C101=""),"",SUMIFS('Reference Sheet'!$D$9:$D$42,'Reference Sheet'!$A$9:$A$42,C101,'Reference Sheet'!$B$9:$B$42,B101)) -> 168 | AC101: =AB101-AA101 -> 14.5 | AD101: =(G101/$AA101)*$AB101 -> 0 | AE101: =(H101/$AA101)*$AB101 -> 0 | AF101: =(I101/$AA101)*$AB101 -> 0 | AG101: =(J101/$AA101)*$AB101 -> 0 | AH101: =(K101/$AA101)*$AB101 -> 0 | AI101: =(L101/$AA101)*$AB101 -> 3.2833876 | AJ101: =(M101/$AA101)*$AB101 -> 0 | AK101: =(N101/$AA101)*$AB101 -> 0 | ... AW101: =(Z101/$AA101)*$AB101 -> 149.94137 | AX101: =SUM(AF101:AW101) -> 168 | AY101: =$F101*AD101 -> 0 | AZ101: =$F101*AE101 -> 0 | BA101: =$F101*AF101 -> 0 | BB101: =$F101*AG101 -> 0 | BC101: =$F101*AH101 -> 0 | BD101: =$F101*AI101 -> 129.56939 | BE101: =$F101*AJ101 -> 0 | BF101: =$F101*AK101 -> 0 | ... BR101: =$F101*AW101 -> 5917.0022
A102: Jaric | B102: June | C102: 2024 | D102: =INDEX('Reference Sheet'!$G$9:$J$100, MATCH(A102,'Reference Sheet'!$F$9:$F$100,0), MATCH(C102,'Reference Sheet'!$G$8:$J$8,0))/2080 -> 37.870995 | E102: =VLOOKUP(C102,'Reference Sheet'!$A$2:$B$5,2) -> 0.1913 | F102: =D102*(1+E102) -> 45.115717 | L102: 16 | M102: 80 | Z102: 64 | AA102: =SUM(G102:Z102) -> 160 | AB102: =IF(OR(B102="",C102=""),"",SUMIFS('Reference Sheet'!$D$9:$D$42,'Reference Sheet'!$A$9:$A$42,C102,'Reference Sheet'!$B$9:$B$42,B102)) -> 160 | AC102: =AB102-AA102 -> 0 | AD102: =(G102/$AA102)*$AB102 -> 0 | AE102: =(H102/$AA102)*$AB102 -> 0 | AF102: =(I102/$AA102)*$AB102 -> 0 | AG102: =(J102/$AA102)*$AB102 -> 0 | AH102: =(K102/$AA102)*$AB102 -> 0 | AI102: =(L102/$AA102)*$AB102 -> 16 | AJ102: =(M102/$AA102)*$AB102 -> 80 | AK102: =(N102/$AA102)*$AB102 -> 0 | ... AW102: =(Z102/$AA102)*$AB102 -> 64 | AX102: =SUM(AF102:AW102) -> 160 | AY102: =$F102*AD102 -> 0 | AZ102: =$F102*AE102 -> 0 | BA102: =$F102*AF102 -> 0 | BB102: =$F102*AG102 -> 0 | BC102: =$F102*AH102 -> 0 | BD102: =$F102*AI102 -> 721.85147 | BE102: =$F102*AJ102 -> 3609.2573 | BF102: =$F102*AK102 -> 0 | ... BR102: =$F102*AW102 -> 2887.4059
A103: Jaric | B103: February | C103: 2024 | D103: =INDEX('Reference Sheet'!$G$9:$J$100, MATCH(A103,'Reference Sheet'!$F$9:$F$100,0), MATCH(C103,'Reference Sheet'!$G$8:$J$8,0))/2080 -> 37.870995 | E103: =VLOOKUP(C103,'Reference Sheet'!$A$2:$B$5,2) -> 0.1913 | F103: =D103*(1+E103) -> 45.115717 | L103: 16.8 | M103: 84 | Z103: 67.2 | AA103: =SUM(G103:Z103) -> 168 | AB103: =IF(OR(B103="",C103=""),"",SUMIFS('Reference Sheet'!$D$9:$D$42,'Reference Sheet'!$A$9:$A$42,C103,'Reference Sheet'!$B$9:$B$42,B103)) -> 168 | AC103: =AB103-AA103 -> 0 | AD103: =(G103/$AA103)*$AB103 -> 0 | AE103: =(H103/$AA103)*$AB103 -> 0 | AF103: =(I103/$AA103)*$AB103 -> 0 | AG103: =(J103/$AA103)*$AB103 -> 0 | AH103: =(K103/$AA103)*$AB103 -> 0 | AI103: =(L103/$AA103)*$AB103 -> 16.8 | AJ103: =(M103/$AA103)*$AB103 -> 84 | AK103: =(N103/$AA103)*$AB103 -> 0 | ... AW103: =(Z103/$AA103)*$AB103 -> 67.2 | AX103: =SUM(AF103:AW103) -> 168 | AY103: =$F103*AD103 -> 0 | AZ103: =$F103*AE103 -> 0 | BA103: =$F103*AF103 -> 0 | BB103: =$F103*AG103 -> 0 | BC103: =$F103*AH103 -> 0 | BD103: =$F103*AI103 -> 757.94404 | BE103: =$F103*AJ103 -> 3789.7202 | BF103: =$F103*AK103 -> 0 | ... BR103: =$F103*AW103 -> 3031.7762
A104: Jaric | B104: March | C104: 2024 | D104: =INDEX('Reference Sheet'!$G$9:$J$100, MATCH(A104,'Reference Sheet'!$F$9:$F$100,0), MATCH(C104,'Reference Sheet'!$G$8:$J$8,0))/2080 -> 37.870995 | E104: =VLOOKUP(C104,'Reference Sheet'!$A$2:$B$5,2) -> 0.1913 | F104: =D104*(1+E104) -> 45.115717 | L104: 16.8 | M104: 84 | Z104: 67.2 | AA104: =SUM(G104:Z104) -> 168 | AB104: =IF(OR(B104="",C104=""),"",SUMIFS('Reference Sheet'!$D$9:$D$42,'Reference Sheet'!$A$9:$A$42,C104,'Reference Sheet'!$B$9:$B$42,B104)) -> 168 | AC104: =AB104-AA104 -> 0 | AD104: =(G104/$AA104)*$AB104 -> 0 | AE104: =(H104/$AA104)*$AB104 -> 0 | AF104: =(I104/$AA104)*$AB104 -> 0 | AG104: =(J104/$AA104)*$AB104 -> 0 | AH104: =(K104/$AA104)*$AB104 -> 0 | AI104: =(L104/$AA104)*$AB104 -> 16.8 | AJ104: =(M104/$AA104)*$AB104 -> 84 | AK104: =(N104/$AA104)*$AB104 -> 0 | ... AW104: =(Z104/$AA104)*$AB104 -> 67.2 | AX104: =SUM(AF104:AW104) -> 168 | AY104: =$F104*AD104 -> 0 | AZ104: =$F104*AE104 -> 0 | BA104: =$F104*AF104 -> 0 | BB104: =$F104*AG104 -> 0 | BC104: =$F104*AH104 -> 0 | BD104: =$F104*AI104 -> 757.94404 | BE104: =$F104*AJ104 -> 3789.7202 | BF104: =$F104*AK104 -> 0 | ... BR104: =$F104*AW104 -> 3031.7762
A105: Jaric | B105: September | C105: 2024 | D105: =INDEX('Reference Sheet'!$G$9:$J$100, MATCH(A105,'Reference Sheet'!$F$9:$F$100,0), MATCH(C105,'Reference Sheet'!$G$8:$J$8,0))/2080 -> 37.870995 | E105: =VLOOKUP(C105,'Reference Sheet'!$A$2:$B$5,2) -> 0.1913 | F105: =D105*(1+E105) -> 45.115717 | L105: 16.8 | M105: 84 | Z105: 67.2 | AA105: =SUM(G105:Z105) -> 168 | AB105: =IF(OR(B105="",C105=""),"",SUMIFS('Reference Sheet'!$D$9:$D$42,'Reference Sheet'!$A$9:$A$42,C105,'Reference Sheet'!$B$9:$B$42,B105)) -> 168 | AC105: =AB105-AA105 -> 0 | AD105: =(G105/$AA105)*$AB105 -> 0 | AE105: =(H105/$AA105)*$AB105 -> 0 | AF105: =(I105/$AA105)*$AB105 -> 0 | AG105: =(J105/$AA105)*$AB105 -> 0 | AH105: =(K105/$AA105)*$AB105 -> 0 | AI105: =(L105/$AA105)*$AB105 -> 16.8 | AJ105: =(M105/$AA105)*$AB105 -> 84 | AK105: =(N105/$AA105)*$AB105 -> 0 | ... AW105: =(Z105/$AA105)*$AB105 -> 67.2 | AX105: =SUM(AF105:AW105) -> 168 | AY105: =$F105*AD105 -> 0 | AZ105: =$F105*AE105 -> 0 | BA105: =$F105*AF105 -> 0 | BB105: =$F105*AG105 -> 0 | BC105: =$F105*AH105 -> 0 | BD105: =$F105*AI105 -> 757.94404 | BE105: =$F105*AJ105 -> 3789.7202 | BF105: =$F105*AK105 -> 0 | ... BR105: =$F105*AW105 -> 3031.7762
A106: Jaric | B106: November | C106: 2024 | D106: =INDEX('Reference Sheet'!$G$9:$J$100, MATCH(A106,'Reference Sheet'!$F$9:$F$100,0), MATCH(C106,'Reference Sheet'!$G$8:$J$8,0))/2080 -> 37.870995 | E106: =VLOOKUP(C106,'Reference Sheet'!$A$2:$B$5,2) -> 0.1913 | F106: =D106*(1+E106) -> 45.115717 | L106: 16.8 | M106: 84 | Z106: 67.2 | AA106: =SUM(G106:Z106) -> 168 | AB106: =IF(OR(B106="",C106=""),"",SUMIFS('Reference Sheet'!$D$9:$D$42,'Reference Sheet'!$A$9:$A$42,C106,'Reference Sheet'!$B$9:$B$42,B106)) -> 168 | AC106: =AB106-AA106 -> 0 | AD106: =(G106/$AA106)*$AB106 -> 0 | AE106: =(H106/$AA106)*$AB106 -> 0 | AF106: =(I106/$AA106)*$AB106 -> 0 | AG106: =(J106/$AA106)*$AB106 -> 0 | AH106: =(K106/$AA106)*$AB106 -> 0 | AI106: =(L106/$AA106)*$AB106 -> 16.8 | AJ106: =(M106/$AA106)*$AB106 -> 84 | AK106: =(N106/$AA106)*$AB106 -> 0 | ... AW106: =(Z106/$AA106)*$AB106 -> 67.2 | AX106: =SUM(AF106:AW106) -> 168 | AY106: =$F106*AD106 -> 0 | AZ106: =$F106*AE106 -> 0 | BA106: =$F106*AF106 -> 0 | BB106: =$F106*AG106 -> 0 | BC106: =$F106*AH106 -> 0 | BD106: =$F106*AI106 -> 757.94404 | BE106: =$F106*AJ106 -> 3789.7202 | BF106: =$F106*AK106 -> 0 | ... BR106: =$F106*AW106 -> 3031.7762
A107: Jaric | B107: April | C107: 2024 | D107: =INDEX('Reference Sheet'!$G$9:$J$100, MATCH(A107,'Reference Sheet'!$F$9:$F$100,0), MATCH(C107,'Reference Sheet'!$G$8:$J$8,0))/2080 -> 37.870995 | E107: =VLOOKUP(C107,'Reference Sheet'!$A$2:$B$5,2) -> 0.1913 | F107: =D107*(1+E107) -> 45.115717 | L107: 17.6 | M107: 88 | Z107: 70.4 | AA107: =SUM(G107:Z107) -> 176 | AB107: =IF(OR(B107="",C107=""),"",SUMIFS('Reference Sheet'!$D$9:$D$42,'Reference Sheet'!$A$9:$A$42,C107,'Reference Sheet'!$B$9:$B$42,B107)) -> 176 | AC107: =AB107-AA107 -> 0 | AD107: =(G107/$AA107)*$AB107 -> 0 | AE107: =(H107/$AA107)*$AB107 -> 0 | AF107: =(I107/$AA107)*$AB107 -> 0 | AG107: =(J107/$AA107)*$AB107 -> 0 | AH107: =(K107/$AA107)*$AB107 -> 0 | AI107: =(L107/$AA107)*$AB107 -> 17.6 | AJ107: =(M107/$AA107)*$AB107 -> 88 | AK107: =(N107/$AA107)*$AB107 -> 0 | ... AW107: =(Z107/$AA107)*$AB107 -> 70.4 | AX107: =SUM(AF107:AW107) -> 176 | AY107: =$F107*AD107 -> 0 | AZ107: =$F107*AE107 -> 0 | BA107: =$F107*AF107 -> 0 | BB107: =$F107*AG107 -> 0 | BC107: =$F107*AH107 -> 0 | BD107: =$F107*AI107 -> 794.03661 | BE107: =$F107*AJ107 -> 3970.1831 | BF107: =$F107*AK107 -> 0 | ... BR107: =$F107*AW107 -> 3176.1464
A108: Jaric | B108: August | C108: 2024 | D108: =INDEX('Reference Sheet'!$G$9:$J$100, MATCH(A108,'Reference Sheet'!$F$9:$F$100,0), MATCH(C108,'Reference Sheet'!$G$8:$J$8,0))/2080 -> 37.870995 | E108: =VLOOKUP(C108,'Reference Sheet'!$A$2:$B$5,2) -> 0.1913 | F108: =D108*(1+E108) -> 45.115717 | L108: 17.6 | M108: 88 | Z108: 70.4 | AA108: =SUM(G108:Z108) -> 176 | AB108: =IF(OR(B108="",C108=""),"",SUMIFS('Reference Sheet'!$D$9:$D$42,'Reference Sheet'!$A$9:$A$42,C108,'Reference Sheet'!$B$9:$B$42,B108)) -> 176 | AC108: =AB108-AA108 -> 0 | AD108: =(G108/$AA108)*$AB108 -> 0 | AE108: =(H108/$AA108)*$AB108 -> 0 | AF108: =(I108/$AA108)*$AB108 -> 0 | AG108: =(J108/$AA108)*$AB108 -> 0 | AH108: =(K108/$AA108)*$AB108 -> 0 | AI108: =(L108/$AA108)*$AB108 -> 17.6 | AJ108: =(M108/$AA108)*$AB108 -> 88 | AK108: =(N108/$AA108)*$AB108 -> 0 | ... AW108: =(Z108/$AA108)*$AB108 -> 70.4 | AX108: =SUM(AF108:AW108) -> 176 | AY108: =$F108*AD108 -> 0 | AZ108: =$F108*AE108 -> 0 | BA108: =$F108*AF108 -> 0 | BB108: =$F108*AG108 -> 0 | BC108: =$F108*AH108 -> 0 | BD108: =$F108*AI108 -> 794.03661 | BE108: =$F108*AJ108 -> 3970.1831 | BF108: =$F108*AK108 -> 0 | ... BR108: =$F108*AW108 -> 3176.1464
...

Sheet Reference Sheet
A1: Fringe Rate
A2: 2023 | B2: 0.2136
A3: 2024 | B3: 0.1913
A4: 2025 | B4: 0.2245
A5: 2026 | B5: 0.2363
A7: Hours Available | F7: Annual Salaries | L7: TM Monthly Hr/Rate
A8: Year | B8: Month | C8: Work Days | D8: Avail Hours | F8: Employee | G8: 2023 | H8: 2024 | I8: 2025 | J8: 2026 | L8: Year | M8: Month | N8: Hourly Rate
A9: 2023 | B9: October | C9: 22 | D9: =C9*8 -> 176 | F9: Alkarein | I9: -53.2 | L9: 2023 | M9: October | N9: 90.415913
A10: 2023 | B10: November | C10: 22 | D10: =C10*8 -> 176 | F10: Anderson | I10: 61232 | L10: 2023 | M10: November | N10: 113.21531
A11: 2023 | B11: December | C11: 21 | D11: =C11*8 -> 168 | F11: Baxter | I11: 10805.36 | L11: 2023 | M11: December | N11: 103.87158
A12: 2024 | B12: January | C12: 23 | D12: =C12*8 -> 184 | F12: Bixel | I12: 2412.3 | L12: 2024 | M12: January | N12: 92.019408
A13: 2024 | B13: February | C13: 21 | D13: =C13*8 -> 168 | F13: Byers | I13: 20280.45 | L13: 2024 | M13: February | N13: 87.301587
A14: 2024 | B14: March | C14: 21 | D14: =C14*8 -> 168 | F14: Canton | I14: 9608.44 | L14: 2024 | M14: March | N14: 84.942085
A15: 2024 | B15: April | C15: 22 | D15: =C15*8 -> 176 | F15: Chunn | I15: 1430.65 | L15: 2024 | M15: April | N15: 98.619329
A16: 2024 | B16: May | C16: 23 | D16: =C16*8 -> 184 | F16: Davis | I16: 56212.62 | L16: 2024 | M16: May | N16: 80.586081
A17: 2024 | B17: June | C17: 20 | D17: =C17*8 -> 160 | F17: Dively | I17: 12715.75 | L17: 2024 | M17: June | N17: 95.835511
A18: 2024 | B18: July | C18: 23 | D18: =C18*8 -> 184 | F18: Dwyer | I18: 2782.9 | L18: 2024 | M18: July | N18: 79.034344
A19: 2024 | B19: August | C19: 22 | D19: =C19*8 -> 176 | F19: Engel | G19: 0 | H19: =(58028.52/(9.5/12)) -> 73299.183 | I19: 78307.73 | J19: 81000 | L19: 2024 | M19: August | N19: 104.16667
A20: 2024 | B20: September | C20: 21 | D20: =C20*8 -> 168 | F20: Ewing | G20: 148286.24 | H20: 168670.09 | I20: 192087.13 | J20: 210000 | L20: 2024 | M20: September | N20: 149.65986
A21: 2024 | B21: October | C21: 23 | D21: =C21*8 -> 184 | F21: Fiffick | I21: 83316.89 | L21: 2024 | M21: October | N21: 152.43902
A22: 2024 | B22: November | C22: 21 | D22: =C22*8 -> 168 | F22: Fries | I22: 4526.19 | L22: 2024 | M22: November | N22: 119.12497
A23: 2024 | B23: December | C23: 22 | D23: =C23*8 -> 176 | F23: Gaffney | G23: 118989.26 | H23: 134499.99 | I23: 171799.06 | J23: 189625 | L23: 2024 | M23: December | N23: 97.777778
A24: 2025 | B24: January | C24: 23 | D24: =C24*8 -> 184 | F24: Gordon | I24: 4533.22 | L24: 2025 | M24: January | N24: 99.547511
A25: 2025 | B25: February | C25: 20 | D25: =C25*8 -> 160 | F25: Griffin | I25: 65247.29 | L25: 2025 | M25: February | N25: 73.627845
A26: 2025 | B26: March | C26: 21 | D26: =C26*8 -> 168 | F26: Hurd | I26: 220.59 | L26: 2025 | M26: March | N26: 79.422383
A27: 2025 | B27: April | C27: 22 | D27: =C27*8 -> 176 | F27: Islam | I27: 19807.72 | L27: 2025 | M27: April | N27: 108.91089
A28: 2025 | B28: May | C28: 22 | D28: =C28*8 -> 176 | F28: Jadue | I28: 11359.63 | L28: 2025 | M28: May | N28: 90.415913
A29: 2025 | B29: June | C29: 21 | D29: =C29*8 -> 168 | F29: Jafarli | I29: 4599.01 | L29: 2025 | M29: June | N29: 73.450855
A30: 2025 | B30: July | C30: 23 | D30: =C30*8 -> 184 | F30: Jaric | G30: 67634.46 | H30: 78771.67 | I30: 78492.76 | J30: 80000 | L30: 2025 | M30: July | N30: 81.541883
A31: 2025 | B31: August | C31: 21 | D31: =C31*8 -> 168 | F31: Kale | G31: 0 | H31: 49157.16 | I31: 59850 | J31: 65000 | L31: 2025 | M31: August | N31: 79.15947
A32: 2025 | B32: September | C32: 22 | D32: =C32*8 -> 176 | F32: Kelly | I32: 117507.73 | L32: 2025 | M32: September | N32: 76.762038
A33: 2025 | B33: October | C33: 23 | D33: =C33*8 -> 184 | F33: Kummari | I33: 10726 | L33: 2025 | M33: October | N33: 80.093199
A34: 2025 | B34: November | C34: 20 | D34: =C34*8 -> 160 | F34: Lawrence | I34: 8947.31 | L34: 2025 | M34: November | N34: 86.614173
A35: 2025 | B35: December | C35: 23 | D35: =C35*8 -> 184 | F35: Leonard | I35: 14502.31 | L35: 2025 | M35: December | N35: 118.93204
A36: 2026 | B36: January | C36: 22 | D36: =C36*8 -> 176 | F36: Longo | G36: 70134.6 | H36: 89403.83 | I36: 91374.4 | J36: 96000 | L36: 2026 | M36: January | N36: 100.82151
A37: 2026 | B37: February | C37: 20 | D37: =C37*8 -> 160 | F37: Metzinger | G37: =2750*24 -> 66000 | H37: =2750*24 -> 66000 | I37: =(3000*23)+3375 -> 72375 | J37: =3375*24 -> 81000 | L37: 2026 | M37: February | N37: 99.206349
A38: 2026 | B38: March | C38: 22 | D38: =C38*8 -> 176 | F38: Micco | I38: 5059.17 | L38: 2026 | M38: March | N38: 89.689078
A39: 2026 | B39: April | C39: 22 | D39: =C39*8 -> 176 | F39: Moreno | I39: 1375.74 | L39: 2026 | M39: April | N39: 99.896404
A40: 2026 | B40: May | C40: 21 | D40: =C40*8 -> 168 | F40: Negro | G40: 54586.61 | H40: 68442.31 | I40: 76312.09 | J40: 80000 | L40: 2026 | M40: May | N40: 95.460331
A41: 2026 | B41: June | C41: 22 | D41: =C41*8 -> 176 | F41: Pasha | I41: 40670.05 | L41: 2026 | M41: June | N41: 142.85714
A42: 2026 | B42: July | C42: 23 | D42: =C42*8 -> 184 | F42: Payich | I42: 66222.22 | L42: 2026 | M42: July | N42: 108.88853
A43: 2026 | B43: August | C43: 22 | D43: =C43*8 -> 176 | F43: Politsky | I43: 68284.8
F44: Precurato | I44: 3001.55
F45: Rabenstine | I45: 8988.92
F46: Rhoades | I46: 23538.44
F47: Roch | I47: 18563.16
F48: Ruby | I48: 112467.42
F49: Shaulis | I49: 41192.27
F50: Sprowl | G50: =(49250/(9.5/12)) -> 62210.526 | H50: 71346.13 | I50: 71317.16 | J50: 77000
F51: Strock | I51: 13965.95
F52: Taylor | I52: 6085.9
F53: Unger | I53: 0
F54: Wheeler | I54: 83316.89

Sheet Summary Sheet
A1: Grant | B1: Billed | C1: Actual | D1: Difference
A2: Drive AM | B2: =SUM('D-AM'!B11:AF11) -> 668909.02 | C2: =SUM('D-AM'!B10:AF10) -> 506630.94 | D2: =C2-B2 -> -162278.08
A3: Hybrid | B3: =SUM(Hybrid!B28:AH28) -> 512509.12 | C3: =SUM(Hybrid!B27:AH27) -> 253639.06 | D3: =C3-B3 -> -258870.06
A4: LTM | B4: =SUM(LTM!B11:W11) -> 164857.44 | C4: =SUM(LTM!B10:W10) -> 142280.2 | D4: =C4-B4 -> -22577.237
D5: =SUM(D2:D4) -> -443725.38

Sheet D-AM
B1: 2024 | N1: 2025 | Z1: 2026
A2: Employee | B2: January | C2: February | D2: March | E2: April | F2: May | G2: June | H2: July | I2: August | J2: September | K2: October | L2: November | M2: December | N2: January | O2: February | P2: March | Q2: April | R2: May | S2: June | T2: July | U2: August | V2: September | W2: October | X2: November | Y2: December | Z2: January | AA2: February | AB2: March | AC2: April | AD2: May | AE2: June | AF2: July
A3: Engel | B3: {=SUMPRODUCT(('Hours Log'!$A$2:$A$980=$A3)*('Hours Log'!$B$2:$B$980=B$2)*('Hours Log'!$C$2:$C$980=LOOKUP(2,1/($A$1:B$1<>""),$A$1:B$1))*'Hours Log'!$F$2:$F$980*'Hours Log'!$AJ$2:$AJ$980)} -> 0 | C3: {=SUMPRODUCT(('Hours Log'!$A$2:$A$980=$A3)*('Hours Log'!$B$2:$B$980=C$2)*('Hours Log'!$C$2:$C$980=LOOKUP(2,1/($A$1:C$1<>""),$A$1:C$1))*'Hours Log'!$F$2:$F$980*'Hours Log'!$AJ$2:$AJ$980)} -> 0 | D3: {=SUMPRODUCT(('Hours Log'!$A$2:$A$980=$A3)*('Hours Log'!$B$2:$B$980=D$2)*('Hours Log'!$C$2:$C$980=LOOKUP(2,1/($A$1:D$1<>""),$A$1:D$1))*'Hours Log'!$F$2:$F$980*'Hours Log'!$AJ$2:$AJ$980)} -> 3358.5122 | E3: {=SUMPRODUCT(('Hours Log'!$A$2:$A$980=$A3)*('Hours Log'!$B$2:$B$980=E$2)*('Hours Log'!$C$2:$C$980=LOOKUP(2,1/($A$1:E$1<>""),$A$1:E$1))*'Hours Log'!$F$2:$F$980*'Hours Log'!$AJ$2:$AJ$980)} -> 7388.7268 | F3: {=SUMPRODUCT(('Hours Log'!$A$2:$A$980=$A3)*('Hours Log'!$B$2:$B$980=F$2)*('Hours Log'!$C$2:$C$980=LOOKUP(2,1/($A$1:F$1<>""),$A$1:F$1))*'Hours Log'!$F$2:$F$980*'Hours Log'!$AJ$2:$AJ$980)} -> 7724.578 | G3: {=SUMPRODUCT(('Hours Log'!$A$2:$A$980=$A3)*('Hours Log'!$B$2:$B$980=G$2)*('Hours Log'!$C$2:$C$980=LOOKUP(2,1/($A$1:G$1<>""),$A$1:G$1))*'Hours Log'!$F$2:$F$980*'Hours Log'!$AJ$2:$AJ$980)} -> 6717.0244 | H3: {=SUMPRODUCT(('Hours Log'!$A$2:$A$980=$A3)*('Hours Log'!$B$2:$B$980=H$2)*('Hours Log'!$C$2:$C$980=LOOKUP(2,1/($A$1:H$1<>""),$A$1:H$1))*'Hours Log'!$F$2:$F$980*'Hours Log'!$AJ$2:$AJ$980)} -> 7724.578 | I3: {=SUMPRODUCT(('Hours Log'!$A$2:$A$980=$A3)*('Hours Log'!$B$2:$B$980=I$2)*('Hours Log'!$C$2:$C$980=LOOKUP(2,1/($A$1:I$1<>""),$A$1:I$1))*'Hours Log'!$F$2:$F$980*'Hours Log'!$AJ$2:$AJ$980)} -> 7388.7268 | ... AF3: {=SUMPRODUCT(('Hours Log'!$A$2:$A$980=$A3)*('Hours Log'!$B$2:$B$980=AF$2)*('Hours Log'!$C$2:$C$980=LOOKUP(2,1/($A$1:AF$1<>""),$A$1:AF$1))*'Hours Log'!$F$2:$F$980*'Hours Log'!$AJ$2:$AJ$980)} -> 361.57408
A4: Jaric | B4: {=SUMPRODUCT(('Hours Log'!$A$2:$A$980=$A4)*('Hours Log'!$B$2:$B$980=B$2)*('Hours Log'!$C$2:$C$980=LOOKUP(2,1/($A$1:B$1<>""),$A$1:B$1))*'Hours Log'!$F$2:$F$980*'Hours Log'!$AJ$2:$AJ$980)} -> 4150.6459 | C4: {=SUMPRODUCT(('Hours Log'!$A$2:$A$980=$A4)*('Hours Log'!$B$2:$B$980=C$2)*('Hours Log'!$C$2:$C$980=LOOKUP(2,1/($A$1:C$1<>""),$A$1:C$1))*'Hours Log'!$F$2:$F$980*'Hours Log'!$AJ$2:$AJ$980)} -> 3789.7202 | D4: {=SUMPRODUCT(('Hours Log'!$A$2:$A$980=$A4)*('Hours Log'!$B$2:$B$980=D$2)*('Hours Log'!$C$2:$C$980=LOOKUP(2,1/($A$1:D$1<>""),$A$1:D$1))*'Hours Log'!$F$2:$F$980*'Hours Log'!$AJ$2:$AJ$980)} -> 3789.7202 | E4: {=SUMPRODUCT(('Hours Log'!$A$2:$A$980=$A4)*('Hours Log'!$B$2:$B$980=E$2)*('Hours Log'!$C$2:$C$980=LOOKUP(2,1/($A$1:E$1<>""),$A$1:E$1))*'Hours Log'!$F$2:$F$980*'Hours Log'!$AJ$2:$AJ$980)} -> 3970.1831 | F4: {=SUMPRODUCT(('Hours Log'!$A$2:$A$980=$A4)*('Hours Log'!$B$2:$B$980=F$2)*('Hours Log'!$C$2:$C$980=LOOKUP(2,1/($A$1:F$1<>""),$A$1:F$1))*'Hours Log'!$F$2:$F$980*'Hours Log'!$AJ$2:$AJ$980)} -> 4150.6459 | G4: {=SUMPRODUCT(('Hours Log'!$A$2:$A$980=$A4)*('Hours Log'!$B$2:$B$980=G$2)*('Hours Log'!$C$2:$C$980=LOOKUP(2,1/($A$1:G$1<>""),$A$1:G$1))*'Hours Log'!$F$2:$F$980*'Hours Log'!$AJ$2:$AJ$980)} -> 3609.2573 | H4: {=SUMPRODUCT(('Hours Log'!$A$2:$A$980=$A4)*('Hours Log'!$B$2:$B$980=H$2)*('Hours Log'!$C$2:$C$980=LOOKUP(2,1/($A$1:H$1<>""),$A$1:H$1))*'Hours Log'!$F$2:$F$980*'Hours Log'!$AJ$2:$AJ$980)} -> 4150.6459 | I4: {=SUMPRODUCT(('Hours Log'!$A$2:$A$980=$A4)*('Hours Log'!$B$2:$B$980=I$2)*('Hours Log'!$C$2:$C$980=LOOKUP(2,1/($A$1:I$1<>""),$A$1:I$1))*'Hours Log'!$F$2:$F$980*'Hours Log'!$AJ$2:$AJ$980)} -> 3970.1831 | ... AF4: {=SUMPRODUCT(('Hours Log'!$A$2:$A$980=$A4)*('Hours Log'!$B$2:$B$980=AF$2)*('Hours Log'!$C$2:$C$980=LOOKUP(2,1/($A$1:AF$1<>""),$A$1:AF$1))*'Hours Log'!$F$2:$F$980*'Hours Log'!$AJ$2:$AJ$980)} -> 4374.6
A5: Gaffney | B5: {=SUMPRODUCT(('Hours Log'!$A$2:$A$980=$A5)*('Hours Log'!$B$2:$B$980=B$2)*('Hours Log'!$C$2:$C$980=LOOKUP(2,1/($A$1:B$1<>""),$A$1:B$1))*'Hours Log'!$F$2:$F$980*'Hours Log'!$AJ$2:$AJ$980)} -> 1155.5036 | C5: {=SUMPRODUCT(('Hours Log'!$A$2:$A$980=$A5)*('Hours Log'!$B$2:$B$980=C$2)*('Hours Log'!$C$2:$C$980=LOOKUP(2,1/($A$1:C$1<>""),$A$1:C$1))*'Hours Log'!$F$2:$F$980*'Hours Log'!$AJ$2:$AJ$980)} -> 1325.3488 | D5: {=SUMPRODUCT(('Hours Log'!$A$2:$A$980=$A5)*('Hours Log'!$B$2:$B$980=D$2)*('Hours Log'!$C$2:$C$980=LOOKUP(2,1/($A$1:D$1<>""),$A$1:D$1))*'Hours Log'!$F$2:$F$980*'Hours Log'!$AJ$2:$AJ$980)} -> 4448.689 | E5: {=SUMPRODUCT(('Hours Log'!$A$2:$A$980=$A5)*('Hours Log'!$B$2:$B$980=E$2)*('Hours Log'!$C$2:$C$980=LOOKUP(2,1/($A$1:E$1<>""),$A$1:E$1))*'Hours Log'!$F$2:$F$980*'Hours Log'!$AJ$2:$AJ$980)} -> 3389.4773 | F5: {=SUMPRODUCT(('Hours Log'!$A$2:$A$980=$A5)*('Hours Log'!$B$2:$B$980=F$2)*('Hours Log'!$C$2:$C$980=LOOKUP(2,1/($A$1:F$1<>""),$A$1:F$1))*'Hours Log'!$F$2:$F$980*'Hours Log'!$AJ$2:$AJ$980)} -> 3624.0796 | G5: {=SUMPRODUCT(('Hours Log'!$A$2:$A$980=$A5)*('Hours Log'!$B$2:$B$980=G$2)*('Hours Log'!$C$2:$C$980=LOOKUP(2,1/($A$1:G$1<>""),$A$1:G$1))*'Hours Log'!$F$2:$F$980*'Hours Log'!$AJ$2:$AJ$980)} -> 3318.3694 | H5: {=SUMPRODUCT(('Hours Log'!$A$2:$A$980=$A5)*('Hours Log'!$B$2:$B$980=H$2)*('Hours Log'!$C$2:$C$980=LOOKUP(2,1/($A$1:H$1<>""),$A$1:H$1))*'Hours Log'!$F$2:$F$980*'Hours Log'!$AJ$2:$AJ$980)} -> 3624.0796 | I5: {=SUMPRODUCT(('Hours Log'!$A$2:$A$980=$A5)*('Hours Log'!$B$2:$B$980=I$2)*('Hours Log'!$C$2:$C$980=LOOKUP(2,1/($A$1:I$1<>""),$A$1:I$1))*'Hours Log'!$F$2:$F$980*'Hours Log'!$AJ$2:$AJ$980)} -> 2744.8528 | ... AF5: {=SUMPRODUCT(('Hours Log'!$A$2:$A$980=$A5)*('Hours Log'!$B$2:$B$980=AF$2)*('Hours Log'!$C$2:$C$980=LOOKUP(2,1/($A$1:AF$1<>""),$A$1:AF$1))*'Hours Log'!$F$2:$F$980*'Hours Log'!$AJ$2:$AJ$980)} -> 4573.0694
A6: Negro | B6: {=SUMPRODUCT(('Hours Log'!$A$2:$A$980=$A6)*('Hours Log'!$B$2:$B$980=B$2)*('Hours Log'!$C$2:$C$980=LOOKUP(2,1/($A$1:B$1<>""),$A$1:B$1))*'Hours Log'!$F$2:$F$980*'Hours Log'!$AJ$2:$AJ$980)} -> 0 | C6: {=SUMPRODUCT(('Hours Log'!$A$2:$A$980=$A6)*('Hours Log'!$B$2:$B$980=C$2)*('Hours Log'!$C$2:$C$980=LOOKUP(2,1/($A$1:C$1<>""),$A$1:C$1))*'Hours Log'!$F$2:$F$980*'Hours Log'!$AJ$2:$AJ$980)} -> 0 | D6: {=SUMPRODUCT(('Hours Log'!$A$2:$A$980=$A6)*('Hours Log'!$B$2:$B$980=D$2)*('Hours Log'!$C$2:$C$980=LOOKUP(2,1/($A$1:D$1<>""),$A$1:D$1))*'Hours Log'!$F$2:$F$980*'Hours Log'!$AJ$2:$AJ$980)} -> 3684.2212 | E6: {=SUMPRODUCT(('Hours Log'!$A$2:$A$980=$A6)*('Hours Log'!$B$2:$B$980=E$2)*('Hours Log'!$C$2:$C$980=LOOKUP(2,1/($A$1:E$1<>""),$A$1:E$1))*'Hours Log'!$F$2:$F$980*'Hours Log'!$AJ$2:$AJ$980)} -> 3942.3673 | F6: {=SUMPRODUCT(('Hours Log'!$A$2:$A$980=$A6)*('Hours Log'!$B$2:$B$980=F$2)*('Hours Log'!$C$2:$C$980=LOOKUP(2,1/($A$1:F$1<>""),$A$1:F$1))*'Hours Log'!$F$2:$F$980*'Hours Log'!$AJ$2:$AJ$980)} -> 4042.8098 | G6: {=SUMPRODUCT(('Hours Log'!$A$2:$A$980=$A6)*('Hours Log'!$B$2:$B$980=G$2)*('Hours Log'!$C$2:$C$980=LOOKUP(2,1/($A$1:G$1<>""),$A$1:G$1))*'Hours Log'!$F$2:$F$980*'Hours Log'!$AJ$2:$AJ$980)} -> 3729.2664 | H6: {=SUMPRODUCT(('Hours Log'!$A$2:$A$980=$A6)*('Hours Log'!$B$2:$B$980=H$2)*('Hours Log'!$C$2:$C$980=LOOKUP(2,1/($A$1:H$1<>""),$A$1:H$1))*'Hours Log'!$F$2:$F$980*'Hours Log'!$AJ$2:$AJ$980)} -> 4042.8098 | I6: {=SUMPRODUCT(('Hours Log'!$A$2:$A$980=$A6)*('Hours Log'!$B$2:$B$980=I$2)*('Hours Log'!$C$2:$C$980=LOOKUP(2,1/($A$1:I$1<>""),$A$1:I$1))*'Hours Log'!$F$2:$F$980*'Hours Log'!$AJ$2:$AJ$980)} -> 3942.3673 | ... AF6: {=SUMPRODUCT(('Hours Log'!$A$2:$A$980=$A6)*('Hours Log'!$B$2:$B$980=AF$2)*('Hours Log'!$C$2:$C$980=LOOKUP(2,1/($A$1:AF$1<>""),$A$1:AF$1))*'Hours Log'!$F$2:$F$980*'Hours Log'!$AJ$2:$AJ$980)} -> 4839.983
A7: Kale | B7: {=SUMPRODUCT(('Hours Log'!$A$2:$A$980=$A7)*('Hours Log'!$B$2:$B$980=B$2)*('Hours Log'!$C$2:$C$980=LOOKUP(2,1/($A$1:B$1<>""),$A$1:B$1))*'Hours Log'!$F$2:$F$980*'Hours Log'!$AJ$2:$AJ$980)} -> 140.77145 | C7: {=SUMPRODUCT(('Hours Log'!$A$2:$A$980=$A7)*('Hours Log'!$B$2:$B$980=C$2)*('Hours Log'!$C$2:$C$980=LOOKUP(2,1/($A$1:C$1<>""),$A$1:C$1))*'Hours Log'!$F$2:$F$980*'Hours Log'!$AJ$2:$AJ$980)} -> 760.16585 | D7: {=SUMPRODUCT(('Hours Log'!$A$2:$A$980=$A7)*('Hours Log'!$B$2:$B$980=D$2)*('Hours Log'!$C$2:$C$980=LOOKUP(2,1/($A$1:D$1<>""),$A$1:D$1))*'Hours Log'!$F$2:$F$980*'Hours Log'!$AJ$2:$AJ$980)} -> 1126.1716 | E7: {=SUMPRODUCT(('Hours Log'!$A$2:$A$980=$A7)*('Hours Log'!$B$2:$B$980=E$2)*('Hours Log'!$C$2:$C$980=LOOKUP(2,1/($A$1:E$1<>""),$A$1:E$1))*'Hours Log'!$F$2:$F$980*'Hours Log'!$AJ$2:$AJ$980)} -> 1266.9431 | F7: {=SUMPRODUCT(('Hours Log'!$A$2:$A$980=$A7)*('Hours Log'!$B$2:$B$980=F$2)*('Hours Log'!$C$2:$C$980=LOOKUP(2,1/($A$1:F$1<>""),$A$1:F$1))*'Hours Log'!$F$2:$F$980*'Hours Log'!$AJ$2:$AJ$980)} -> 1604.7946 | G7: {=SUMPRODUCT(('Hours Log'!$A$2:$A$980=$A7)*('Hours Log'!$B$2:$B$980=G$2)*('Hours Log'!$C$2:$C$980=LOOKUP(2,1/($A$1:G$1<>""),$A$1:G$1))*'Hours Log'!$F$2:$F$980*'Hours Log'!$AJ$2:$AJ$980)} -> 1238.7888 | H7: {=SUMPRODUCT(('Hours Log'!$A$2:$A$980=$A7)*('Hours Log'!$B$2:$B$980=H$2)*('Hours Log'!$C$2:$C$980=LOOKUP(2,1/($A$1:H$1<>""),$A$1:H$1))*'Hours Log'!$F$2:$F$980*'Hours Log'!$AJ$2:$AJ$980)} -> 1041.7088 | I7: {=SUMPRODUCT(('Hours Log'!$A$2:$A$980=$A7)*('Hours Log'!$B$2:$B$980=I$2)*('Hours Log'!$C$2:$C$980=LOOKUP(2,1/($A$1:I$1<>""),$A$1:I$1))*'Hours Log'!$F$2:$F$980*'Hours Log'!$AJ$2:$AJ$980)} -> 1351.406 | ... AF7: {=SUMPRODUCT(('Hours Log'!$A$2:$A$980=$A7)*('Hours Log'!$B$2:$B$980=AF$2)*('Hours Log'!$C$2:$C$980=LOOKUP(2,1/($A$1:AF$1<>""),$A$1:AF$1))*'Hours Log'!$F$2:$F$980*'Hours Log'!$AJ$2:$AJ$980)} -> 0
A8: Sprowl | B8: {=SUMPRODUCT(('Hours Log'!$A$2:$A$980=$A8)*('Hours Log'!$B$2:$B$980=B$2)*('Hours Log'!$C$2:$C$980=LOOKUP(2,1/($A$1:B$1<>""),$A$1:B$1))*'Hours Log'!$F$2:$F$980*'Hours Log'!$AJ$2:$AJ$980)} -> 0 | C8: {=SUMPRODUCT(('Hours Log'!$A$2:$A$980=$A8)*('Hours Log'!$B$2:$B$980=C$2)*('Hours Log'!$C$2:$C$980=LOOKUP(2,1/($A$1:C$1<>""),$A$1:C$1))*'Hours Log'!$F$2:$F$980*'Hours Log'!$AJ$2:$AJ$980)} -> 61.294215 | D8: {=SUMPRODUCT(('Hours Log'!$A$2:$A$980=$A8)*('Hours Log'!$B$2:$B$980=D$2)*('Hours Log'!$C$2:$C$980=LOOKUP(2,1/($A$1:D$1<>""),$A$1:D$1))*'Hours Log'!$F$2:$F$980*'Hours Log'!$AJ$2:$AJ$980)} -> 122.58843 | E8: {=SUMPRODUCT(('Hours Log'!$A$2:$A$980=$A8)*('Hours Log'!$B$2:$B$980=E$2)*('Hours Log'!$C$2:$C$980=LOOKUP(2,1/($A$1:E$1<>""),$A$1:E$1))*'Hours Log'!$F$2:$F$980*'Hours Log'!$AJ$2:$AJ$980)} -> 102.15702 | F8: {=SUMPRODUCT(('Hours Log'!$A$2:$A$980=$A8)*('Hours Log'!$B$2:$B$980=F$2)*('Hours Log'!$C$2:$C$980=LOOKUP(2,1/($A$1:F$1<>""),$A$1:F$1))*'Hours Log'!$F$2:$F$980*'Hours Log'!$AJ$2:$AJ$980)} -> 490.35372 | G8: {=SUMPRODUCT(('Hours Log'!$A$2:$A$980=$A8)*('Hours Log'!$B$2:$B$980=G$2)*('Hours Log'!$C$2:$C$980=LOOKUP(2,1/($A$1:G$1<>""),$A$1:G$1))*'Hours Log'!$F$2:$F$980*'Hours Log'!$AJ$2:$AJ$980)} -> 20.431405 | H8: {=SUMPRODUCT(('Hours Log'!$A$2:$A$980=$A8)*('Hours Log'!$B$2:$B$980=H$2)*('Hours Log'!$C$2:$C$980=LOOKUP(2,1/($A$1:H$1<>""),$A$1:H$1))*'Hours Log'!$F$2:$F$980*'Hours Log'!$AJ$2:$AJ$980)} -> 510.78512 | I8: {=SUMPRODUCT(('Hours Log'!$A$2:$A$980=$A8)*('Hours Log'!$B$2:$B$980=I$2)*('Hours Log'!$C$2:$C$980=LOOKUP(2,1/($A$1:I$1<>""),$A$1:I$1))*'Hours Log'!$F$2:$F$980*'Hours Log'!$AJ$2:$AJ$980)} -> 81.72562 | ... AF8: {=SUMPRODUCT(('Hours Log'!$A$2:$A$980=$A8)*('Hours Log'!$B$2:$B$980=AF$2)*('Hours Log'!$C$2:$C$980=LOOKUP(2,1/($A$1:AF$1<>""),$A$1:AF$1))*'Hours Log'!$F$2:$F$980*'Hours Log'!$AJ$2:$AJ$980)} -> 68.650312
A10: Total Actual Labor | B10: =SUM(B3:B8) -> 5446.921 | C10: =SUM(C3:C8) -> 5936.529 | D10: =SUM(D3:D8) -> 16529.903 | E10: =SUM(E3:E8) -> 20059.855 | F10: =SUM(F3:F8) -> 21637.262 | G10: =SUM(G3:G8) -> 18633.138 | H10: =SUM(H3:H8) -> 21094.607 | I10: =SUM(I3:I8) -> 19479.262 | ... AF10: =SUM(AF3:AF8) -> 14217.877
A11: Billed Labor | D11: 25373.65 | E11: 25373.65 | F11: 25373.65 | G11: 25373.65 | H11: 25373.65 | I11: 25373.65 | J11: 25373.65 | K11: 25373.65 | L11: 25373.65 | M11: 25373.65 | N11: 25373.65 | O11: 25373.65 | P11: 25373.65 | Q11: 25373.65 | R11: 25373.65 | S11: 25373.65 | T11: 25373.65 | U11: 25373.65 | V11: 25373.65 | W11: 25373.65 | X11: 25373.65 | Y11: 25373.65 | Z11: 18448.11 | AA11: 18448.11 | AB11: 18448.11 | AC11: 18448.11 | AD11: 18448.11 | AE11: 18448.17
A12: Difference | B12: =B10-B11 -> 5446.921 | C12: 77 | D12: =D10-D11 -> -8843.7473 | E12: =E10-E11 -> -5313.7954 | F12: =F10-F11 -> -3736.3884 | G12: =G10-G11 -> -6740.5123 | H12: =H10-H11 -> -4279.0428 | I12: =I10-I11 -> -5894.3884 | J12: =J10-J11 -> -4804.1628 | K12: =K10-K11 -> -9372.9914 | ... AF12: =AF10-AF11 -> 14217.877 | AG12: =SUM(B12:AF12) -> -168137.61
A14: Indirect is taken on all of it

Sheet Hybrid
B1: 2023 | E1: 2024 | Q1: 2025 | AC1: 2026
A2: Employee | B2: October | C2: November | D2: December | E2: January | F2: February | G2: March | H2: April | I2: May | J2: June | K2: July | L2: August | M2: September | N2: October | O2: November | P2: December | Q2: January | R2: February | S2: March | T2: April | U2: May | V2: June | W2: July | X2: August | Y2: September | Z2: October | AA2: November | AB2: December | AC2: January | AD2: February | AE2: March | AF2: April | AG2: May | AH2: June
A3: Longo | B3: {=SUMPRODUCT(('Hours Log'!$A$2:$A$979=$A3)*('Hours Log'!$B$2:$B$979=B$2)*('Hours Log'!$C$2:$C$979=LOOKUP(2,1/($A$1:B$1<>""),$A$1:B$1))*'Hours Log'!$F$2:$F$979*'Hours Log'!$AN$2:$AN$979)} -> 4501.2926 | C3: {=SUMPRODUCT(('Hours Log'!$A$2:$A$979=$A3)*('Hours Log'!$B$2:$B$979=C$2)*('Hours Log'!$C$2:$C$979=LOOKUP(2,1/($A$1:C$1<>""),$A$1:C$1))*'Hours Log'!$F$2:$F$979*'Hours Log'!$AN$2:$AN$979)} -> 4051.1633 | D3: {=SUMPRODUCT(('Hours Log'!$A$2:$A$979=$A3)*('Hours Log'!$B$2:$B$979=D$2)*('Hours Log'!$C$2:$C$979=LOOKUP(2,1/($A$1:D$1<>""),$A$1:D$1))*'Hours Log'!$F$2:$F$979*'Hours Log'!$AN$2:$AN$979)} -> 4378.5301 | E3: {=SUMPRODUCT(('Hours Log'!$A$2:$A$979=$A3)*('Hours Log'!$B$2:$B$979=E$2)*('Hours Log'!$C$2:$C$979=LOOKUP(2,1/($A$1:E$1<>""),$A$1:E$1))*'Hours Log'!$F$2:$F$979*'Hours Log'!$AN$2:$AN$979)} -> 3251.5292 | F3: {=SUMPRODUCT(('Hours Log'!$A$2:$A$979=$A3)*('Hours Log'!$B$2:$B$979=F$2)*('Hours Log'!$C$2:$C$979=LOOKUP(2,1/($A$1:F$1<>""),$A$1:F$1))*'Hours Log'!$F$2:$F$979*'Hours Log'!$AN$2:$AN$979)} -> 2637.067 | G3: {=SUMPRODUCT(('Hours Log'!$A$2:$A$979=$A3)*('Hours Log'!$B$2:$B$979=G$2)*('Hours Log'!$C$2:$C$979=LOOKUP(2,1/($A$1:G$1<>""),$A$1:G$1))*'Hours Log'!$F$2:$F$979*'Hours Log'!$AN$2:$AN$979)} -> 1382.54 | H3: {=SUMPRODUCT(('Hours Log'!$A$2:$A$979=$A3)*('Hours Log'!$B$2:$B$979=H$2)*('Hours Log'!$C$2:$C$979=LOOKUP(2,1/($A$1:H$1<>""),$A$1:H$1))*'Hours Log'!$F$2:$F$979*'Hours Log'!$AN$2:$AN$979)} -> 3971.4394 | I3: {=SUMPRODUCT(('Hours Log'!$A$2:$A$979=$A3)*('Hours Log'!$B$2:$B$979=I$2)*('Hours Log'!$C$2:$C$979=LOOKUP(2,1/($A$1:I$1<>""),$A$1:I$1))*'Hours Log'!$F$2:$F$979*'Hours Log'!$AN$2:$AN$979)} -> 3379.5421 | ... AH3: {=SUMPRODUCT(('Hours Log'!$A$2:$A$979=$A3)*('Hours Log'!$B$2:$B$979=AH$2)*('Hours Log'!$C$2:$C$979=LOOKUP(2,1/($A$1:AH$1<>""),$A$1:AH$1))*'Hours Log'!$F$2:$F$979*'Hours Log'!$AN$2:$AN$979)} -> 5306.58
A4: Jaric | B4: {=SUMPRODUCT(('Hours Log'!$A$2:$A$979=$A4)*('Hours Log'!$B$2:$B$979=B$2)*('Hours Log'!$C$2:$C$979=LOOKUP(2,1/($A$1:B$1<>""),$A$1:B$1))*'Hours Log'!$F$2:$F$979*'Hours Log'!$AN$2:$AN$979)} -> 1562.0986 | C4: {=SUMPRODUCT(('Hours Log'!$A$2:$A$979=$A4)*('Hours Log'!$B$2:$B$979=C$2)*('Hours Log'!$C$2:$C$979=LOOKUP(2,1/($A$1:C$1<>""),$A$1:C$1))*'Hours Log'!$F$2:$F$979*'Hours Log'!$AN$2:$AN$979)} -> 1712.5473 | D4: {=SUMPRODUCT(('Hours Log'!$A$2:$A$979=$A4)*('Hours Log'!$B$2:$B$979=D$2)*('Hours Log'!$C$2:$C$979=LOOKUP(2,1/($A$1:D$1<>""),$A$1:D$1))*'Hours Log'!$F$2:$F$979*'Hours Log'!$AN$2:$AN$979)} -> 583.06226 | E4: {=SUMPRODUCT(('Hours Log'!$A$2:$A$979=$A4)*('Hours Log'!$B$2:$B$979=E$2)*('Hours Log'!$C$2:$C$979=LOOKUP(2,1/($A$1:E$1<>""),$A$1:E$1))*'Hours Log'!$F$2:$F$979*'Hours Log'!$AN$2:$AN$979)} -> 0 | F4: {=SUMPRODUCT(('Hours Log'!$A$2:$A$979=$A4)*('Hours Log'!$B$2:$B$979=F$2)*('Hours Log'!$C$2:$C$979=LOOKUP(2,1/($A$1:F$1<>""),$A$1:F$1))*'Hours Log'!$F$2:$F$979*'Hours Log'!$AN$2:$AN$979)} -> 0 | G4: {=SUMPRODUCT(('Hours Log'!$A$2:$A$979=$A4)*('Hours Log'!$B$2:$B$979=G$2)*('Hours Log'!$C$2:$C$979=LOOKUP(2,1/($A$1:G$1<>""),$A$1:G$1))*'Hours Log'!$F$2:$F$979*'Hours Log'!$AN$2:$AN$979)} -> 0 | H4: {=SUMPRODUCT(('Hours Log'!$A$2:$A$979=$A4)*('Hours Log'!$B$2:$B$979=H$2)*('Hours Log'!$C$2:$C$979=LOOKUP(2,1/($A$1:H$1<>""),$A$1:H$1))*'Hours Log'!$F$2:$F$979*'Hours Log'!$AN$2:$AN$979)} -> 0 | I4: {=SUMPRODUCT(('Hours Log'!$A$2:$A$979=$A4)*('Hours Log'!$B$2:$B$979=I$2)*('Hours Log'!$C$2:$C$979=LOOKUP(2,1/($A$1:I$1<>""),$A$1:I$1))*'Hours Log'!$F$2:$F$979*'Hours Log'!$AN$2:$AN$979)} -> 0 | ... AH4: {=SUMPRODUCT(('Hours Log'!$A$2:$A$979=$A4)*('Hours Log'!$B$2:$B$979=AH$2)*('Hours Log'!$C$2:$C$979=LOOKUP(2,1/($A$1:AH$1<>""),$A$1:AH$1))*'Hours Log'!$F$2:$F$979*'Hours Log'!$AN$2:$AN$979)} -> 0
A5: Gaffney | B5: {=SUMPRODUCT(('Hours Log'!$A$2:$A$979=$A5)*('Hours Log'!$B$2:$B$979=B$2)*('Hours Log'!$C$2:$C$979=LOOKUP(2,1/($A$1:B$1<>""),$A$1:B$1))*'Hours Log'!$F$2:$F$979*'Hours Log'!$AN$2:$AN$979)} -> 2181.9492 | C5: {=SUMPRODUCT(('Hours Log'!$A$2:$A$979=$A5)*('Hours Log'!$B$2:$B$979=C$2)*('Hours Log'!$C$2:$C$979=LOOKUP(2,1/($A$1:C$1<>""),$A$1:C$1))*'Hours Log'!$F$2:$F$979*'Hours Log'!$AN$2:$AN$979)} -> 3064.3048 | D5: {=SUMPRODUCT(('Hours Log'!$A$2:$A$979=$A5)*('Hours Log'!$B$2:$B$979=D$2)*('Hours Log'!$C$2:$C$979=LOOKUP(2,1/($A$1:D$1<>""),$A$1:D$1))*'Hours Log'!$F$2:$F$979*'Hours Log'!$AN$2:$AN$979)} -> 2344.4242 | E5: {=SUMPRODUCT(('Hours Log'!$A$2:$A$979=$A5)*('Hours Log'!$B$2:$B$979=E$2)*('Hours Log'!$C$2:$C$979=LOOKUP(2,1/($A$1:E$1<>""),$A$1:E$1))*'Hours Log'!$F$2:$F$979*'Hours Log'!$AN$2:$AN$979)} -> 3851.6788 | F5: {=SUMPRODUCT(('Hours Log'!$A$2:$A$979=$A5)*('Hours Log'!$B$2:$B$979=F$2)*('Hours Log'!$C$2:$C$979=LOOKUP(2,1/($A$1:F$1<>""),$A$1:F$1))*'Hours Log'!$F$2:$F$979*'Hours Log'!$AN$2:$AN$979)} -> 3118.4677 | G5: {=SUMPRODUCT(('Hours Log'!$A$2:$A$979=$A5)*('Hours Log'!$B$2:$B$979=G$2)*('Hours Log'!$C$2:$C$979=LOOKUP(2,1/($A$1:G$1<>""),$A$1:G$1))*'Hours Log'!$F$2:$F$979*'Hours Log'!$AN$2:$AN$979)} -> 2022.1314 | H5: {=SUMPRODUCT(('Hours Log'!$A$2:$A$979=$A5)*('Hours Log'!$B$2:$B$979=H$2)*('Hours Log'!$C$2:$C$979=LOOKUP(2,1/($A$1:H$1<>""),$A$1:H$1))*'Hours Log'!$F$2:$F$979*'Hours Log'!$AN$2:$AN$979)} -> 2601.2268 | I5: {=SUMPRODUCT(('Hours Log'!$A$2:$A$979=$A5)*('Hours Log'!$B$2:$B$979=I$2)*('Hours Log'!$C$2:$C$979=LOOKUP(2,1/($A$1:I$1<>""),$A$1:I$1))*'Hours Log'!$F$2:$F$979*'Hours Log'!$AN$2:$AN$979)} -> 3463.0094 | ... AH5: {=SUMPRODUCT(('Hours Log'!$A$2:$A$979=$A5)*('Hours Log'!$B$2:$B$979=AH$2)*('Hours Log'!$C$2:$C$979=LOOKUP(2,1/($A$1:AH$1<>""),$A$1:AH$1))*'Hours Log'!$F$2:$F$979*'Hours Log'!$AN$2:$AN$979)} -> 0
A6: Ewing | B6: {=SUMPRODUCT(('Hours Log'!$A$2:$A$979=$A6)*('Hours Log'!$B$2:$B$979=B$2)*('Hours Log'!$C$2:$C$979=LOOKUP(2,1/($A$1:B$1<>""),$A$1:B$1))*'Hours Log'!$F$2:$F$979*'Hours Log'!$AN$2:$AN$979)} -> 415.29273 | C6: {=SUMPRODUCT(('Hours Log'!$A$2:$A$979=$A6)*('Hours Log'!$B$2:$B$979=C$2)*('Hours Log'!$C$2:$C$979=LOOKUP(2,1/($A$1:C$1<>""),$A$1:C$1))*'Hours Log'!$F$2:$F$979*'Hours Log'!$AN$2:$AN$979)} -> 415.29273 | D6: {=SUMPRODUCT(('Hours Log'!$A$2:$A$979=$A6)*('Hours Log'!$B$2:$B$979=D$2)*('Hours Log'!$C$2:$C$979=LOOKUP(2,1/($A$1:D$1<>""),$A$1:D$1))*'Hours Log'!$F$2:$F$979*'Hours Log'!$AN$2:$AN$979)} -> 415.29273 | E6: {=SUMPRODUCT(('Hours Log'!$A$2:$A$979=$A6)*('Hours Log'!$B$2:$B$979=E$2)*('Hours Log'!$C$2:$C$979=LOOKUP(2,1/($A$1:E$1<>""),$A$1:E$1))*'Hours Log'!$F$2:$F$979*'Hours Log'!$AN$2:$AN$979)} -> 463.70003 | F6: {=SUMPRODUCT(('Hours Log'!$A$2:$A$979=$A6)*('Hours Log'!$B$2:$B$979=F$2)*('Hours Log'!$C$2:$C$979=LOOKUP(2,1/($A$1:F$1<>""),$A$1:F$1))*'Hours Log'!$F$2:$F$979*'Hours Log'!$AN$2:$AN$979)} -> 463.70003 | G6: {=SUMPRODUCT(('Hours Log'!$A$2:$A$979=$A6)*('Hours Log'!$B$2:$B$979=G$2)*('Hours Log'!$C$2:$C$979=LOOKUP(2,1/($A$1:G$1<>""),$A$1:G$1))*'Hours Log'!$F$2:$F$979*'Hours Log'!$AN$2:$AN$979)} -> 463.70003 | H6: {=SUMPRODUCT(('Hours Log'!$A$2:$A$979=$A6)*('Hours Log'!$B$2:$B$979=H$2)*('Hours Log'!$C$2:$C$979=LOOKUP(2,1/($A$1:H$1<>""),$A$1:H$1))*'Hours Log'!$F$2:$F$979*'Hours Log'!$AN$2:$AN$979)} -> 463.70003 | I6: {=SUMPRODUCT(('Hours Log'!$A$2:$A$979=$A6)*('Hours Log'!$B$2:$B$979=I$2)*('Hours Log'!$C$2:$C$979=LOOKUP(2,1/($A$1:I$1<>""),$A$1:I$1))*'Hours Log'!$F$2:$F$979*'Hours Log'!$AN$2:$AN$979)} -> 463.70003 | ... AH6: {=SUMPRODUCT(('Hours Log'!$A$2:$A$979=$A6)*('Hours Log'!$B$2:$B$979=AH$2)*('Hours Log'!$C$2:$C$979=LOOKUP(2,1/($A$1:AH$1<>""),$A$1:AH$1))*'Hours Log'!$F$2:$F$979*'Hours Log'!$AN$2:$AN$979)} -> 599.13
A7: Metzinger | B7: {=SUMPRODUCT(('Hours Log'!$A$2:$A$979=$A7)*('Hours Log'!$B$2:$B$979=B$2)*('Hours Log'!$C$2:$C$979=LOOKUP(2,1/($A$1:B$1<>""),$A$1:B$1))*'Hours Log'!$F$2:$F$979*'Hours Log'!$AN$2:$AN$979)} -> 317.30769 | C7: {=SUMPRODUCT(('Hours Log'!$A$2:$A$979=$A7)*('Hours Log'!$B$2:$B$979=C$2)*('Hours Log'!$C$2:$C$979=LOOKUP(2,1/($A$1:C$1<>""),$A$1:C$1))*'Hours Log'!$F$2:$F$979*'Hours Log'!$AN$2:$AN$979)} -> 317.30769 | D7: {=SUMPRODUCT(('Hours Log'!$A$2:$A$979=$A7)*('Hours Log'!$B$2:$B$979=D$2)*('Hours Log'!$C$2:$C$979=LOOKUP(2,1/($A$1:D$1<>""),$A$1:D$1))*'Hours Log'!$F$2:$F$979*'Hours Log'!$AN$2:$AN$979)} -> 317.30769 | E7: {=SUMPRODUCT(('Hours Log'!$A$2:$A$979=$A7)*('Hours Log'!$B$2:$B$979=E$2)*('Hours Log'!$C$2:$C$979=LOOKUP(2,1/($A$1:E$1<>""),$A$1:E$1))*'Hours Log'!$F$2:$F$979*'Hours Log'!$AN$2:$AN$979)} -> 317.30769 | F7: {=SUMPRODUCT(('Hours Log'!$A$2:$A$979=$A7)*('Hours Log'!$B$2:$B$979=F$2)*('Hours Log'!$C$2:$C$979=LOOKUP(2,1/($A$1:F$1<>""),$A$1:F$1))*'Hours Log'!$F$2:$F$979*'Hours Log'!$AN$2:$AN$979)} -> 317.30769 | G7: {=SUMPRODUCT(('Hours Log'!$A$2:$A$979=$A7)*('Hours Log'!$B$2:$B$979=G$2)*('Hours Log'!$C$2:$C$979=LOOKUP(2,1/($A$1:G$1<>""),$A$1:G$1))*'Hours Log'!$F$2:$F$979*'Hours Log'!$AN$2:$AN$979)} -> 317.30769 | H7: {=SUMPRODUCT(('Hours Log'!$A$2:$A$979=$A7)*('Hours Log'!$B$2:$B$979=H$2)*('Hours Log'!$C$2:$C$979=LOOKUP(2,1/($A$1:H$1<>""),$A$1:H$1))*'Hours Log'!$F$2:$F$979*'Hours Log'!$AN$2:$AN$979)} -> 317.30769 | I7: {=SUMPRODUCT(('Hours Log'!$A$2:$A$979=$A7)*('Hours Log'!$B$2:$B$979=I$2)*('Hours Log'!$C$2:$C$979=LOOKUP(2,1/($A$1:I$1<>""),$A$1:I$1))*'Hours Log'!$F$2:$F$979*'Hours Log'!$AN$2:$AN$979)} -> 317.30769 | ... AH7: {=SUMPRODUCT(('Hours Log'!$A$2:$A$979=$A7)*('Hours Log'!$B$2:$B$979=AH$2)*('Hours Log'!$C$2:$C$979=LOOKUP(2,1/($A$1:AH$1<>""),$A$1:AH$1))*'Hours Log'!$F$2:$F$979*'Hours Log'!$AN$2:$AN$979)} -> 389.42308
A8: Total Actual Labor | B8: =SUM(B3:B7) -> 8977.9408 | C8: =SUM(C3:C7) -> 9560.6159 | D8: =SUM(D3:D7) -> 8038.6169 | E8: =SUM(E3:E7) -> 7884.2157 | F8: =SUM(F3:F7) -> 6536.5423 | G8: =SUM(G3:G7) -> 4185.6791 | H8: =SUM(H3:H7) -> 7353.6739 | I8: =SUM(I3:I7) -> 7623.5593 | ... AH8: =SUM(AH3:AH7) -> 6295.1331
A9: Billed Labor | B9: 19168.47 | C9: 19168.47 | D9: 19168.47 | E9: 19168.47 | F9: 19168.47 | G9: 19168.47 | H9: 19168.47 | I9: 19168.47 | J9: 19168.47 | K9: 19168.47 | L9: 19168.47 | M9: 19168.47 | N9: 19168.47 | O9: 19168.47 | P9: 19168.47 | Q9: 19168.47 | R9: 19168.47 | S9: 19168.47 | T9: 19168.47 | U9: 19168.47 | V9: 19168.47 | W9: 19168.47 | X9: 19168.47 | Y9: 19168.47 | Z9: 1474 | AA9: 1374 | AB9: 1374 | AC9: 1374 | AD9: 1374 | AE9: 1374 | AF9: 1374 | AG9: 1374 | AH9: 1374
A10: Difference | B10: =B8-B9 -> -10190.529 | C10: =C8-C9 -> -9607.8541 | D10: =D8-D9 -> -11129.853 | E10: =E8-E9 -> -11284.254 | F10: =F8-F9 -> -12631.928 | G10: =G8-G9 -> -14982.791 | H10: =H8-H9 -> -11814.796 | I10: =I8-I9 -> -11544.911 | ... AH10: =AH8-AH9 -> 4921.1331
A12: Consultant
A13: Actual | B13: 1666.66 | C13: 1666.66 | D13: 1666.66 | E13: 1666.66 | F13: 1666.66 | G13: 1666.66 | H13: 1666.66 | I13: 1666.66 | J13: 1666.66 | K13: 1666.66 | L13: 1666.66 | M13: 1666.66 | N13: 1666.66 | O13: 1666.66 | P13: 1666.66 | Q13: 1666.66 | R13: 1666.66 | S13: 1666.66 | T13: 1666.66 | U13: 1666.66 | V13: 1666.66 | W13: 1666.66 | X13: 1666.66 | Y13: 1666.66
A14: Billed | B14: 1666.66 | C14: 1666.66 | D14: 1666.66 | E14: 1666.66 | F14: 1666.66 | G14: 1666.66 | H14: 1666.66 | I14: 1666.66 | J14: 1666.66 | K14: 1666.66 | L14: 1666.66 | M14: 1666.66 | N14: 1666.66 | O14: 1666.66 | P14: 1666.66 | Q14: 1666.66 | R14: 1666.66 | S14: 1666.66 | T14: 1666.66 | U14: 1666.66 | V14: 1666.66 | W14: 1666.66 | X14: 1666.66 | Y14: 1666.66
A15: Difference | B15: =B13-B14 -> 0 | C15: =C13-C14 -> 0 | D15: =D13-D14 -> 0 | E15: =E13-E14 -> 0 | F15: =F13-F14 -> 0 | G15: =G13-G14 -> 0 | H15: =H13-H14 -> 0 | I15: =I13-I14 -> 0 | ... Y15: =Y13-Y14 -> 0
A17: Travel
A18: Actual
A19: Billed | B19: 0 | C19: 0 | D19: 0 | E19: 0 | F19: 0 | G19: 0 | H19: 0 | I19: 0 | J19: 0 | K19: 0 | L19: 0 | M19: 0 | N19: 0 | O19: 0 | P19: 0 | Q19: 0 | R19: 0 | S19: 0 | T19: 0 | U19: 0 | V19: 0 | W19: 0 | X19: 0 | Y19: 0 | Z19: 0 | AA19: 0 | AB19: 0 | AC19: 0 | AD19: 0 | AE19: 0 | AF19: 0 | AG19: 0 | AH19: 0
A20: Difference
A22: ODCs
A23: Actual
A24: Billed | B24: 0 | C24: 0 | D24: 0 | E24: 0 | F24: 0 | G24: 0 | H24: 0 | I24: 0 | J24: 0 | K24: 0 | L24: 0 | M24: 0 | N24: 0 | O24: 0 | P24: 0 | Q24: 0 | R24: 0 | S24: 0 | T24: 0 | U24: 0 | V24: 0 | W24: 0 | X24: 0 | Y24: 0 | Z24: 0 | AA24: 0 | AB24: 0 | AC24: 0 | AD24: 0 | AE24: 0 | AF24: 0 | AG24: 0 | AH24: 0
A25: Difference
A27: Total Actual | B27: =B8+B13+B18+B23 -> 10644.601 | C27: =C8+C13+C18+C23 -> 11227.276 | D27: =D8+D13+D18+D23 -> 9705.2769 | E27: =E8+E13+E18+E23 -> 9550.8757 | F27: =F8+F13+F18+F23 -> 8203.2023 | G27: =G8+G13+G18+G23 -> 5852.3391 | H27: =H8+H13+H18+H23 -> 9020.3339 | I27: =I8+I13+I18+I23 -> 9290.2193 | ... AH27: =AH8+AH13+AH18+AH23 -> 6295.1331
A28: Total Billed | B28: =B9+B14+B19+B24 -> 20835.13 | C28: =C9+C14+C19+C24 -> 20835.13 | D28: =D9+D14+D19+D24 -> 20835.13 | E28: =E9+E14+E19+E24 -> 20835.13 | F28: =F9+F14+F19+F24 -> 20835.13 | G28: =G9+G14+G19+G24 -> 20835.13 | H28: =H9+H14+H19+H24 -> 20835.13 | I28: =I9+I14+I19+I24 -> 20835.13 | ... AH28: =AH9+AH14+AH19+AH24 -> 1374
A29: Difference | B29: =B27-B28 -> -10190.529 | C29: =C27-C28 -> -9607.8541 | D29: =D27-D28 -> -11129.853 | E29: =E27-E28 -> -11284.254 | F29: =F27-F28 -> -12631.928 | G29: =G27-G28 -> -14982.791 | H29: =H27-H28 -> -11814.796 | I29: =I27-I28 -> -11544.911 | ... AH29: =AH27-AH28 -> 4921.1331 | AI29: =SUM(B29:AH29) -> -258870.06
E30: =0.1*E28 -> 2083.513
A32: Indirects on all of it | E32: =E27*47.4% -> 4527.1151
E33: =E32*33 -> 149394.8

Sheet LTM
B1: 2024 | E1: 2025 | Q1: 2026
A2: Employee | B2: October | C2: November | D2: December | E2: January | F2: February | G2: March | H2: April | I2: May | J2: June | K2: July | L2: August | M2: September | N2: October | O2: November | P2: December | Q2: January | R2: February | S2: March | T2: April | U2: May | V2: June | W2: July
A3: Engel | B3: {=SUMPRODUCT(('Hours Log'!$A$2:$A$980=$A3)*('Hours Log'!$B$2:$B$980=B$2)*('Hours Log'!$C$2:$C$980=LOOKUP(2,1/($A$1:B$1<>""),$A$1:B$1))*'Hours Log'!$F$2:$F$980*'Hours Log'!$AP$2:$AP$980)} -> 3503.4971 | C3: {=SUMPRODUCT(('Hours Log'!$A$2:$A$980=$A3)*('Hours Log'!$B$2:$B$980=C$2)*('Hours Log'!$C$2:$C$980=LOOKUP(2,1/($A$1:C$1<>""),$A$1:C$1))*'Hours Log'!$F$2:$F$980*'Hours Log'!$AP$2:$AP$980)} -> 3134.6114 | D3: {=SUMPRODUCT(('Hours Log'!$A$2:$A$980=$A3)*('Hours Log'!$B$2:$B$980=D$2)*('Hours Log'!$C$2:$C$980=LOOKUP(2,1/($A$1:D$1<>""),$A$1:D$1))*'Hours Log'!$F$2:$F$980*'Hours Log'!$AP$2:$AP$980)} -> 3283.8786 | E3: {=SUMPRODUCT(('Hours Log'!$A$2:$A$980=$A3)*('Hours Log'!$B$2:$B$980=E$2)*('Hours Log'!$C$2:$C$980=LOOKUP(2,1/($A$1:E$1<>""),$A$1:E$1))*'Hours Log'!$F$2:$F$980*'Hours Log'!$AP$2:$AP$980)} -> 3769.9483 | F3: {=SUMPRODUCT(('Hours Log'!$A$2:$A$980=$A3)*('Hours Log'!$B$2:$B$980=F$2)*('Hours Log'!$C$2:$C$980=LOOKUP(2,1/($A$1:F$1<>""),$A$1:F$1))*'Hours Log'!$F$2:$F$980*'Hours Log'!$AP$2:$AP$980)} -> 3687.9929 | G3: {=SUMPRODUCT(('Hours Log'!$A$2:$A$980=$A3)*('Hours Log'!$B$2:$B$980=G$2)*('Hours Log'!$C$2:$C$980=LOOKUP(2,1/($A$1:G$1<>""),$A$1:G$1))*'Hours Log'!$F$2:$F$980*'Hours Log'!$AP$2:$AP$980)} -> 3442.1267 | H3: {=SUMPRODUCT(('Hours Log'!$A$2:$A$980=$A3)*('Hours Log'!$B$2:$B$980=H$2)*('Hours Log'!$C$2:$C$980=LOOKUP(2,1/($A$1:H$1<>""),$A$1:H$1))*'Hours Log'!$F$2:$F$980*'Hours Log'!$AP$2:$AP$980)} -> 3606.0375 | I3: {=SUMPRODUCT(('Hours Log'!$A$2:$A$980=$A3)*('Hours Log'!$B$2:$B$980=I$2)*('Hours Log'!$C$2:$C$980=LOOKUP(2,1/($A$1:I$1<>""),$A$1:I$1))*'Hours Log'!$F$2:$F$980*'Hours Log'!$AP$2:$AP$980)} -> 2912.5688 | ... W3: {=SUMPRODUCT(('Hours Log'!$A$2:$A$980=$A3)*('Hours Log'!$B$2:$B$980=W$2)*('Hours Log'!$C$2:$C$980=LOOKUP(2,1/($A$1:W$1<>""),$A$1:W$1))*'Hours Log'!$F$2:$F$980*'Hours Log'!$AP$2:$AP$980)} -> 8496.9909
A4: Jaric | B4: {=SUMPRODUCT(('Hours Log'!$A$2:$A$980=$A4)*('Hours Log'!$B$2:$B$980=B$2)*('Hours Log'!$C$2:$C$980=LOOKUP(2,1/($A$1:B$1<>""),$A$1:B$1))*'Hours Log'!$F$2:$F$980*'Hours Log'!$AP$2:$AP$980)} -> 0 | C4: {=SUMPRODUCT(('Hours Log'!$A$2:$A$980=$A4)*('Hours Log'!$B$2:$B$980=C$2)*('Hours Log'!$C$2:$C$980=LOOKUP(2,1/($A$1:C$1<>""),$A$1:C$1))*'Hours Log'!$F$2:$F$980*'Hours Log'!$AP$2:$AP$980)} -> 0 | D4: {=SUMPRODUCT(('Hours Log'!$A$2:$A$980=$A4)*('Hours Log'!$B$2:$B$980=D$2)*('Hours Log'!$C$2:$C$980=LOOKUP(2,1/($A$1:D$1<>""),$A$1:D$1))*'Hours Log'!$F$2:$F$980*'Hours Log'!$AP$2:$AP$980)} -> 0 | E4: {=SUMPRODUCT(('Hours Log'!$A$2:$A$980=$A4)*('Hours Log'!$B$2:$B$980=E$2)*('Hours Log'!$C$2:$C$980=LOOKUP(2,1/($A$1:E$1<>""),$A$1:E$1))*'Hours Log'!$F$2:$F$980*'Hours Log'!$AP$2:$AP$980)} -> 0 | F4: {=SUMPRODUCT(('Hours Log'!$A$2:$A$980=$A4)*('Hours Log'!$B$2:$B$980=F$2)*('Hours Log'!$C$2:$C$980=LOOKUP(2,1/($A$1:F$1<>""),$A$1:F$1))*'Hours Log'!$F$2:$F$980*'Hours Log'!$AP$2:$AP$980)} -> 716.93713 | G4: {=SUMPRODUCT(('Hours Log'!$A$2:$A$980=$A4)*('Hours Log'!$B$2:$B$980=G$2)*('Hours Log'!$C$2:$C$980=LOOKUP(2,1/($A$1:G$1<>""),$A$1:G$1))*'Hours Log'!$F$2:$F$980*'Hours Log'!$AP$2:$AP$980)} -> 991.03212 | H4: {=SUMPRODUCT(('Hours Log'!$A$2:$A$980=$A4)*('Hours Log'!$B$2:$B$980=H$2)*('Hours Log'!$C$2:$C$980=LOOKUP(2,1/($A$1:H$1<>""),$A$1:H$1))*'Hours Log'!$F$2:$F$980*'Hours Log'!$AP$2:$AP$980)} -> 1043.7761 | I4: {=SUMPRODUCT(('Hours Log'!$A$2:$A$980=$A4)*('Hours Log'!$B$2:$B$980=I$2)*('Hours Log'!$C$2:$C$980=LOOKUP(2,1/($A$1:I$1<>""),$A$1:I$1))*'Hours Log'!$F$2:$F$980*'Hours Log'!$AP$2:$AP$980)} -> 593.9653 | ... W4: {=SUMPRODUCT(('Hours Log'!$A$2:$A$980=$A4)*('Hours Log'!$B$2:$B$980=W$2)*('Hours Log'!$C$2:$C$980=LOOKUP(2,1/($A$1:W$1<>""),$A$1:W$1))*'Hours Log'!$F$2:$F$980*'Hours Log'!$AP$2:$AP$980)} -> 2523.8077
A5: Gaffney | B5: {=SUMPRODUCT(('Hours Log'!$A$2:$A$980=$A5)*('Hours Log'!$B$2:$B$980=B$2)*('Hours Log'!$C$2:$C$980=LOOKUP(2,1/($A$1:B$1<>""),$A$1:B$1))*'Hours Log'!$F$2:$F$980*'Hours Log'!$AP$2:$AP$980)} -> 0 | C5: {=SUMPRODUCT(('Hours Log'!$A$2:$A$980=$A5)*('Hours Log'!$B$2:$B$980=C$2)*('Hours Log'!$C$2:$C$980=LOOKUP(2,1/($A$1:C$1<>""),$A$1:C$1))*'Hours Log'!$F$2:$F$980*'Hours Log'!$AP$2:$AP$980)} -> 2554.2712 | D5: {=SUMPRODUCT(('Hours Log'!$A$2:$A$980=$A5)*('Hours Log'!$B$2:$B$980=D$2)*('Hours Log'!$C$2:$C$980=LOOKUP(2,1/($A$1:D$1<>""),$A$1:D$1))*'Hours Log'!$F$2:$F$980*'Hours Log'!$AP$2:$AP$980)} -> 2937.547 | E5: {=SUMPRODUCT(('Hours Log'!$A$2:$A$980=$A5)*('Hours Log'!$B$2:$B$980=E$2)*('Hours Log'!$C$2:$C$980=LOOKUP(2,1/($A$1:E$1<>""),$A$1:E$1))*'Hours Log'!$F$2:$F$980*'Hours Log'!$AP$2:$AP$980)} -> 478.70025 | F5: {=SUMPRODUCT(('Hours Log'!$A$2:$A$980=$A5)*('Hours Log'!$B$2:$B$980=F$2)*('Hours Log'!$C$2:$C$980=LOOKUP(2,1/($A$1:F$1<>""),$A$1:F$1))*'Hours Log'!$F$2:$F$980*'Hours Log'!$AP$2:$AP$980)} -> 471.89745 | G5: {=SUMPRODUCT(('Hours Log'!$A$2:$A$980=$A5)*('Hours Log'!$B$2:$B$980=G$2)*('Hours Log'!$C$2:$C$980=LOOKUP(2,1/($A$1:G$1<>""),$A$1:G$1))*'Hours Log'!$F$2:$F$980*'Hours Log'!$AP$2:$AP$980)} -> 1383.7192 | H5: {=SUMPRODUCT(('Hours Log'!$A$2:$A$980=$A5)*('Hours Log'!$B$2:$B$980=H$2)*('Hours Log'!$C$2:$C$980=LOOKUP(2,1/($A$1:H$1<>""),$A$1:H$1))*'Hours Log'!$F$2:$F$980*'Hours Log'!$AP$2:$AP$980)} -> 682.31387 | I5: {=SUMPRODUCT(('Hours Log'!$A$2:$A$980=$A5)*('Hours Log'!$B$2:$B$980=I$2)*('Hours Log'!$C$2:$C$980=LOOKUP(2,1/($A$1:I$1<>""),$A$1:I$1))*'Hours Log'!$F$2:$F$980*'Hours Log'!$AP$2:$AP$980)} -> 667.26836 | ... W5: {=SUMPRODUCT(('Hours Log'!$A$2:$A$980=$A5)*('Hours Log'!$B$2:$B$980=W$2)*('Hours Log'!$C$2:$C$980=LOOKUP(2,1/($A$1:W$1<>""),$A$1:W$1))*'Hours Log'!$F$2:$F$980*'Hours Log'!$AP$2:$AP$980)} -> 1169.855
A6: Negro | B6: {=SUMPRODUCT(('Hours Log'!$A$2:$A$980=$A6)*('Hours Log'!$B$2:$B$980=B$2)*('Hours Log'!$C$2:$C$980=LOOKUP(2,1/($A$1:B$1<>""),$A$1:B$1))*'Hours Log'!$F$2:$F$980*'Hours Log'!$AP$2:$AP$980)} -> 0 | C6: {=SUMPRODUCT(('Hours Log'!$A$2:$A$980=$A6)*('Hours Log'!$B$2:$B$980=C$2)*('Hours Log'!$C$2:$C$980=LOOKUP(2,1/($A$1:C$1<>""),$A$1:C$1))*'Hours Log'!$F$2:$F$980*'Hours Log'!$AP$2:$AP$980)} -> 0 | D6: {=SUMPRODUCT(('Hours Log'!$A$2:$A$980=$A6)*('Hours Log'!$B$2:$B$980=D$2)*('Hours Log'!$C$2:$C$980=LOOKUP(2,1/($A$1:D$1<>""),$A$1:D$1))*'Hours Log'!$F$2:$F$980*'Hours Log'!$AP$2:$AP$980)} -> 0 | E6: {=SUMPRODUCT(('Hours Log'!$A$2:$A$980=$A6)*('Hours Log'!$B$2:$B$980=E$2)*('Hours Log'!$C$2:$C$980=LOOKUP(2,1/($A$1:E$1<>""),$A$1:E$1))*'Hours Log'!$F$2:$F$980*'Hours Log'!$AP$2:$AP$980)} -> 0 | F6: {=SUMPRODUCT(('Hours Log'!$A$2:$A$980=$A6)*('Hours Log'!$B$2:$B$980=F$2)*('Hours Log'!$C$2:$C$980=LOOKUP(2,1/($A$1:F$1<>""),$A$1:F$1))*'Hours Log'!$F$2:$F$980*'Hours Log'!$AP$2:$AP$980)} -> 0 | G6: {=SUMPRODUCT(('Hours Log'!$A$2:$A$980=$A6)*('Hours Log'!$B$2:$B$980=G$2)*('Hours Log'!$C$2:$C$980=LOOKUP(2,1/($A$1:G$1<>""),$A$1:G$1))*'Hours Log'!$F$2:$F$980*'Hours Log'!$AP$2:$AP$980)} -> 0 | H6: {=SUMPRODUCT(('Hours Log'!$A$2:$A$980=$A6)*('Hours Log'!$B$2:$B$980=H$2)*('Hours Log'!$C$2:$C$980=LOOKUP(2,1/($A$1:H$1<>""),$A$1:H$1))*'Hours Log'!$F$2:$F$980*'Hours Log'!$AP$2:$AP$980)} -> 0 | I6: {=SUMPRODUCT(('Hours Log'!$A$2:$A$980=$A6)*('Hours Log'!$B$2:$B$980=I$2)*('Hours Log'!$C$2:$C$980=LOOKUP(2,1/($A$1:I$1<>""),$A$1:I$1))*'Hours Log'!$F$2:$F$980*'Hours Log'!$AP$2:$AP$980)} -> 0 | ... W6: {=SUMPRODUCT(('Hours Log'!$A$2:$A$980=$A6)*('Hours Log'!$B$2:$B$980=W$2)*('Hours Log'!$C$2:$C$980=LOOKUP(2,1/($A$1:W$1<>""),$A$1:W$1))*'Hours Log'!$F$2:$F$980*'Hours Log'!$AP$2:$AP$980)} -> 1954.6085
A7: Sprowl | B7: {=SUMPRODUCT(('Hours Log'!$A$2:$A$980=$A7)*('Hours Log'!$B$2:$B$980=B$2)*('Hours Log'!$C$2:$C$980=LOOKUP(2,1/($A$1:B$1<>""),$A$1:B$1))*'Hours Log'!$F$2:$F$980*'Hours Log'!$AP$2:$AP$980)} -> 122.58843 | C7: {=SUMPRODUCT(('Hours Log'!$A$2:$A$980=$A7)*('Hours Log'!$B$2:$B$980=C$2)*('Hours Log'!$C$2:$C$980=LOOKUP(2,1/($A$1:C$1<>""),$A$1:C$1))*'Hours Log'!$F$2:$F$980*'Hours Log'!$AP$2:$AP$980)} -> 0 | D7: {=SUMPRODUCT(('Hours Log'!$A$2:$A$980=$A7)*('Hours Log'!$B$2:$B$980=D$2)*('Hours Log'!$C$2:$C$980=LOOKUP(2,1/($A$1:D$1<>""),$A$1:D$1))*'Hours Log'!$F$2:$F$980*'Hours Log'!$AP$2:$AP$980)} -> 102.15702 | E7: {=SUMPRODUCT(('Hours Log'!$A$2:$A$980=$A7)*('Hours Log'!$B$2:$B$980=E$2)*('Hours Log'!$C$2:$C$980=LOOKUP(2,1/($A$1:E$1<>""),$A$1:E$1))*'Hours Log'!$F$2:$F$980*'Hours Log'!$AP$2:$AP$980)} -> 160.0074 | F7: {=SUMPRODUCT(('Hours Log'!$A$2:$A$980=$A7)*('Hours Log'!$B$2:$B$980=F$2)*('Hours Log'!$C$2:$C$980=LOOKUP(2,1/($A$1:F$1<>""),$A$1:F$1))*'Hours Log'!$F$2:$F$980*'Hours Log'!$AP$2:$AP$980)} -> 539.76782 | G7: {=SUMPRODUCT(('Hours Log'!$A$2:$A$980=$A7)*('Hours Log'!$B$2:$B$980=G$2)*('Hours Log'!$C$2:$C$980=LOOKUP(2,1/($A$1:G$1<>""),$A$1:G$1))*'Hours Log'!$F$2:$F$980*'Hours Log'!$AP$2:$AP$980)} -> 38.919628 | H7: {=SUMPRODUCT(('Hours Log'!$A$2:$A$980=$A7)*('Hours Log'!$B$2:$B$980=H$2)*('Hours Log'!$C$2:$C$980=LOOKUP(2,1/($A$1:H$1<>""),$A$1:H$1))*'Hours Log'!$F$2:$F$980*'Hours Log'!$AP$2:$AP$980)} -> 38.632722 | I7: {=SUMPRODUCT(('Hours Log'!$A$2:$A$980=$A7)*('Hours Log'!$B$2:$B$980=I$2)*('Hours Log'!$C$2:$C$980=LOOKUP(2,1/($A$1:I$1<>""),$A$1:I$1))*'Hours Log'!$F$2:$F$980*'Hours Log'!$AP$2:$AP$980)} -> 272.64036 | ... W7: {=SUMPRODUCT(('Hours Log'!$A$2:$A$980=$A7)*('Hours Log'!$B$2:$B$980=W$2)*('Hours Log'!$C$2:$C$980=LOOKUP(2,1/($A$1:W$1<>""),$A$1:W$1))*'Hours Log'!$F$2:$F$980*'Hours Log'!$AP$2:$AP$980)} -> 160.18406
A10: Total Actual Labor | B10: =SUM(B3:B7) -> 3626.0856 | C10: =SUM(C3:C7) -> 5688.8826 | D10: =SUM(D3:D7) -> 6323.5826 | E10: =SUM(E3:E7) -> 4408.6559 | F10: =SUM(F3:F7) -> 5416.5953 | G10: =SUM(G3:G7) -> 5855.7976 | H10: =SUM(H3:H7) -> 5370.7602 | I10: =SUM(I3:I7) -> 4446.4428 | ... W10: =SUM(W3:W7) -> 14305.446
A11: Billed Labor | B11: 7493.52 | C11: 7493.52 | D11: 7493.52 | E11: 7493.52 | F11: 7493.52 | G11: 7493.52 | H11: 7493.52 | I11: 7493.52 | J11: 7493.52 | K11: 7493.52 | L11: 7493.52 | M11: 7493.52 | N11: 7493.52 | O11: 7493.52 | P11: 7493.52 | Q11: 7493.52 | R11: 7493.52 | S11: 7493.52 | T11: 7493.52 | U11: 7493.52 | V11: 7493.52 | W11: 7493.52
A12: Difference | B12: =B10-B11 -> -3867.4344 | C12: =C10-C11 -> -1804.6374 | D12: =D10-D11 -> -1169.9374 | E12: =E10-E11 -> -3084.8641 | F12: =F10-F11 -> -2076.9247 | G12: =G10-G11 -> -1637.7224 | H12: =H10-H11 -> -2122.7598 | I12: =I10-I11 -> -3047.0772 | ... W12: =W10-W11 -> 6811.9262 | X12: =SUM(B12:W12) -> -22577.237

Sheet Rising Tides
B1: 2024 | E1: 2025 | Q1: 2026
A2: Employee | B2: October | C2: November | D2: December | E2: January | F2: February | G2: March | H2: April | I2: May | J2: June | K2: July | L2: August | M2: September | N2: October | O2: November | P2: December | Q2: January | R2: February | S2: March | T2: April | U2: May | V2: June | W2: July | X2: August | Y2: COST SHARE BACK-OUT | Z2: TOTAL | AA2: BILLED TO AUGUST | AB2: Diff
A3: Longo | B3: {=SUMPRODUCT(('Hours Log'!$A$2:$A$980=$A3)*('Hours Log'!$B$2:$B$980=B$2)*('Hours Log'!$C$2:$C$980=LOOKUP(2,1/($A$1:B$1<>""),$A$1:B$1))*'Hours Log'!$D$2:$D$980*'Hours Log'!$AS$2:$AS$980)} -> 1074.5653 | C3: {=SUMPRODUCT(('Hours Log'!$A$2:$A$980=$A3)*('Hours Log'!$B$2:$B$980=C$2)*('Hours Log'!$C$2:$C$980=LOOKUP(2,1/($A$1:C$1<>""),$A$1:C$1))*'Hours Log'!$D$2:$D$980*'Hours Log'!$AS$2:$AS$980)} -> 1547.374 | D3: {=SUMPRODUCT(('Hours Log'!$A$2:$A$980=$A3)*('Hours Log'!$B$2:$B$980=D$2)*('Hours Log'!$C$2:$C$980=LOOKUP(2,1/($A$1:D$1<>""),$A$1:D$1))*'Hours Log'!$D$2:$D$980*'Hours Log'!$AS$2:$AS$980)} -> 1504.3914 | E3: {=SUMPRODUCT(('Hours Log'!$A$2:$A$980=$A3)*('Hours Log'!$B$2:$B$980=E$2)*('Hours Log'!$C$2:$C$980=LOOKUP(2,1/($A$1:E$1<>""),$A$1:E$1))*'Hours Log'!$D$2:$D$980*'Hours Log'!$AS$2:$AS$980)} -> 2855.45 | F3: {=SUMPRODUCT(('Hours Log'!$A$2:$A$980=$A3)*('Hours Log'!$B$2:$B$980=F$2)*('Hours Log'!$C$2:$C$980=LOOKUP(2,1/($A$1:F$1<>""),$A$1:F$1))*'Hours Log'!$D$2:$D$980*'Hours Log'!$AS$2:$AS$980)} -> 3250.82 | G3: {=SUMPRODUCT(('Hours Log'!$A$2:$A$980=$A3)*('Hours Log'!$B$2:$B$980=G$2)*('Hours Log'!$C$2:$C$980=LOOKUP(2,1/($A$1:G$1<>""),$A$1:G$1))*'Hours Log'!$D$2:$D$980*'Hours Log'!$AS$2:$AS$980)} -> 3602.26 | H3: {=SUMPRODUCT(('Hours Log'!$A$2:$A$980=$A3)*('Hours Log'!$B$2:$B$980=H$2)*('Hours Log'!$C$2:$C$980=LOOKUP(2,1/($A$1:H$1<>""),$A$1:H$1))*'Hours Log'!$D$2:$D$980*'Hours Log'!$AS$2:$AS$980)} -> 3534.4823 | I3: {=SUMPRODUCT(('Hours Log'!$A$2:$A$980=$A3)*('Hours Log'!$B$2:$B$980=I$2)*('Hours Log'!$C$2:$C$980=LOOKUP(2,1/($A$1:I$1<>""),$A$1:I$1))*'Hours Log'!$D$2:$D$980*'Hours Log'!$AS$2:$AS$980)} -> 3694.0249 | ... X3: {=SUMPRODUCT(('Hours Log'!$A$2:$A$980=$A3)*('Hours Log'!$B$2:$B$980=X$2)*('Hours Log'!$C$2:$C$980=LOOKUP(2,1/($A$1:X$1<>""),$A$1:X$1))*'Hours Log'!$D$2:$D$980*'Hours Log'!$AS$2:$AS$980)} -> 8123.0769 | Y3: -9583.18 | Z3: =SUM(B3:Y3) -> 91532.217 | AA3: 81458.18 | AB3: =AA3-Z3 -> -10074.037
A4: Gaffney | B4: {=SUMPRODUCT(('Hours Log'!$A$2:$A$980=$A4)*('Hours Log'!$B$2:$B$980=B$2)*('Hours Log'!$C$2:$C$980=LOOKUP(2,1/($A$1:B$1<>""),$A$1:B$1))*'Hours Log'!$D$2:$D$980*'Hours Log'!$AS$2:$AS$980)} -> 0 | C4: {=SUMPRODUCT(('Hours Log'!$A$2:$A$980=$A4)*('Hours Log'!$B$2:$B$980=C$2)*('Hours Log'!$C$2:$C$980=LOOKUP(2,1/($A$1:C$1<>""),$A$1:C$1))*'Hours Log'!$D$2:$D$980*'Hours Log'!$AS$2:$AS$980)} -> 2144.1041 | D4: {=SUMPRODUCT(('Hours Log'!$A$2:$A$980=$A4)*('Hours Log'!$B$2:$B$980=D$2)*('Hours Log'!$C$2:$C$980=LOOKUP(2,1/($A$1:D$1<>""),$A$1:D$1))*'Hours Log'!$D$2:$D$980*'Hours Log'!$AS$2:$AS$980)} -> 2370.9934 | E4: {=SUMPRODUCT(('Hours Log'!$A$2:$A$980=$A4)*('Hours Log'!$B$2:$B$980=E$2)*('Hours Log'!$C$2:$C$980=LOOKUP(2,1/($A$1:E$1<>""),$A$1:E$1))*'Hours Log'!$D$2:$D$980*'Hours Log'!$AS$2:$AS$980)} -> 2117.5661 | F4: {=SUMPRODUCT(('Hours Log'!$A$2:$A$980=$A4)*('Hours Log'!$B$2:$B$980=F$2)*('Hours Log'!$C$2:$C$980=LOOKUP(2,1/($A$1:F$1<>""),$A$1:F$1))*'Hours Log'!$D$2:$D$980*'Hours Log'!$AS$2:$AS$980)} -> 1926.8985 | G4: {=SUMPRODUCT(('Hours Log'!$A$2:$A$980=$A4)*('Hours Log'!$B$2:$B$980=G$2)*('Hours Log'!$C$2:$C$980=LOOKUP(2,1/($A$1:G$1<>""),$A$1:G$1))*'Hours Log'!$D$2:$D$980*'Hours Log'!$AS$2:$AS$980)} -> 1728.278 | H4: {=SUMPRODUCT(('Hours Log'!$A$2:$A$980=$A4)*('Hours Log'!$B$2:$B$980=H$2)*('Hours Log'!$C$2:$C$980=LOOKUP(2,1/($A$1:H$1<>""),$A$1:H$1))*'Hours Log'!$D$2:$D$980*'Hours Log'!$AS$2:$AS$980)} -> 1802.7653 | I4: {=SUMPRODUCT(('Hours Log'!$A$2:$A$980=$A4)*('Hours Log'!$B$2:$B$980=I$2)*('Hours Log'!$C$2:$C$980=LOOKUP(2,1/($A$1:I$1<>""),$A$1:I$1))*'Hours Log'!$D$2:$D$980*'Hours Log'!$AS$2:$AS$980)} -> 1987.3965 | ... X4: {=SUMPRODUCT(('Hours Log'!$A$2:$A$980=$A4)*('Hours Log'!$B$2:$B$980=X$2)*('Hours Log'!$C$2:$C$980=LOOKUP(2,1/($A$1:X$1<>""),$A$1:X$1))*'Hours Log'!$D$2:$D$980*'Hours Log'!$AS$2:$AS$980)} -> 0 | Z4: =SUM(B4:Y4) -> 41566.58 | AA4: 62291.59 | AB4: =AA4-Z4 -> 20725.01
A5: Negro | B5: {=SUMPRODUCT(('Hours Log'!$A$2:$A$980=$A5)*('Hours Log'!$B$2:$B$980=B$2)*('Hours Log'!$C$2:$C$980=LOOKUP(2,1/($A$1:B$1<>""),$A$1:B$1))*'Hours Log'!$D$2:$D$980*'Hours Log'!$AS$2:$AS$980)} -> 263.23965 | C5: {=SUMPRODUCT(('Hours Log'!$A$2:$A$980=$A5)*('Hours Log'!$B$2:$B$980=C$2)*('Hours Log'!$C$2:$C$980=LOOKUP(2,1/($A$1:C$1<>""),$A$1:C$1))*'Hours Log'!$D$2:$D$980*'Hours Log'!$AS$2:$AS$980)} -> 460.66939 | D5: {=SUMPRODUCT(('Hours Log'!$A$2:$A$980=$A5)*('Hours Log'!$B$2:$B$980=D$2)*('Hours Log'!$C$2:$C$980=LOOKUP(2,1/($A$1:D$1<>""),$A$1:D$1))*'Hours Log'!$D$2:$D$980*'Hours Log'!$AS$2:$AS$980)} -> 394.85948 | E5: {=SUMPRODUCT(('Hours Log'!$A$2:$A$980=$A5)*('Hours Log'!$B$2:$B$980=E$2)*('Hours Log'!$C$2:$C$980=LOOKUP(2,1/($A$1:E$1<>""),$A$1:E$1))*'Hours Log'!$D$2:$D$980*'Hours Log'!$AS$2:$AS$980)} -> 767.12328 | F5: {=SUMPRODUCT(('Hours Log'!$A$2:$A$980=$A5)*('Hours Log'!$B$2:$B$980=F$2)*('Hours Log'!$C$2:$C$980=LOOKUP(2,1/($A$1:F$1<>""),$A$1:F$1))*'Hours Log'!$D$2:$D$980*'Hours Log'!$AS$2:$AS$980)} -> 1540.9172 | G5: {=SUMPRODUCT(('Hours Log'!$A$2:$A$980=$A5)*('Hours Log'!$B$2:$B$980=G$2)*('Hours Log'!$C$2:$C$980=LOOKUP(2,1/($A$1:G$1<>""),$A$1:G$1))*'Hours Log'!$D$2:$D$980*'Hours Log'!$AS$2:$AS$980)} -> 1540.9172 | H5: {=SUMPRODUCT(('Hours Log'!$A$2:$A$980=$A5)*('Hours Log'!$B$2:$B$980=H$2)*('Hours Log'!$C$2:$C$980=LOOKUP(2,1/($A$1:H$1<>""),$A$1:H$1))*'Hours Log'!$D$2:$D$980*'Hours Log'!$AS$2:$AS$980)} -> 1557.3191 | I5: {=SUMPRODUCT(('Hours Log'!$A$2:$A$980=$A5)*('Hours Log'!$B$2:$B$980=I$2)*('Hours Log'!$C$2:$C$980=LOOKUP(2,1/($A$1:I$1<>""),$A$1:I$1))*'Hours Log'!$D$2:$D$980*'Hours Log'!$AS$2:$AS$980)} -> 2494.8183 | ... X5: {=SUMPRODUCT(('Hours Log'!$A$2:$A$980=$A5)*('Hours Log'!$B$2:$B$980=X$2)*('Hours Log'!$C$2:$C$980=LOOKUP(2,1/($A$1:X$1<>""),$A$1:X$1))*'Hours Log'!$D$2:$D$980*'Hours Log'!$AS$2:$AS$980)} -> 3384.6154 | Z5: =SUM(B5:Y5) -> 33945.579 | AA5: 28750 | AB5: =AA5-Z5 -> -5195.5792
